Workbook
Name Вид_изделия: Диапазоны!$C$2:$C$7
Name Название: Рецепты[Название]
Name Название_ингредиента: Ингредиенты!$A$2:$A$1048576
Name Рецепты_для_Москит: Диапазоны!$K$25
Name Способ_приготовления: Диапазоны!$E$2:$E$1048576
Name Срез_Вид: #N/A
Name Срез_Вид1: #N/A
Name Срез_Вид2: #N/A
Name Срез_Где_покупать: #N/A
Name Срез_Название: #N/A
Name Срез_Название1: #N/A
Name Срез_Наличие: #N/A
Name Срез_Способ: #N/A
Name Срез_Способ1: #N/A
Name Срез_Способ2: #N/A
Name Срез_Сырье: #N/A
Name Сырье: Диапазоны!$A$2:$A$1048576

Sheet Диапазоны
A1: Сырье | C1: Вид изделия | E1: Способ приготовления | F1: Потери | G1: Маржа | J1: ГК | K1: ХК
A2: Баранина | C2: Колбаса | E2: Вареное | F2: 0.15 | G2: 0.7 | J2: Сушка при +20 до потери веса 10% | K2: Солим
A3: Говядина | C3: Рыба | E3: ГК | F3: 0.15 | G3: 0.9 | J3: Отепление при +35 до +22 внутри | K3: ...Вымачиваем...
A4: Добавки | C4: Цельное | E4: Соленое | F4: 0.05 | G4: 0.5 | J4: Сушка при +60 до +40 внутри | K4: Сушка при +20 до потери веса 10%
A5: Оболочка | C5: Сосиски | E5: Сырокопченое | F5: 0.35 | G5: 2 | J5: Коптим без статики при +80 в течение 1 часа | K5: Копчение при +20 с электростатикой 1 час
A6: Птица | C6: Сыр | E6: Сыровяленное | F6: 0.35 | G6: 2 | J6: Варка при +90 - +110 до +70 внутри | K6: В холодильник на сутки
A7: Рыба | C7: Еда | E7: ХК | F7: 0.15 | G7: 1 | J7: Душируем в ледяной воде до +20 внутри
A8: Свинина | E8: Провесная | F8: 0.1 | G8: 0.9
A9: Специи | E9: Сыр | F9: 0.92 | G9: 3
E10: Еда | F10: 0.05 | G10: 0.5
K25: Рецепты для Москит от Строгой

Sheet Ингредиенты
A1: Название ингредиента | B1: Сырье | C1: Цена | D1: Тип сырья | E1: Где покупать | F1: Ссылка | G1: Обьем | H1: Цена/Обьем | I1: Наличие | J1: Выход
A2: Карбонад свиной | B2: Свинина | C2: =IFERROR(IF(Ингредиенты[[#This Row],[Выход]]<>"",(Ингредиенты[[#This Row],[Цена/Обьем]]/Ингредиенты[[#This Row],[Обьем]]*100%/Ингредиенты[[#This Row],[Выход]]),Ингредиенты[[#This Row],[Цена/Обьем]]/Ингредиенты[[#This Row],[Обьем]]),"") -> 0.39999 | D2: Основа | E2: Европа | G2: 1000 | H2: 399.99 | I2: Нет
A3: Окорок свиной | B3: Свинина | C3: =IFERROR(IF(Ингредиенты[[#This Row],[Выход]]<>"",(Ингредиенты[[#This Row],[Цена/Обьем]]/Ингредиенты[[#This Row],[Обьем]]*100%/Ингредиенты[[#This Row],[Выход]]),Ингредиенты[[#This Row],[Цена/Обьем]]/Ингредиенты[[#This Row],[Обьем]]),"") -> 0.369 | D3: Основа | E3: Обуховский | G3: 1000 | H3: 369 | I3: Да
A4: Лопатка свиная | B4: Свинина | C4: =IFERROR(IF(Ингредиенты[[#This Row],[Выход]]<>"",(Ингредиенты[[#This Row],[Цена/Обьем]]/Ингредиенты[[#This Row],[Обьем]]*100%/Ингредиенты[[#This Row],[Выход]]),Ингредиенты[[#This Row],[Цена/Обьем]]/Ингредиенты[[#This Row],[Обьем]]),"") -> 0.369 | D4: Основа | E4: Европа | G4: 1000 | H4: 369 | I4: Нет
A5: Шея свиная | B5: Свинина | C5: =IFERROR(IF(Ингредиенты[[#This Row],[Выход]]<>"",(Ингредиенты[[#This Row],[Цена/Обьем]]/Ингредиенты[[#This Row],[Обьем]]*100%/Ингредиенты[[#This Row],[Выход]]),Ингредиенты[[#This Row],[Цена/Обьем]]/Ингредиенты[[#This Row],[Обьем]]),"") -> 0.58 | D5: Основа | E5: Европа | G5: 1000 | H5: 580 | I5: Нет
A6: Грудинка свиная | B6: Свинина | C6: =IFERROR(IF(Ингредиенты[[#This Row],[Выход]]<>"",(Ингредиенты[[#This Row],[Цена/Обьем]]/Ингредиенты[[#This Row],[Обьем]]*100%/Ингредиенты[[#This Row],[Выход]]),Ингредиенты[[#This Row],[Цена/Обьем]]/Ингредиенты[[#This Row],[Обьем]]),"") -> 0.42999 | D6: Основа | E6: Европа | G6: 1000 | H6: 429.99 | I6: Нет
A7: Ребра свиные | B7: Свинина | C7: =IFERROR(IF(Ингредиенты[[#This Row],[Выход]]<>"",(Ингредиенты[[#This Row],[Цена/Обьем]]/Ингредиенты[[#This Row],[Обьем]]*100%/Ингредиенты[[#This Row],[Выход]]),Ингредиенты[[#This Row],[Цена/Обьем]]/Ингредиенты[[#This Row],[Обьем]]),"") -> 0.28999 | D7: Основа | E7: Европа | F7: Грудинка свиная б/к с/ш, собственное производство - купить онлайн с доставкой по цене 429.99 в интернет-магазине ЕВРОПА | G7: 1000 | H7: 289.99 | I7: Нет
A8: Рулька свиная | B8: Свинина | C8: =IFERROR(IF(Ингредиенты[[#This Row],[Выход]]<>"",(Ингредиенты[[#This Row],[Цена/Обьем]]/Ингредиенты[[#This Row],[Обьем]]*100%/Ингредиенты[[#This Row],[Выход]]),Ингредиенты[[#This Row],[Цена/Обьем]]/Ингредиенты[[#This Row],[Обьем]]),"") -> 0.27999 | D8: Основа | E8: Европа | F8: Свинина рулька собственное производство - купить онлайн с доставкой по цене 239.99 в интернет-магазине ЕВРОПА | G8: 1000 | H8: 279.99 | I8: Нет
A9: Сало свиное | B9: Свинина | C9: =IFERROR(IF(Ингредиенты[[#This Row],[Выход]]<>"",(Ингредиенты[[#This Row],[Цена/Обьем]]/Ингредиенты[[#This Row],[Обьем]]*100%/Ингредиенты[[#This Row],[Выход]]),Ингредиенты[[#This Row],[Цена/Обьем]]/Ингредиенты[[#This Row],[Обьем]]),"") -> 0.3 | D9: Основа | E9: Авито | G9: 1000 | H9: 300 | I9: Да
A10: Шпик | B10: Свинина | C10: =IFERROR(IF(Ингредиенты[[#This Row],[Выход]]<>"",(Ингредиенты[[#This Row],[Цена/Обьем]]/Ингредиенты[[#This Row],[Обьем]]*100%/Ингредиенты[[#This Row],[Выход]]),Ингредиенты[[#This Row],[Цена/Обьем]]/Ингредиенты[[#This Row],[Обьем]]),"") -> 0.3 | D10: Основа | E10: Авито | G10: 1000 | H10: 300 | I10: Нет
A11: Швартенблок | B11: Свинина | C11: =IFERROR(IF(Ингредиенты[[#This Row],[Выход]]<>"",(Ингредиенты[[#This Row],[Цена/Обьем]]/Ингредиенты[[#This Row],[Обьем]]*100%/Ингредиенты[[#This Row],[Выход]]),Ингредиенты[[#This Row],[Цена/Обьем]]/Ингредиенты[[#This Row],[Обьем]]),"") -> 0.3 | D11: Основа | E11: Сам делаю | G11: 1000 | H11: 300 | I11: Нет
A12: Шкуры, голова, обрезь | B12: Свинина | C12: =IFERROR(IF(Ингредиенты[[#This Row],[Выход]]<>"",(Ингредиенты[[#This Row],[Цена/Обьем]]/Ингредиенты[[#This Row],[Обьем]]*100%/Ингредиенты[[#This Row],[Выход]]),Ингредиенты[[#This Row],[Цена/Обьем]]/Ингредиенты[[#This Row],[Обьем]]),"") -> 0.1 | D12: Основа | E12: Сам делаю | G12: 1000 | H12: 100 | I12: Да
A13: Говядина | B13: Говядина | C13: =IFERROR(IF(Ингредиенты[[#This Row],[Выход]]<>"",(Ингредиенты[[#This Row],[Цена/Обьем]]/Ингредиенты[[#This Row],[Обьем]]*100%/Ингредиенты[[#This Row],[Выход]]),Ингредиенты[[#This Row],[Цена/Обьем]]/Ингредиенты[[#This Row],[Обьем]]),"") -> 0.70999 | D13: Основа | E13: Европа | G13: 1000 | H13: 709.99 | I13: Да
A14: Язык говяжий | B14: Говядина | C14: =IFERROR(IF(Ингредиенты[[#This Row],[Выход]]<>"",(Ингредиенты[[#This Row],[Цена/Обьем]]/Ингредиенты[[#This Row],[Обьем]]*100%/Ингредиенты[[#This Row],[Выход]]),Ингредиенты[[#This Row],[Цена/Обьем]]/Ингредиенты[[#This Row],[Обьем]]),"") -> 1.09999 | D14: Основа | E14: Европа | G14: 1000 | H14: 1099.99 | I14: Нет
A15: Жир говяжий | B15: Говядина | C15: =IFERROR(IF(Ингредиенты[[#This Row],[Выход]]<>"",(Ингредиенты[[#This Row],[Цена/Обьем]]/Ингредиенты[[#This Row],[Обьем]]*100%/Ингредиенты[[#This Row],[Выход]]),Ингредиенты[[#This Row],[Цена/Обьем]]/Ингредиенты[[#This Row],[Обьем]]),"") -> 0.25 | D15: Основа | E15: Обрезки | G15: 1000 | H15: 250 | I15: Нет
A16: Баранина | B16: Баранина | C16: =IFERROR(IF(Ингредиенты[[#This Row],[Выход]]<>"",(Ингредиенты[[#This Row],[Цена/Обьем]]/Ингредиенты[[#This Row],[Обьем]]*100%/Ингредиенты[[#This Row],[Выход]]),Ингредиенты[[#This Row],[Цена/Обьем]]/Ингредиенты[[#This Row],[Обьем]]),"") -> 0.70588235 | D16: Основа | E16: Авито | G16: 1000 | H16: 480 | I16: Нет | J16: 0.68
A17: Гусь | B17: Птица | C17: =IFERROR(IF(Ингредиенты[[#This Row],[Выход]]<>"",(Ингредиенты[[#This Row],[Цена/Обьем]]/Ингредиенты[[#This Row],[Обьем]]*100%/Ингредиенты[[#This Row],[Выход]]),Ингредиенты[[#This Row],[Цена/Обьем]]/Ингредиенты[[#This Row],[Обьем]]),"") -> 0.9 | D17: Основа | G17: 1000 | H17: 900
A18: Курица целая | B18: Птица | C18: =IFERROR(IF(Ингредиенты[[#This Row],[Выход]]<>"",(Ингредиенты[[#This Row],[Цена/Обьем]]/Ингредиенты[[#This Row],[Обьем]]*100%/Ингредиенты[[#This Row],[Выход]]),Ингредиенты[[#This Row],[Цена/Обьем]]/Ингредиенты[[#This Row],[Обьем]]),"") -> 0.2 | D18: Основа | E18: Европа | F18: Тушка ц/б 1 кат охл - купить онлайн с доставкой по цене 179.99 в интернет-магазине ЕВРОПА | G18: 1000 | H18: 200 | I18: Да
A19: Грудка куриная | B19: Птица | C19: =IFERROR(IF(Ингредиенты[[#This Row],[Выход]]<>"",(Ингредиенты[[#This Row],[Цена/Обьем]]/Ингредиенты[[#This Row],[Обьем]]*100%/Ингредиенты[[#This Row],[Выход]]),Ингредиенты[[#This Row],[Цена/Обьем]]/Ингредиенты[[#This Row],[Обьем]]),"") -> 0.27999 | D19: Основа | E19: Европа | G19: 1000 | H19: 279.99 | I19: Нет
A20: Бедра куриные | B20: Птица | C20: =IFERROR(IF(Ингредиенты[[#This Row],[Выход]]<>"",(Ингредиенты[[#This Row],[Цена/Обьем]]/Ингредиенты[[#This Row],[Обьем]]*100%/Ингредиенты[[#This Row],[Выход]]),Ингредиенты[[#This Row],[Цена/Обьем]]/Ингредиенты[[#This Row],[Обьем]]),"") -> 0.26117647 | D20: Основа | E20: Европа | G20: 1000 | H20: 222 | I20: Нет | J20: 0.85
A21: Индейка | B21: Птица | C21: =IFERROR(IF(Ингредиенты[[#This Row],[Выход]]<>"",(Ингредиенты[[#This Row],[Цена/Обьем]]/Ингредиенты[[#This Row],[Обьем]]*100%/Ингредиенты[[#This Row],[Выход]]),Ингредиенты[[#This Row],[Цена/Обьем]]/Ингредиенты[[#This Row],[Обьем]]),"") -> 0.56999 | D21: Основа | E21: Европа | G21: 1000 | H21: 569.99 | I21: Нет
A22: Скумбрия | B22: Рыба | C22: =IFERROR(IF(Ингредиенты[[#This Row],[Выход]]<>"",(Ингредиенты[[#This Row],[Цена/Обьем]]/Ингредиенты[[#This Row],[Обьем]]*100%/Ингредиенты[[#This Row],[Выход]]),Ингредиенты[[#This Row],[Цена/Обьем]]/Ингредиенты[[#This Row],[Обьем]]),"") -> 0.425 | D22: Основа | E22: Европа | G22: 1000 | H22: 340 | I22: Нет | J22: 0.8
A23: Горбуша | B23: Рыба | C23: =IFERROR(IF(Ингредиенты[[#This Row],[Выход]]<>"",(Ингредиенты[[#This Row],[Цена/Обьем]]/Ингредиенты[[#This Row],[Обьем]]*100%/Ингредиенты[[#This Row],[Выход]]),Ингредиенты[[#This Row],[Цена/Обьем]]/Ингредиенты[[#This Row],[Обьем]]),"") -> 0.37855714 | D23: Основа | E23: Европа | G23: 1000 | H23: 264.99 | I23: Нет | J23: 0.7
A24: Сельдь | B24: Рыба | C24: =IFERROR(IF(Ингредиенты[[#This Row],[Выход]]<>"",(Ингредиенты[[#This Row],[Цена/Обьем]]/Ингредиенты[[#This Row],[Обьем]]*100%/Ингредиенты[[#This Row],[Выход]]),Ингредиенты[[#This Row],[Цена/Обьем]]/Ингредиенты[[#This Row],[Обьем]]),"") -> 0.34285714 | D24: Основа | E24: Европа | G24: 1000 | H24: 240 | I24: Нет | J24: 0.7
A25: Карп | B25: Рыба | C25: =IFERROR(IF(Ингредиенты[[#This Row],[Выход]]<>"",(Ингредиенты[[#This Row],[Цена/Обьем]]/Ингредиенты[[#This Row],[Обьем]]*100%/Ингредиенты[[#This Row],[Выход]]),Ингредиенты[[#This Row],[Цена/Обьем]]/Ингредиенты[[#This Row],[Обьем]]),"") -> 0.49998333 | D25: Основа | E25: Европа | G25: 1000 | H25: 299.99 | I25: Да | J25: 0.6
A26: Белый амур | B26: Рыба | C26: =IFERROR(IF(Ингредиенты[[#This Row],[Выход]]<>"",(Ингредиенты[[#This Row],[Цена/Обьем]]/Ингредиенты[[#This Row],[Обьем]]*100%/Ингредиенты[[#This Row],[Выход]]),Ингредиенты[[#This Row],[Цена/Обьем]]/Ингредиенты[[#This Row],[Обьем]]),"") -> 0.66666667 | D26: Основа | G26: 1000 | H26: 400 | I26: Да | J26: 0.6
A27: Карась | B27: Рыба | C27: =IFERROR(IF(Ингредиенты[[#This Row],[Выход]]<>"",(Ингредиенты[[#This Row],[Цена/Обьем]]/Ингредиенты[[#This Row],[Обьем]]*100%/Ингредиенты[[#This Row],[Выход]]),Ингредиенты[[#This Row],[Цена/Обьем]]/Ингредиенты[[#This Row],[Обьем]]),"") -> 0.25 | D27: Основа | E27: Авито | G27: 1000 | H27: 150 | I27: Да | J27: 0.6
A28: Щука | B28: Рыба | C28: =IFERROR(IF(Ингредиенты[[#This Row],[Выход]]<>"",(Ингредиенты[[#This Row],[Цена/Обьем]]/Ингредиенты[[#This Row],[Обьем]]*100%/Ингредиенты[[#This Row],[Выход]]),Ингредиенты[[#This Row],[Цена/Обьем]]/Ингредиенты[[#This Row],[Обьем]]),"") -> 0.30769231 | D28: Основа | E28: Авито | G28: 1000 | H28: 200 | I28: Да | J28: 0.65
A29: Форель | B29: Рыба | C29: =IFERROR(IF(Ингредиенты[[#This Row],[Выход]]<>"",(Ингредиенты[[#This Row],[Цена/Обьем]]/Ингредиенты[[#This Row],[Обьем]]*100%/Ингредиенты[[#This Row],[Выход]]),Ингредиенты[[#This Row],[Цена/Обьем]]/Ингредиенты[[#This Row],[Обьем]]),"") -> 1.37375 | D29: Основа | E29: Европа | F29: Форель с\м б/г крупная - купить онлайн с доставкой по цене 1099.99 в интернет-магазине ЕВРОПА | G29: 1000 | H29: 1099 | I29: Нет | J29: 0.8
A30: Рис круглозерновой | B30: Добавки | C30: =IFERROR(IF(Ингредиенты[[#This Row],[Выход]]<>"",(Ингредиенты[[#This Row],[Цена/Обьем]]/Ингредиенты[[#This Row],[Обьем]]*100%/Ингредиенты[[#This Row],[Выход]]),Ингредиенты[[#This Row],[Цена/Обьем]]/Ингредиенты[[#This Row],[Обьем]]),"") -> 0.24444444 | D30: Основа | G30: 900 | H30: 220
A31: Перловка | B31: Добавки | C31: =IFERROR(IF(Ингредиенты[[#This Row],[Выход]]<>"",(Ингредиенты[[#This Row],[Цена/Обьем]]/Ингредиенты[[#This Row],[Обьем]]*100%/Ингредиенты[[#This Row],[Выход]]),Ингредиенты[[#This Row],[Цена/Обьем]]/Ингредиенты[[#This Row],[Обьем]]),"") -> 0.04125 | D31: Основа | E31: Европа | F31: Крупа перловая Европа 800г - купить онлайн с доставкой по цене 33 в интернет-магазине ЕВРОПА (europa-market.ru) | G31: 800 | H31: 33 | I31: Да
A32: Картофель | B32: Добавки | C32: =IFERROR(IF(Ингредиенты[[#This Row],[Выход]]<>"",(Ингредиенты[[#This Row],[Цена/Обьем]]/Ингредиенты[[#This Row],[Обьем]]*100%/Ингредиенты[[#This Row],[Выход]]),Ингредиенты[[#This Row],[Цена/Обьем]]/Ингредиенты[[#This Row],[Обьем]]),"") -> 0.03999 | D32: Основа | E32: Европа | F32: Картофель вес - купить онлайн с доставкой по цене 39.99 в интернет-магазине ЕВРОПА (europa-market.ru) | G32: 1000 | H32: 39.99 | I32: Да
A33: Молоко | B33: Добавки | C33: =IFERROR(IF(Ингредиенты[[#This Row],[Выход]]<>"",(Ингредиенты[[#This Row],[Цена/Обьем]]/Ингредиенты[[#This Row],[Обьем]]*100%/Ингредиенты[[#This Row],[Выход]]),Ингредиенты[[#This Row],[Цена/Обьем]]/Ингредиенты[[#This Row],[Обьем]]),"") -> 0.06666 | D33: Основа | E33: Панарин | G33: 1000 | H33: 66.66 | I33: Да
A34: Морковь | B34: Специи | C34: =IFERROR(IF(Ингредиенты[[#This Row],[Выход]]<>"",(Ингредиенты[[#This Row],[Цена/Обьем]]/Ингредиенты[[#This Row],[Обьем]]*100%/Ингредиенты[[#This Row],[Выход]]),Ингредиенты[[#This Row],[Цена/Обьем]]/Ингредиенты[[#This Row],[Обьем]]),"") -> 0.02999 | D34: Добавка | E34: Европа | F34: Морковь вес - купить онлайн с доставкой по цене 29.99 в интернет-магазине ЕВРОПА (europa-market.ru) | G34: 1000 | H34: 29.99 | I34: Да
A35: Сливочное масло | B35: Добавки | C35: =IFERROR(IF(Ингредиенты[[#This Row],[Выход]]<>"",(Ингредиенты[[#This Row],[Цена/Обьем]]/Ингредиенты[[#This Row],[Обьем]]*100%/Ингредиенты[[#This Row],[Выход]]),Ингредиенты[[#This Row],[Цена/Обьем]]/Ингредиенты[[#This Row],[Обьем]]),"") -> 0.91666667 | D35: Добавка | E35: Европа | F35: Масло сливочное традиционное 180 г 82, 5% фольга курскмаслопром - купить онлайн с доставкой по цене 165 в интернет-магазине ЕВРОПА (europa-market.ru) | G35: 180 | H35: 165 | I35: Да
A36: Яйцо | B36: Добавки | C36: =IFERROR(IF(Ингредиенты[[#This Row],[Выход]]<>"",(Ингредиенты[[#This Row],[Цена/Обьем]]/Ингредиенты[[#This Row],[Обьем]]*100%/Ингредиенты[[#This Row],[Выход]]),Ингредиенты[[#This Row],[Цена/Обьем]]/Ингредиенты[[#This Row],[Обьем]]),"") -> 0.11111111 | D36: Добавка | E36: Европа | G36: 1800 | H36: 200 | I36: Да
A37: Вода | B37: Добавки | C37: =IFERROR(IF(Ингредиенты[[#This Row],[Выход]]<>"",(Ингредиенты[[#This Row],[Цена/Обьем]]/Ингредиенты[[#This Row],[Обьем]]*100%/Ингредиенты[[#This Row],[Выход]]),Ингредиенты[[#This Row],[Цена/Обьем]]/Ингредиенты[[#This Row],[Обьем]]),"") -> 0.001 | D37: Добавка | E37: Сам делаю | G37: 1000 | H37: 1 | I37: Да
A38: Мука пшеничная | B38: Добавки | C38: =IFERROR(IF(Ингредиенты[[#This Row],[Выход]]<>"",(Ингредиенты[[#This Row],[Цена/Обьем]]/Ингредиенты[[#This Row],[Обьем]]*100%/Ингредиенты[[#This Row],[Выход]]),Ингредиенты[[#This Row],[Цена/Обьем]]/Ингредиенты[[#This Row],[Обьем]]),"") -> 0.0484 | D38: Добавка | E38: Европа | F38: Мука пшеничная Европа хлебопекарная высший сорт 1кг - купить онлайн с доставкой по цене 48.4 в интернет-магазине ЕВРОПА (europa-market.ru) | G38: 1000 | H38: 48.4 | I38: Да
A39: Уксус 9% | B39: Добавки | C39: =IFERROR(IF(Ингредиенты[[#This Row],[Выход]]<>"",(Ингредиенты[[#This Row],[Цена/Обьем]]/Ингредиенты[[#This Row],[Обьем]]*100%/Ингредиенты[[#This Row],[Выход]]),Ингредиенты[[#This Row],[Цена/Обьем]]/Ингредиенты[[#This Row],[Обьем]]),"") -> 0.173 | D39: Добавка | E39: Озон | F39: Уксус столовый 9% 1 л - купить с доставкой по выгодным ценам в интернет-магазине OZON (1194373193) | G39: 1000 | H39: 173 | I39: Да
A40: Лимонная кислота | B40: Добавки | C40: =IFERROR(IF(Ингредиенты[[#This Row],[Выход]]<>"",(Ингредиенты[[#This Row],[Цена/Обьем]]/Ингредиенты[[#This Row],[Обьем]]*100%/Ингредиенты[[#This Row],[Выход]]),Ингредиенты[[#This Row],[Цена/Обьем]]/Ингредиенты[[#This Row],[Обьем]]),"") -> 0.17766667 | D40: Добавка | E40: Озон | F40: Лимонная кислота пищевая 3 кг - регулятор кислотности, антиокислитель - купить с доставкой по выгодным ценам в интернет-магазине OZON (787154197) | G40: 3000 | H40: 533 | I40: Да
A41: Подсолнечное масло | B41: Добавки | C41: =IFERROR(IF(Ингредиенты[[#This Row],[Выход]]<>"",(Ингредиенты[[#This Row],[Цена/Обьем]]/Ингредиенты[[#This Row],[Обьем]]*100%/Ингредиенты[[#This Row],[Выход]]),Ингредиенты[[#This Row],[Цена/Обьем]]/Ингредиенты[[#This Row],[Обьем]]),"") -> 0.165 | D41: Добавка | E41: Европа | G41: 1000 | H41: 165 | I41: Да
A42: Вино красное сухое | B42: Добавки | C42: =IFERROR(IF(Ингредиенты[[#This Row],[Выход]]<>"",(Ингредиенты[[#This Row],[Цена/Обьем]]/Ингредиенты[[#This Row],[Обьем]]*100%/Ингредиенты[[#This Row],[Выход]]),Ингредиенты[[#This Row],[Цена/Обьем]]/Ингредиенты[[#This Row],[Обьем]]),"") -> 0.517 | D42: Добавка | E42: Европа | F42: Вино густо 1л 10-12% красное сух тетра-пак - купить онлайн с доставкой по цене 429 в интернет-магазине ЕВРОПА (europa-market.ru) | G42: 1000 | H42: 517 | I42: Да
A43: Вино белое сухое | B43: Добавки | C43: =IFERROR(IF(Ингредиенты[[#This Row],[Выход]]<>"",(Ингредиенты[[#This Row],[Цена/Обьем]]/Ингредиенты[[#This Row],[Обьем]]*100%/Ингредиенты[[#This Row],[Выход]]),Ингредиенты[[#This Row],[Цена/Обьем]]/Ингредиенты[[#This Row],[Обьем]]),"") -> 0.539 | D43: Добавка | E43: Европа | F43: Вино густо 1л 10-12% белое сух тетра-пак - купить онлайн с доставкой по цене 539 в интернет-магазине ЕВРОПА (europa-market.ru) | G43: 1000 | H43: 539 | I43: Нет
A44: Коньяк | B44: Добавки | C44: =IFERROR(IF(Ингредиенты[[#This Row],[Выход]]<>"",(Ингредиенты[[#This Row],[Цена/Обьем]]/Ингредиенты[[#This Row],[Обьем]]*100%/Ингредиенты[[#This Row],[Выход]]),Ингредиенты[[#This Row],[Цена/Обьем]]/Ингредиенты[[#This Row],[Обьем]]),"") -> 1 | D44: Добавка | G44: 500 | H44: 500 | I44: Нет
A45: Крахмал картофельный | B45: Добавки | C45: =IFERROR(IF(Ингредиенты[[#This Row],[Выход]]<>"",(Ингредиенты[[#This Row],[Цена/Обьем]]/Ингредиенты[[#This Row],[Обьем]]*100%/Ингредиенты[[#This Row],[Выход]]),Ингредиенты[[#This Row],[Цена/Обьем]]/Ингредиенты[[#This Row],[Обьем]]),"") -> 0.215 | D45: Добавка | E45: Озон | F45: Крахмал картофельный, ГОСТ 3шт по 1 кг Роспланта, Без глютена Высший сорт - купить с доставкой по выгодным ценам в интернет-магазине OZON (838789167) | G45: 1000 | H45: 215 | I45: Нет
A46: Сухое молоко | B46: Добавки | C46: =IFERROR(IF(Ингредиенты[[#This Row],[Выход]]<>"",(Ингредиенты[[#This Row],[Цена/Обьем]]/Ингредиенты[[#This Row],[Обьем]]*100%/Ингредиенты[[#This Row],[Выход]]),Ингредиенты[[#This Row],[Цена/Обьем]]/Ингредиенты[[#This Row],[Обьем]]),"") -> 0.549 | D46: Добавка | E46: Европа | F46: Сухое молоко для выпечки сп - купить онлайн с доставкой по цене 549.9 в интернет-магазине ЕВРОПА (europa-market.ru) | G46: 1000 | H46: 549 | I46: Да
A47: Фисташки | B47: Добавки | C47: =IFERROR(IF(Ингредиенты[[#This Row],[Выход]]<>"",(Ингредиенты[[#This Row],[Цена/Обьем]]/Ингредиенты[[#This Row],[Обьем]]*100%/Ингредиенты[[#This Row],[Выход]]),Ингредиенты[[#This Row],[Цена/Обьем]]/Ингредиенты[[#This Row],[Обьем]]),"") -> 2.2 | D47: Добавка | E47: Европа | F47: Фисташки 500 г жареные соленые - купить онлайн с доставкой по цене 847 в интернет-магазине ЕВРОПА (europa-market.ru) | G47: 500 | H47: 880 | I47: Нет | J47: 0.8
A48: Сыр российский | B48: Добавки | C48: =IFERROR(IF(Ингредиенты[[#This Row],[Выход]]<>"",(Ингредиенты[[#This Row],[Цена/Обьем]]/Ингредиенты[[#This Row],[Обьем]]*100%/Ингредиенты[[#This Row],[Выход]]),Ингредиенты[[#This Row],[Цена/Обьем]]/Ингредиенты[[#This Row],[Обьем]]),"") -> 0.79999 | D48: Добавка | E48: Европа | F48: Сыр российский 50% беларусь - купить онлайн с доставкой по цене 599.99 в интернет-магазине ЕВРОПА (europa-market.ru) | G48: 1000 | H48: 799.99 | I48: Нет
A49: Краситель пищевой | B49: Добавки | C49: =IFERROR(IF(Ингредиенты[[#This Row],[Выход]]<>"",(Ингредиенты[[#This Row],[Цена/Обьем]]/Ингредиенты[[#This Row],[Обьем]]*100%/Ингредиенты[[#This Row],[Выход]]),Ингредиенты[[#This Row],[Цена/Обьем]]/Ингредиенты[[#This Row],[Обьем]]),"") -> 9.0769231 | D49: Добавка | E49: Озон | F49: Краситель пищевой Красный бархат ART COLOR BASE для выпечки, десертов, кондитерских изделий, гелевый водорастворимый, 10 мл - купить с доставкой по выгодным ценам в интернет-магазине OZON (311527017) | G49: 13 | H49: 118 | I49: Нет
A50: Альбумин пищевой (кровь) | B50: Добавки | C50: =IFERROR(IF(Ингредиенты[[#This Row],[Выход]]<>"",(Ингредиенты[[#This Row],[Цена/Обьем]]/Ингредиенты[[#This Row],[Обьем]]*100%/Ингредиенты[[#This Row],[Выход]]),Ингредиенты[[#This Row],[Цена/Обьем]]/Ингредиенты[[#This Row],[Обьем]]),"") -> 1.006 | D50: Добавка | E50: Озон | F50: Альбумин (сухая кровь), 500 г - купить с доставкой по выгодным ценам в интернет-магазине OZON (1322993999) | G50: 500 | H50: 503 | I50: Нет
A51: Аспик, 220 блюм | B51: Добавки | C51: =IFERROR(IF(Ингредиенты[[#This Row],[Выход]]<>"",(Ингредиенты[[#This Row],[Цена/Обьем]]/Ингредиенты[[#This Row],[Обьем]]*100%/Ингредиенты[[#This Row],[Выход]]),Ингредиенты[[#This Row],[Цена/Обьем]]/Ингредиенты[[#This Row],[Обьем]]),"") -> 1.812 | D51: Добавка | E51: Озон | F51: Желатин Гала Аспик с ароматом говядины, 100 гр - 5 пакетов - купить с доставкой по выгодным ценам в интернет-магазине OZON (1328180818) | G51: 500 | H51: 906 | I51: Нет
A52: Сливки | B52: Добавки | C52: =IFERROR(IF(Ингредиенты[[#This Row],[Выход]]<>"",(Ингредиенты[[#This Row],[Цена/Обьем]]/Ингредиенты[[#This Row],[Обьем]]*100%/Ингредиенты[[#This Row],[Выход]]),Ингредиенты[[#This Row],[Цена/Обьем]]/Ингредиенты[[#This Row],[Обьем]]),"") -> 0.506 | D52: Добавка | E52: Европа | F52: Сливки Свитлогорье 500г 20% ультрапастеризованные - купить онлайн с доставкой по цене 253 в интернет-магазине ЕВРОПА (europa-market.ru) | G52: 500 | H52: 253 | I52: Да
A53: Дрожжи | B53: Добавки | C53: =IFERROR(IF(Ингредиенты[[#This Row],[Выход]]<>"",(Ингредиенты[[#This Row],[Цена/Обьем]]/Ингредиенты[[#This Row],[Обьем]]*100%/Ингредиенты[[#This Row],[Выход]]),Ингредиенты[[#This Row],[Цена/Обьем]]/Ингредиенты[[#This Row],[Обьем]]),"") -> 0.58426966 | D53: Добавка | E53: Озон | F53: Дрожжи спиртовые турбо Bragman Industrial 200L, 520 г (Брагман Индастриал 200 литров для самогона) купить на OZON по низкой цене (170040789) | G53: 890 | H53: 520 | I53: Нет
A54: Соль нитритная | B54: Специи | C54: =IFERROR(IF(Ингредиенты[[#This Row],[Выход]]<>"",(Ингредиенты[[#This Row],[Цена/Обьем]]/Ингредиенты[[#This Row],[Обьем]]*100%/Ингредиенты[[#This Row],[Выход]]),Ингредиенты[[#This Row],[Цена/Обьем]]/Ингредиенты[[#This Row],[Обьем]]),"") -> 0.128 | D54: Добавка | E54: Емколбаски | F54: ОПТ - НИТРИТНАЯ соль, AKZO NOBEL (Дания) - 25 кг (emkolbaski.ru) | G54: 25000 | H54: 3200 | I54: Да
A55: Соль пищевая | B55: Специи | C55: =IFERROR(IF(Ингредиенты[[#This Row],[Выход]]<>"",(Ингредиенты[[#This Row],[Цена/Обьем]]/Ингредиенты[[#This Row],[Обьем]]*100%/Ингредиенты[[#This Row],[Выход]]),Ингредиенты[[#This Row],[Цена/Обьем]]/Ингредиенты[[#This Row],[Обьем]]),"") -> 0.0385 | D55: Добавка | E55: Европа | F55: Соль 1кг пищевая в пачке - купить онлайн с доставкой по цене 38.5 в интернет-магазине ЕВРОПА (europa-market.ru) | G55: 1000 | H55: 38.5 | I55: Да
A56: Соль рассол | B56: Специи | C56: =IFERROR(IF(Ингредиенты[[#This Row],[Выход]]<>"",(Ингредиенты[[#This Row],[Цена/Обьем]]/Ингредиенты[[#This Row],[Обьем]]*100%/Ингредиенты[[#This Row],[Выход]]),Ингредиенты[[#This Row],[Цена/Обьем]]/Ингредиенты[[#This Row],[Обьем]]),"") -> 0.0385 | D56: Добавка | E56: Европа | F56: Соль 1кг пищевая в пачке - купить онлайн с доставкой по цене 38.5 в интернет-магазине ЕВРОПА (europa-market.ru) | G56: 1000 | H56: 38.5 | I56: Да
A57: Сахар | B57: Специи | C57: =IFERROR(IF(Ингредиенты[[#This Row],[Выход]]<>"",(Ингредиенты[[#This Row],[Цена/Обьем]]/Ингредиенты[[#This Row],[Обьем]]*100%/Ингредиенты[[#This Row],[Выход]]),Ингредиенты[[#This Row],[Цена/Обьем]]/Ингредиенты[[#This Row],[Обьем]]),"") -> 0.080882353 | D57: Добавка | E57: Европа | F57: Сахар-песок Европа 1,7кг - купить онлайн с доставкой по цене 137.5 в интернет-магазине ЕВРОПА (europa-market.ru) | G57: 1700 | H57: 137.5 | I57: Да
A58: Перец черный молотый | B58: Специи | C58: =IFERROR(IF(Ингредиенты[[#This Row],[Выход]]<>"",(Ингредиенты[[#This Row],[Цена/Обьем]]/Ингредиенты[[#This Row],[Обьем]]*100%/Ингредиенты[[#This Row],[Выход]]),Ингредиенты[[#This Row],[Цена/Обьем]]/Ингредиенты[[#This Row],[Обьем]]),"") -> 1.0945455 | D58: Добавка | E58: Озон | F58: Перец черный молотый Индана 550 гр./1 000 мл., с дозатором - купить с доставкой по выгодным ценам в интернет-магазине OZON (828189366) | G58: 550 | H58: 602 | I58: Да
A59: Перец белый молотый | B59: Специи | C59: =IFERROR(IF(Ингредиенты[[#This Row],[Выход]]<>"",(Ингредиенты[[#This Row],[Цена/Обьем]]/Ингредиенты[[#This Row],[Обьем]]*100%/Ингредиенты[[#This Row],[Выход]]),Ингредиенты[[#This Row],[Цена/Обьем]]/Ингредиенты[[#This Row],[Обьем]]),"") -> 1.58 | D59: Добавка | E59: Озон | F59: Перец белый горошек, перец горошком NOYER 250 гр. - купить с доставкой по выгодным ценам в интернет-магазине OZON (202659590) | G59: 250 | H59: 395 | I59: Да
... A66: Мускатный орех | B66: Специи | C66: =IFERROR(IF(Ингредиенты[[#This Row],[Выход]]<>"",(Ингредиенты[[#This Row],[Цена/Обьем]]/Ингредиенты[[#This Row],[Обьем]]*100%/Ингредиенты[[#This Row],[Выход]]),Ингредиенты[[#This Row],[Цена/Обьем]]/Ингредиенты[[#This Row],[Обьем]]),"") -> 2.0772727 | D66: Добавка | E66: Озон | F66: Мускатный орех молотый Индана 220 г./ 500 мл., с дозатором - купить с доставкой по выгодным ценам в интернет-магазине OZON (233676928) | G66: 220 | H66: 457 | I66: Да
A67: Чеснок свежий | B67: Специи | C67: =IFERROR(IF(Ингредиенты[[#This Row],[Выход]]<>"",(Ингредиенты[[#This Row],[Цена/Обьем]]/Ингредиенты[[#This Row],[Обьем]]*100%/Ингредиенты[[#This Row],[Выход]]),Ингредиенты[[#This Row],[Цена/Обьем]]/Ингредиенты[[#This Row],[Обьем]]),"") -> 0.49999 | D67: Добавка | E67: Европа | F67: Чеснок молодой вес - купить онлайн с доставкой по цене 499.99 в интернет-магазине ЕВРОПА | G67: 1000 | H67: 499.99
A68: Чеснок сушеный | B68: Специи | C68: =IFERROR(IF(Ингредиенты[[#This Row],[Выход]]<>"",(Ингредиенты[[#This Row],[Цена/Обьем]]/Ингредиенты[[#This Row],[Обьем]]*100%/Ингредиенты[[#This Row],[Выход]]),Ингредиенты[[#This Row],[Цена/Обьем]]/Ингредиенты[[#This Row],[Обьем]]),"") -> 0.87833333 | D68: Добавка | E68: Озон | F68: Чеснок сушеный гранулированный Индана 600 г./1000 мл., с дозатором - купить с доставкой по выгодным ценам в интернет-магазине OZON (214345648) | G68: 600 | H68: 527 | I68: Да
A69: Лук сушеный | B69: Специи | C69: =IFERROR(IF(Ингредиенты[[#This Row],[Выход]]<>"",(Ингредиенты[[#This Row],[Цена/Обьем]]/Ингредиенты[[#This Row],[Обьем]]*100%/Ингредиенты[[#This Row],[Выход]]),Ингредиенты[[#This Row],[Цена/Обьем]]/Ингредиенты[[#This Row],[Обьем]]),"") -> 0.888 | D69: Добавка | E69: Озон | F69: Луковый порошок (сушеный молотый лук) ПРЕМИУМ купить на OZON по низкой цене (768326092) | G69: 1000 | H69: 888 | I69: Нет
A70: Кардамон | B70: Специи | C70: =IFERROR(IF(Ингредиенты[[#This Row],[Выход]]<>"",(Ингредиенты[[#This Row],[Цена/Обьем]]/Ингредиенты[[#This Row],[Обьем]]*100%/Ингредиенты[[#This Row],[Выход]]),Ингредиенты[[#This Row],[Цена/Обьем]]/Ингредиенты[[#This Row],[Обьем]]),"") -> 1.5133333 | D70: Добавка | E70: Озон | F70: Кардамон молотый высший сорт, 300 г, Курагово - купить с доставкой по выгодным ценам в интернет-магазине OZON (1072075710) | G70: 300 | H70: 454 | I70: Да
A71: Кориандр | B71: Специи | C71: =IFERROR(IF(Ингредиенты[[#This Row],[Выход]]<>"",(Ингредиенты[[#This Row],[Цена/Обьем]]/Ингредиенты[[#This Row],[Обьем]]*100%/Ингредиенты[[#This Row],[Выход]]),Ингредиенты[[#This Row],[Цена/Обьем]]/Ингредиенты[[#This Row],[Обьем]]),"") -> 0.50222222 | D71: Добавка | E71: Озон | F71: Кориандр молотый Индана, 450 г./1000 мл. с дозатором - купить с доставкой по выгодным ценам в интернет-магазине OZON (213559863) | G71: 450 | H71: 226 | I71: Да
A72: Фосфат | B72: Специи | C72: =IFERROR(IF(Ингредиенты[[#This Row],[Выход]]<>"",(Ингредиенты[[#This Row],[Цена/Обьем]]/Ингредиенты[[#This Row],[Обьем]]*100%/Ингредиенты[[#This Row],[Выход]]),Ингредиенты[[#This Row],[Цена/Обьем]]/Ингредиенты[[#This Row],[Обьем]]),"") -> 0.748 | D72: Добавка | E72: Озон | F72: Фосфат пищевой для колбасы, сосисок, сарделек - купить с доставкой по выгодным ценам в интернет-магазине OZON (1002521417) | G72: 1000 | H72: 748 | I72: Да
A73: Аскорбиновая кислота | B73: Специи | C73: =IFERROR(IF(Ингредиенты[[#This Row],[Выход]]<>"",(Ингредиенты[[#This Row],[Цена/Обьем]]/Ингредиенты[[#This Row],[Обьем]]*100%/Ингредиенты[[#This Row],[Выход]]),Ингредиенты[[#This Row],[Цена/Обьем]]/Ингредиенты[[#This Row],[Обьем]]),"") -> 1.702 | D73: Добавка | E73: Емколбаски | F73: Аскорбинат (аскорбат) натрия - 1 кг (emkolbaski.ru) | G73: 1000 | H73: 1702 | I73: Да
A74: Глютамат натрия | B74: Специи | C74: =IFERROR(IF(Ингредиенты[[#This Row],[Выход]]<>"",(Ингредиенты[[#This Row],[Цена/Обьем]]/Ингредиенты[[#This Row],[Обьем]]*100%/Ингредиенты[[#This Row],[Выход]]),Ингредиенты[[#This Row],[Цена/Обьем]]/Ингредиенты[[#This Row],[Обьем]]),"") -> 0.555 | D74: Добавка | E74: Озон | F74: Глутамат натрия натуральный, 1 000 мл./ 800 гр., приправа, усилитель вкуса и аромата, пищевая добавка, ТМ "Индана". - купить с доставкой по выгодным ценам в интернет-магазине OZON (529935601) | G74: 800 | H74: 444 | I74: Да
A75: Цитрат натрия E331 | B75: Специи | C75: =IFERROR(IF(Ингредиенты[[#This Row],[Выход]]<>"",(Ингредиенты[[#This Row],[Цена/Обьем]]/Ингредиенты[[#This Row],[Обьем]]*100%/Ингредиенты[[#This Row],[Выход]]),Ингредиенты[[#This Row],[Цена/Обьем]]/Ингредиенты[[#This Row],[Обьем]]),"") -> 0.267 | D75: Добавка | E75: Озон | F75: Цитрат натрия, пищевая добавка Е331, натрий лимоннокислый / 2 кг (4*500 гр) - купить с доставкой по выгодным ценам в интернет-магазине OZON (755454232) | G75: 2000 | H75: 534 | I75: Нет
A76: Анис | B76: Специи | C76: =IFERROR(IF(Ингредиенты[[#This Row],[Выход]]<>"",(Ингредиенты[[#This Row],[Цена/Обьем]]/Ингредиенты[[#This Row],[Обьем]]*100%/Ингредиенты[[#This Row],[Выход]]),Ингредиенты[[#This Row],[Цена/Обьем]]/Ингредиенты[[#This Row],[Обьем]]),"") -> 1.645 | D76: Добавка | E76: Озон | F76: Анис семена ТМ Индана 200 гр./500 мл. - купить с доставкой по выгодным ценам в интернет-магазине OZON (497986659) | G76: 200 | H76: 329 | I76: Нет
A77: Гвоздика | B77: Специи | C77: =IFERROR(IF(Ингредиенты[[#This Row],[Выход]]<>"",(Ингредиенты[[#This Row],[Цена/Обьем]]/Ингредиенты[[#This Row],[Обьем]]*100%/Ингредиенты[[#This Row],[Выход]]),Ингредиенты[[#This Row],[Цена/Обьем]]/Ингредиенты[[#This Row],[Обьем]]),"") -> 2.7933333 | D77: Добавка | E77: Озон | F77: Гвоздика целая (целые сушеные семена гвоздики, натуральная специя и приправа, травы) Индана 300 г./ 1 000 мл., - купить с доставкой по выгодным ценам в интернет-магазине OZON (828189508) | G77: 300 | H77: 838 | I77: Да
A78: Бадьян | B78: Специи | C78: =IFERROR(IF(Ингредиенты[[#This Row],[Выход]]<>"",(Ингредиенты[[#This Row],[Цена/Обьем]]/Ингредиенты[[#This Row],[Обьем]]*100%/Ингредиенты[[#This Row],[Выход]]),Ингредиенты[[#This Row],[Цена/Обьем]]/Ингредиенты[[#This Row],[Обьем]]),"") -> 3.94 | D78: Добавка | E78: Озон | F78: Бадьян (Анис звездчатый)/ натуральные звездочки цельные семена бадьяна / пряность приправа для кофе, десертов, глинтвейна / специи для пряников, ТМ Индана, 500 мл./ 100 г. - купить с доставкой по выгодным ценам в интернет-магазине OZON (214344546) | G78: 100 | H78: 394 | I78: Нет
A79: Фенхель | B79: Специи | C79: =IFERROR(IF(Ингредиенты[[#This Row],[Выход]]<>"",(Ингредиенты[[#This Row],[Цена/Обьем]]/Ингредиенты[[#This Row],[Обьем]]*100%/Ингредиенты[[#This Row],[Выход]]),Ингредиенты[[#This Row],[Цена/Обьем]]/Ингредиенты[[#This Row],[Обьем]]),"") -> 1.4105263 | D79: Добавка | E79: Озон | F79: Фенхель семена Индана 190 г., с дозатором - купить с доставкой по выгодным ценам в интернет-магазине OZON (233678714) | G79: 190 | H79: 268 | I79: Да
... A89: Барбарис | B89: Специи | C89: =IFERROR(IF(Ингредиенты[[#This Row],[Выход]]<>"",(Ингредиенты[[#This Row],[Цена/Обьем]]/Ингредиенты[[#This Row],[Обьем]]*100%/Ингредиенты[[#This Row],[Выход]]),Ингредиенты[[#This Row],[Цена/Обьем]]/Ингредиенты[[#This Row],[Обьем]]),"") -> 2.21 | D89: Добавка | E89: Озон | F89: Барбарис сушеный HOBBYHELPER красный банка 100г купить на OZON по низкой цене (1323184020) | G89: 200 | H89: 442 | I89: Нет
A90: Изюм | B90: Специи | C90: =IFERROR(IF(Ингредиенты[[#This Row],[Выход]]<>"",(Ингредиенты[[#This Row],[Цена/Обьем]]/Ингредиенты[[#This Row],[Обьем]]*100%/Ингредиенты[[#This Row],[Выход]]),Ингредиенты[[#This Row],[Цена/Обьем]]/Ингредиенты[[#This Row],[Обьем]]),"") -> 0.358 | D90: Добавка | E90: Озон | F90: Изюм Малаяр (Иран) 1000г без косточек / 1 кг ГРИНФУДС купить на OZON по низкой цене (1316030719) | G90: 1000 | H90: 358
A91: Чернослив | B91: Специи | C91: =IFERROR(IF(Ингредиенты[[#This Row],[Выход]]<>"",(Ингредиенты[[#This Row],[Цена/Обьем]]/Ингредиенты[[#This Row],[Обьем]]*100%/Ингредиенты[[#This Row],[Выход]]),Ингредиенты[[#This Row],[Цена/Обьем]]/Ингредиенты[[#This Row],[Обьем]]),"") -> 0.504 | D91: Добавка | E91: Озон | F91: Чернослив сушеный 1 кг, натуральный без косточки Dattie купить на OZON по низкой цене (979081263) | G91: 1000 | H91: 504 | I91: Нет
A92: Нут | B92: Добавки | C92: =IFERROR(IF(Ингредиенты[[#This Row],[Выход]]<>"",(Ингредиенты[[#This Row],[Цена/Обьем]]/Ингредиенты[[#This Row],[Обьем]]*100%/Ингредиенты[[#This Row],[Выход]]),Ингредиенты[[#This Row],[Цена/Обьем]]/Ингредиенты[[#This Row],[Обьем]]),"") -> 0.22 | D92: Основа | E92: Европа | F92: Нут агро-альянс 450 г экстра - купить онлайн с доставкой по цене 99 в интернет-магазине ЕВРОПА | G92: 450 | H92: 99
A93: Лук репчатый | B93: Специи | C93: =IFERROR(IF(Ингредиенты[[#This Row],[Выход]]<>"",(Ингредиенты[[#This Row],[Цена/Обьем]]/Ингредиенты[[#This Row],[Обьем]]*100%/Ингредиенты[[#This Row],[Выход]]),Ингредиенты[[#This Row],[Цена/Обьем]]/Ингредиенты[[#This Row],[Обьем]]),"") -> 0.04999 | D93: Добавка | E93: Европа | F93: Лук репчатый имп вес - купить онлайн с доставкой по цене 49.99 в интернет-магазине ЕВРОПА (europa-market.ru) | G93: 1000 | H93: 49.99 | I93: Да
A94: Корица молотая | B94: Специи | C94: =IFERROR(IF(Ингредиенты[[#This Row],[Выход]]<>"",(Ингредиенты[[#This Row],[Цена/Обьем]]/Ингредиенты[[#This Row],[Обьем]]*100%/Ингредиенты[[#This Row],[Выход]]),Ингредиенты[[#This Row],[Цена/Обьем]]/Ингредиенты[[#This Row],[Обьем]]),"") -> 0.78666667 | D94: Добавка | E94: Озон | F94: Корица молотая натуральная "Индана", 450 г./1000 мл., с дозатором - купить с доставкой по выгодным ценам в интернет-магазине OZON (754952582) | G94: 450 | H94: 354 | I94: Да
A95: Мята сухая | B95: Специи | C95: =IFERROR(IF(Ингредиенты[[#This Row],[Выход]]<>"",(Ингредиенты[[#This Row],[Цена/Обьем]]/Ингредиенты[[#This Row],[Обьем]]*100%/Ингредиенты[[#This Row],[Выход]]),Ингредиенты[[#This Row],[Цена/Обьем]]/Ингредиенты[[#This Row],[Обьем]]),"") -> 0.693 | D95: Добавка | E95: Озон | F95: Мята перечная сушеная ПРЕМИУМ - купить с доставкой по выгодным ценам в интернет-магазине OZON (768746378) | G95: 1000 | H95: 693 | I95: Да
A96: Горчица семена | B96: Специи | C96: =IFERROR(IF(Ингредиенты[[#This Row],[Выход]]<>"",(Ингредиенты[[#This Row],[Цена/Обьем]]/Ингредиенты[[#This Row],[Обьем]]*100%/Ингредиенты[[#This Row],[Выход]]),Ингредиенты[[#This Row],[Цена/Обьем]]/Ингредиенты[[#This Row],[Обьем]]),"") -> 0.469 | D96: Добавка | E96: Озон | F96: Семена горчицы ПРЕМИУМ специи приправы пряность оптом - купить с доставкой по выгодным ценам в интернет-магазине OZON (768587997) | G96: 1000 | H96: 469 | I96: Нет
A97: Перец чили целый | B97: Специи | C97: =IFERROR(IF(Ингредиенты[[#This Row],[Выход]]<>"",(Ингредиенты[[#This Row],[Цена/Обьем]]/Ингредиенты[[#This Row],[Обьем]]*100%/Ингредиенты[[#This Row],[Выход]]),Ингредиенты[[#This Row],[Цена/Обьем]]/Ингредиенты[[#This Row],[Обьем]]),"") -> 1.293 | D97: Добавка | E97: Озон | F97: Перец Чили стручковый целый 1 кг / Приправа, специя - купить с доставкой по выгодным ценам в интернет-магазине OZON (788691363) | G97: 1000 | H97: 1293 | I97: Нет
A98: Имбирь молотый | B98: Специи | C98: =IFERROR(IF(Ингредиенты[[#This Row],[Выход]]<>"",(Ингредиенты[[#This Row],[Цена/Обьем]]/Ингредиенты[[#This Row],[Обьем]]*100%/Ингредиенты[[#This Row],[Выход]]),Ингредиенты[[#This Row],[Цена/Обьем]]/Ингредиенты[[#This Row],[Обьем]]),"") -> 0.582 | D98: Добавка | E98: Озон | F98: Имбирь молотый сушеный натуральный 1 кг купить на OZON по низкой цене (886931793) | G98: 1000 | H98: 582 | I98: Нет
A99: Смесь приправ «Молочные сосиски» | B99: Специи | C99: =IFERROR(IF(Ингредиенты[[#This Row],[Выход]]<>"",(Ингредиенты[[#This Row],[Цена/Обьем]]/Ингредиенты[[#This Row],[Обьем]]*100%/Ингредиенты[[#This Row],[Выход]]),Ингредиенты[[#This Row],[Цена/Обьем]]/Ингредиенты[[#This Row],[Обьем]]),"") -> 1.433 | D99: Добавка | E99: Емколбаски | F99: ОПТ - Сосиски Молочные, смесь приправ - 1 кг (emkolbaski.ru) | G99: 1000 | H99: 1433 | I99: Нет
A100: Смесь приправ Мортаделла | B100: Специи | C100: =IFERROR(IF(Ингредиенты[[#This Row],[Выход]]<>"",(Ингредиенты[[#This Row],[Цена/Обьем]]/Ингредиенты[[#This Row],[Обьем]]*100%/Ингредиенты[[#This Row],[Выход]]),Ингредиенты[[#This Row],[Цена/Обьем]]/Ингредиенты[[#This Row],[Обьем]]),"") -> 1.643 | D100: Добавка | E100: Емколбаски | F100: ОПТ - Мортаделла - 1 кг - смесь приправ (emkolbaski.ru) | G100: 1000 | H100: 1643 | I100: Нет
A101: Смесь приправ «Луканка» | B101: Специи | C101: =IFERROR(IF(Ингредиенты[[#This Row],[Выход]]<>"",(Ингредиенты[[#This Row],[Цена/Обьем]]/Ингредиенты[[#This Row],[Обьем]]*100%/Ингредиенты[[#This Row],[Выход]]),Ингредиенты[[#This Row],[Цена/Обьем]]/Ингредиенты[[#This Row],[Обьем]]),"") -> 1.1 | D101: Добавка | E101: Емколбаски | F101: Смесь для Луканки - 1 кг (emkolbaski.ru) | G101: 1000 | H101: 1100 | I101: Нет
A102: АйЦел 40 | B102: Оболочка | C102: =IFERROR(IF(Ингредиенты[[#This Row],[Выход]]<>"",(Ингредиенты[[#This Row],[Цена/Обьем]]/Ингредиенты[[#This Row],[Обьем]]*100%/Ингредиенты[[#This Row],[Выход]]),Ингредиенты[[#This Row],[Цена/Обьем]]/Ингредиенты[[#This Row],[Обьем]]),"") -> 39.405941 | D102: Добавка | E102: Емколбаски | F102: Айцел для сыровяления 40 мм - 25 метров (полимерная) (emkolbaski.ru) | G102: 25 | H102: 995 | I102: Да | J102: 1.01
A103: Полиамидная 60 | B103: Оболочка | C103: =IFERROR(IF(Ингредиенты[[#This Row],[Выход]]<>"",(Ингредиенты[[#This Row],[Цена/Обьем]]/Ингредиенты[[#This Row],[Обьем]]*100%/Ингредиенты[[#This Row],[Выход]]),Ингредиенты[[#This Row],[Цена/Обьем]]/Ингредиенты[[#This Row],[Обьем]]),"") -> 15.56391 | D103: Добавка | E103: Емколбаски | F103: ОПТ - 50м, калибр 60мм. Полиамидная для Вареных колбас и Ветчин (emkolbaski.ru) | G103: 50 | H103: 1656 | I103: Да | J103: 2.128
A104: Фиброузная 50 | B104: Оболочка | C104: =IFERROR(IF(Ингредиенты[[#This Row],[Выход]]<>"",(Ингредиенты[[#This Row],[Цена/Обьем]]/Ингредиенты[[#This Row],[Обьем]]*100%/Ингредиенты[[#This Row],[Выход]]),Ингредиенты[[#This Row],[Цена/Обьем]]/Ингредиенты[[#This Row],[Обьем]]),"") -> 41.333333 | D104: Добавка | E104: Емколбаски | F104: ОПТ - Фиброузная оболочка для сервелатов ,цвет копчение, калибр 50мм, 56мм, 65мм - 50м. (emkolbaski.ru) | G104: 50 | H104: 3100 | I104: Да | J104: 1.5
A105: Полиамидная 80 | B105: Оболочка | C105: =IFERROR(IF(Ингредиенты[[#This Row],[Выход]]<>"",(Ингредиенты[[#This Row],[Цена/Обьем]]/Ингредиенты[[#This Row],[Обьем]]*100%/Ингредиенты[[#This Row],[Выход]]),Ингредиенты[[#This Row],[Цена/Обьем]]/Ингредиенты[[#This Row],[Обьем]]),"") -> 9.7374533 | D105: Добавка | E105: Емколбаски | F105: ОПТ - 50м, калибр 80 мм. Полиамидная для Вареных колбас и Ветчин (emkolbaski.ru) | G105: 50 | H105: 1656 | I105: Да | J105: 3.4013
A106: Мембрин кольцевой 42 мм | B106: Оболочка | C106: =IFERROR(IF(Ингредиенты[[#This Row],[Выход]]<>"",(Ингредиенты[[#This Row],[Цена/Обьем]]/Ингредиенты[[#This Row],[Обьем]]*100%/Ингредиенты[[#This Row],[Выход]]),Ингредиенты[[#This Row],[Цена/Обьем]]/Ингредиенты[[#This Row],[Обьем]]),"") -> 35.564872 | D106: Добавка | E106: Емколбаски | F106: МЕМБРИН 42 мм, гофра, кольцевая универсальная оболочка - 31 метра (emkolbaski.ru) | G106: 31 | H106: 1225 | I106: Нет | J106: 1.1111
A107: Свиная черева 38/40 | B107: Оболочка | C107: =IFERROR(IF(Ингредиенты[[#This Row],[Выход]]<>"",(Ингредиенты[[#This Row],[Цена/Обьем]]/Ингредиенты[[#This Row],[Обьем]]*100%/Ингредиенты[[#This Row],[Выход]]),Ингредиенты[[#This Row],[Цена/Обьем]]/Ингредиенты[[#This Row],[Обьем]]),"") -> 26.014326 | D107: Добавка | E107: Емколбаски | F107: ОПТ - Свиная черева 38/40 - 91,44м (пучок) (emkolbaski.ru) | G107: 91.44 | H107: 1903 | I107: Да | J107: 0.8
A108: Свиная черева 32/34 | B108: Оболочка | C108: =IFERROR(IF(Ингредиенты[[#This Row],[Выход]]<>"",(Ингредиенты[[#This Row],[Цена/Обьем]]/Ингредиенты[[#This Row],[Обьем]]*100%/Ингредиенты[[#This Row],[Выход]]),Ингредиенты[[#This Row],[Цена/Обьем]]/Ингредиенты[[#This Row],[Обьем]]),"") -> 39.348206 | D108: Добавка | E108: Емколбаски | F108: ОПТ - Свиная черева 32/34 – 91,44м (пучок) (emkolbaski.ru) | G108: 91.44 | H108: 1799 | I108: Нет | J108: 0.5
A109: Баранья черева 22/24 | B109: Оболочка | C109: =IFERROR(IF(Ингредиенты[[#This Row],[Выход]]<>"",(Ингредиенты[[#This Row],[Цена/Обьем]]/Ингредиенты[[#This Row],[Обьем]]*100%/Ингредиенты[[#This Row],[Выход]]),Ингредиенты[[#This Row],[Цена/Обьем]]/Ингредиенты[[#This Row],[Обьем]]),"") -> 45.688733 | D109: Добавка | E109: Емколбаски | F109: ОПТ - Баранья черева, калибр 22/24 мм, 91,44 м (пучок) - купить по цене от 1880 руб. в интернет-магазине ЕМКОЛБАСКИ! | G109: 91.44 | H109: 1880 | I109: Да | J109: 0.45
A110: Полиамидная сосисочная | B110: Оболочка | C110: =IFERROR(IF(Ингредиенты[[#This Row],[Выход]]<>"",(Ингредиенты[[#This Row],[Цена/Обьем]]/Ингредиенты[[#This Row],[Обьем]]*100%/Ингредиенты[[#This Row],[Выход]]),Ингредиенты[[#This Row],[Цена/Обьем]]/Ингредиенты[[#This Row],[Обьем]]),"") -> 15.40718 | D110: Добавка | E110: Емколбаски | F110: Сосисочная полиамидная - 33м, гильза. (emkolbaski.ru) | G110: 33 | H110: 229 | I110: Да | J110: 0.4504 | K110: 100/2,22м
A111: Нало Ферм 45/50 | B111: Оболочка | C111: =IFERROR(IF(Ингредиенты[[#This Row],[Выход]]<>"",(Ингредиенты[[#This Row],[Цена/Обьем]]/Ингредиенты[[#This Row],[Обьем]]*100%/Ингредиенты[[#This Row],[Выход]]),Ингредиенты[[#This Row],[Цена/Обьем]]/Ингредиенты[[#This Row],[Обьем]]),"") -> 32.760033 | D111: Добавка | E111: Емколбаски | F111: ОПТ - Полимерная для Вяления Нало Ферм 50 метров (emkolbaski.ru) | G111: 50 | H111: 1800 | I111: Да | J111: 1.0989
A112: Коллагеновая 45/50 | B112: Оболочка | C112: =IFERROR(IF(Ингредиенты[[#This Row],[Выход]]<>"",(Ингредиенты[[#This Row],[Цена/Обьем]]/Ингредиенты[[#This Row],[Обьем]]*100%/Ингредиенты[[#This Row],[Выход]]),Ингредиенты[[#This Row],[Цена/Обьем]]/Ингредиенты[[#This Row],[Обьем]]),"") -> 29.333333 | D112: Добавка | E112: Емколбаски | F112: ОПТ- Коллагеновая, цвет КАРАМЕЛЬ, калибр 45мм и 50 мм - 50 метров (emkolbaski.ru) | G112: 50 | H112: 2200 | I112: Да | J112: 1.5
A113: Сетка формовочная 220 мм | B113: Оболочка | C113: =IFERROR(IF(Ингредиенты[[#This Row],[Выход]]<>"",(Ингредиенты[[#This Row],[Цена/Обьем]]/Ингредиенты[[#This Row],[Обьем]]*100%/Ингредиенты[[#This Row],[Выход]]),Ингредиенты[[#This Row],[Цена/Обьем]]/Ингредиенты[[#This Row],[Обьем]]),"") -> 20.8 | D113: Добавка | E113: Емколбаски | F113: ОПТ - 50м, калибр 220 мм. Сетка формовочная. | G113: 50 | H113: 1040 | I113: Да
A114: Итог | H114: =SUBTOTAL(109,Ингредиенты[Цена/Обьем]) -> 66879.4

Sheet Рецепты
A11: Название | B11: Вид | C11: Способ | D11: Состав | E11: Тип | F11: % | G11: г | H11: р | I11: Масса | J11: Вес ингр-тов | K11: Траты всего | L11: Потери, % | M11: Маржа | N11: Цена за 1 кг | O11: ЧП | P11: Ссылка интернет | Q11: Ссылка ПК | R11: Наличие | S11: Примечание
A12: Докторская | B12: Колбаса | C12: Вареное | D12: Говядина | E12: =VLOOKUP(Рецепты[[#This Row],[Состав]],Ингредиенты[],2,0) -> Говядина | F12: 0.25 | G12: =IF(Рецепты[[#This Row],[%]]*1000>0,Рецепты[[#This Row],[%]]*1000,"") -> 250 | H12: =IFERROR(VLOOKUP(Рецепты[[#This Row],[Состав]],Ингредиенты!A:I,3,0)*Рецепты[[#This Row],[г]],"") -> 177.4975 | I12: =СводРецепт!$A$1 -> 1000 | J12: =Рецепты[[#This Row],[%]]*Рецепты[[#This Row],[Масса]] -> 250 | K12: =Рецепты[[#This Row],[Вес ингр-тов]]*VLOOKUP(Рецепты[[#This Row],[Состав]],Ингредиенты[],3,FALSE) -> 177.4975 | L12: =IF(VLOOKUP(Рецепты[[#This Row],[Состав]],Ингредиенты[],4,0)="Основа",VLOOKUP(Рецепты[[#This Row],[Способ]],Способ[],2,0),0%) -> 0.15 | M12: =VLOOKUP(Рецепты[[#This Row],[Способ]],Способ[],3,0) -> 0.7 | N12: =Рецепты[[#This Row],[р]]*100%/(100%-Рецепты[[#This Row],[Потери, %]])+Рецепты[[#This Row],[Маржа]]*(Рецепты[[#This Row],[р]]*100%)/(100%-Рецепты[[#This Row],[Потери, %]]) -> 354.995 | O12: =Рецепты[[#This Row],[Цена за 1 кг]]-(Рецепты[[#This Row],[р]]*100%/(100%-Рецепты[[#This Row],[Потери, %]])) -> 146.17441 | P12: https://www.youtube.com/watch?v=5gWsIsh4dpM | Q12: D:\Video\Колбаса_рецепты\Докторская колбаса ГОСТ 23670-79 в домашних условиях.mp12 | R12: =VLOOKUP(Рецепты[[#This Row],[Состав]],Ингредиенты[],9,0) -> Да
A13: Докторская | B13: =B12 -> Колбаса | C13: =C12 -> Вареное | D13: Лопатка свиная | E13: =VLOOKUP(Рецепты[[#This Row],[Состав]],Ингредиенты[],2,0) -> Свинина | F13: 0.7 | G13: =IF(Рецепты[[#This Row],[%]]*1000>0,Рецепты[[#This Row],[%]]*1000,"") -> 700 | H13: =IFERROR(VLOOKUP(Рецепты[[#This Row],[Состав]],Ингредиенты!A:I,3,0)*Рецепты[[#This Row],[г]],"") -> 258.3 | I13: =СводРецепт!$A$1 -> 1000 | J13: =Рецепты[[#This Row],[%]]*Рецепты[[#This Row],[Масса]] -> 700 | K13: =Рецепты[[#This Row],[Вес ингр-тов]]*VLOOKUP(Рецепты[[#This Row],[Состав]],Ингредиенты[],3,FALSE) -> 258.3 | L13: =IF(VLOOKUP(Рецепты[[#This Row],[Состав]],Ингредиенты[],4,0)="Основа",VLOOKUP(Рецепты[[#This Row],[Способ]],Способ[],2,0),0%) -> 0.15 | M13: =VLOOKUP(Рецепты[[#This Row],[Способ]],Способ[],3,0) -> 0.7 | N13: =Рецепты[[#This Row],[р]]*100%/(100%-Рецепты[[#This Row],[Потери, %]])+Рецепты[[#This Row],[Маржа]]*(Рецепты[[#This Row],[р]]*100%)/(100%-Рецепты[[#This Row],[Потери, %]]) -> 516.6 | O13: =Рецепты[[#This Row],[Цена за 1 кг]]-(Рецепты[[#This Row],[р]]*100%/(100%-Рецепты[[#This Row],[Потери, %]])) -> 212.71765 | P13: https://www.youtube.com/watch?v=5gWsIsh4dpM | Q13: D:\Video\Колбаса_рецепты\Докторская колбаса ГОСТ 23670-79 в домашних условиях.mp13 | R13: =VLOOKUP(Рецепты[[#This Row],[Состав]],Ингредиенты[],9,0) -> Нет
A14: Докторская | B14: =B13 -> Колбаса | C14: =C13 -> Вареное | D14: Яйцо | E14: =VLOOKUP(Рецепты[[#This Row],[Состав]],Ингредиенты[],2,0) -> Добавки | F14: 0.03 | G14: =IF(Рецепты[[#This Row],[%]]*1000>0,Рецепты[[#This Row],[%]]*1000,"") -> 30 | H14: =IFERROR(VLOOKUP(Рецепты[[#This Row],[Состав]],Ингредиенты!A:I,3,0)*Рецепты[[#This Row],[г]],"") -> 3.3333333 | I14: =СводРецепт!$A$1 -> 1000 | J14: =Рецепты[[#This Row],[%]]*Рецепты[[#This Row],[Масса]] -> 30 | K14: =Рецепты[[#This Row],[Вес ингр-тов]]*VLOOKUP(Рецепты[[#This Row],[Состав]],Ингредиенты[],3,FALSE) -> 3.3333333 | L14: =IF(VLOOKUP(Рецепты[[#This Row],[Состав]],Ингредиенты[],4,0)="Основа",VLOOKUP(Рецепты[[#This Row],[Способ]],Способ[],2,0),0%) -> 0 | M14: =VLOOKUP(Рецепты[[#This Row],[Способ]],Способ[],3,0) -> 0.7 | N14: =Рецепты[[#This Row],[р]]*100%/(100%-Рецепты[[#This Row],[Потери, %]])+Рецепты[[#This Row],[Маржа]]*(Рецепты[[#This Row],[р]]*100%)/(100%-Рецепты[[#This Row],[Потери, %]]) -> 5.6666667 | O14: =Рецепты[[#This Row],[Цена за 1 кг]]-(Рецепты[[#This Row],[р]]*100%/(100%-Рецепты[[#This Row],[Потери, %]])) -> 2.3333333 | P14: https://www.youtube.com/watch?v=5gWsIsh4dpM | Q14: D:\Video\Колбаса_рецепты\Докторская колбаса ГОСТ 23670-79 в домашних условиях.mp14 | R14: =VLOOKUP(Рецепты[[#This Row],[Состав]],Ингредиенты[],9,0) -> Да
A15: Докторская | B15: =B14 -> Колбаса | C15: =C14 -> Вареное | D15: Сухое молоко | E15: =VLOOKUP(Рецепты[[#This Row],[Состав]],Ингредиенты[],2,0) -> Добавки | F15: 0.02 | G15: =IF(Рецепты[[#This Row],[%]]*1000>0,Рецепты[[#This Row],[%]]*1000,"") -> 20 | H15: =IFERROR(VLOOKUP(Рецепты[[#This Row],[Состав]],Ингредиенты!A:I,3,0)*Рецепты[[#This Row],[г]],"") -> 10.98 | I15: =СводРецепт!$A$1 -> 1000 | J15: =Рецепты[[#This Row],[%]]*Рецепты[[#This Row],[Масса]] -> 20 | K15: =Рецепты[[#This Row],[Вес ингр-тов]]*VLOOKUP(Рецепты[[#This Row],[Состав]],Ингредиенты[],3,FALSE) -> 10.98 | L15: =IF(VLOOKUP(Рецепты[[#This Row],[Состав]],Ингредиенты[],4,0)="Основа",VLOOKUP(Рецепты[[#This Row],[Способ]],Способ[],2,0),0%) -> 0 | M15: =VLOOKUP(Рецепты[[#This Row],[Способ]],Способ[],3,0) -> 0.7 | N15: =Рецепты[[#This Row],[р]]*100%/(100%-Рецепты[[#This Row],[Потери, %]])+Рецепты[[#This Row],[Маржа]]*(Рецепты[[#This Row],[р]]*100%)/(100%-Рецепты[[#This Row],[Потери, %]]) -> 18.666 | O15: =Рецепты[[#This Row],[Цена за 1 кг]]-(Рецепты[[#This Row],[р]]*100%/(100%-Рецепты[[#This Row],[Потери, %]])) -> 7.686 | P15: https://www.youtube.com/watch?v=5gWsIsh4dpM | Q15: D:\Video\Колбаса_рецепты\Докторская колбаса ГОСТ 23670-79 в домашних условиях.mp15 | R15: =VLOOKUP(Рецепты[[#This Row],[Состав]],Ингредиенты[],9,0) -> Да
A16: Докторская | B16: Колбаса | C16: Вареное | D16: Соль нитритная | E16: =VLOOKUP(Рецепты[[#This Row],[Состав]],Ингредиенты[],2,0) -> Специи | F16: 0.02 | G16: =IF(Рецепты[[#This Row],[%]]*1000>0,Рецепты[[#This Row],[%]]*1000,"") -> 20 | H16: =IFERROR(VLOOKUP(Рецепты[[#This Row],[Состав]],Ингредиенты!A:I,3,0)*Рецепты[[#This Row],[г]],"") -> 2.56 | I16: =СводРецепт!$A$1 -> 1000 | J16: =Рецепты[[#This Row],[%]]*Рецепты[[#This Row],[Масса]] -> 20 | K16: =Рецепты[[#This Row],[Вес ингр-тов]]*VLOOKUP(Рецепты[[#This Row],[Состав]],Ингредиенты[],3,FALSE) -> 2.56 | L16: =IF(VLOOKUP(Рецепты[[#This Row],[Состав]],Ингредиенты[],4,0)="Основа",VLOOKUP(Рецепты[[#This Row],[Способ]],Способ[],2,0),0%) -> 0 | M16: =VLOOKUP(Рецепты[[#This Row],[Способ]],Способ[],3,0) -> 0.7 | N16: =Рецепты[[#This Row],[р]]*100%/(100%-Рецепты[[#This Row],[Потери, %]])+Рецепты[[#This Row],[Маржа]]*(Рецепты[[#This Row],[р]]*100%)/(100%-Рецепты[[#This Row],[Потери, %]]) -> 4.352 | O16: =Рецепты[[#This Row],[Цена за 1 кг]]-(Рецепты[[#This Row],[р]]*100%/(100%-Рецепты[[#This Row],[Потери, %]])) -> 1.792 | P16: https://www.youtube.com/watch?v=5gWsIsh4dpM | Q16: D:\Video\Колбаса_рецепты\Докторская колбаса ГОСТ 23670-79 в домашних условиях.mp17 | R16: =VLOOKUP(Рецепты[[#This Row],[Состав]],Ингредиенты[],9,0) -> Да
A17: Докторская | B17: =B16 -> Колбаса | C17: =C16 -> Вареное | D17: Вода | E17: =VLOOKUP(Рецепты[[#This Row],[Состав]],Ингредиенты[],2,0) -> Добавки | F17: 0.1 | G17: =IF(Рецепты[[#This Row],[%]]*1000>0,Рецепты[[#This Row],[%]]*1000,"") -> 100 | H17: =IFERROR(VLOOKUP(Рецепты[[#This Row],[Состав]],Ингредиенты!A:I,3,0)*Рецепты[[#This Row],[г]],"") -> 0.1 | I17: =СводРецепт!$A$1 -> 1000 | J17: =Рецепты[[#This Row],[%]]*Рецепты[[#This Row],[Масса]] -> 100 | K17: =Рецепты[[#This Row],[Вес ингр-тов]]*VLOOKUP(Рецепты[[#This Row],[Состав]],Ингредиенты[],3,FALSE) -> 0.1 | L17: =IF(VLOOKUP(Рецепты[[#This Row],[Состав]],Ингредиенты[],4,0)="Основа",VLOOKUP(Рецепты[[#This Row],[Способ]],Способ[],2,0),0%) -> 0 | M17: =VLOOKUP(Рецепты[[#This Row],[Способ]],Способ[],3,0) -> 0.7 | N17: =Рецепты[[#This Row],[р]]*100%/(100%-Рецепты[[#This Row],[Потери, %]])+Рецепты[[#This Row],[Маржа]]*(Рецепты[[#This Row],[р]]*100%)/(100%-Рецепты[[#This Row],[Потери, %]]) -> 0.17 | O17: =Рецепты[[#This Row],[Цена за 1 кг]]-(Рецепты[[#This Row],[р]]*100%/(100%-Рецепты[[#This Row],[Потери, %]])) -> 0.07 | P17: https://www.youtube.com/watch?v=5gWsIsh4dpM | Q17: D:\Video\Колбаса_рецепты\Докторская колбаса ГОСТ 23670-79 в домашних условиях.mp18 | R17: =VLOOKUP(Рецепты[[#This Row],[Состав]],Ингредиенты[],9,0) -> Да
A18: Докторская | B18: =B17 -> Колбаса | C18: =C17 -> Вареное | D18: Фосфат | E18: =VLOOKUP(Рецепты[[#This Row],[Состав]],Ингредиенты[],2,0) -> Специи | F18: 0.002 | G18: =IF(Рецепты[[#This Row],[%]]*1000>0,Рецепты[[#This Row],[%]]*1000,"") -> 2 | H18: =IFERROR(VLOOKUP(Рецепты[[#This Row],[Состав]],Ингредиенты!A:I,3,0)*Рецепты[[#This Row],[г]],"") -> 1.496 | I18: =СводРецепт!$A$1 -> 1000 | J18: =Рецепты[[#This Row],[%]]*Рецепты[[#This Row],[Масса]] -> 2 | K18: =Рецепты[[#This Row],[Вес ингр-тов]]*VLOOKUP(Рецепты[[#This Row],[Состав]],Ингредиенты[],3,FALSE) -> 1.496 | L18: =IF(VLOOKUP(Рецепты[[#This Row],[Состав]],Ингредиенты[],4,0)="Основа",VLOOKUP(Рецепты[[#This Row],[Способ]],Способ[],2,0),0%) -> 0 | M18: =VLOOKUP(Рецепты[[#This Row],[Способ]],Способ[],3,0) -> 0.7 | N18: =Рецепты[[#This Row],[р]]*100%/(100%-Рецепты[[#This Row],[Потери, %]])+Рецепты[[#This Row],[Маржа]]*(Рецепты[[#This Row],[р]]*100%)/(100%-Рецепты[[#This Row],[Потери, %]]) -> 2.5432 | O18: =Рецепты[[#This Row],[Цена за 1 кг]]-(Рецепты[[#This Row],[р]]*100%/(100%-Рецепты[[#This Row],[Потери, %]])) -> 1.0472 | P18: https://www.youtube.com/watch?v=5gWsIsh4dpM | Q18: D:\Video\Колбаса_рецепты\Докторская колбаса ГОСТ 23670-79 в домашних условиях.mp19 | R18: =VLOOKUP(Рецепты[[#This Row],[Состав]],Ингредиенты[],9,0) -> Да
A19: Докторская | B19: =B17 -> Колбаса | C19: =C17 -> Вареное | D19: Кардамон | E19: =VLOOKUP(Рецепты[[#This Row],[Состав]],Ингредиенты[],2,0) -> Специи | F19: 0.0005 | G19: =IF(Рецепты[[#This Row],[%]]*1000>0,Рецепты[[#This Row],[%]]*1000,"") -> 0.5 | H19: =IFERROR(VLOOKUP(Рецепты[[#This Row],[Состав]],Ингредиенты!A:I,3,0)*Рецепты[[#This Row],[г]],"") -> 0.75666667 | I19: =СводРецепт!$A$1 -> 1000 | J19: =Рецепты[[#This Row],[%]]*Рецепты[[#This Row],[Масса]] -> 0.5 | K19: =Рецепты[[#This Row],[Вес ингр-тов]]*VLOOKUP(Рецепты[[#This Row],[Состав]],Ингредиенты[],3,FALSE) -> 0.75666667 | L19: =IF(VLOOKUP(Рецепты[[#This Row],[Состав]],Ингредиенты[],4,0)="Основа",VLOOKUP(Рецепты[[#This Row],[Способ]],Способ[],2,0),0%) -> 0 | M19: =VLOOKUP(Рецепты[[#This Row],[Способ]],Способ[],3,0) -> 0.7 | N19: =Рецепты[[#This Row],[р]]*100%/(100%-Рецепты[[#This Row],[Потери, %]])+Рецепты[[#This Row],[Маржа]]*(Рецепты[[#This Row],[р]]*100%)/(100%-Рецепты[[#This Row],[Потери, %]]) -> 1.2863333 | O19: =Рецепты[[#This Row],[Цена за 1 кг]]-(Рецепты[[#This Row],[р]]*100%/(100%-Рецепты[[#This Row],[Потери, %]])) -> 0.52966667 | P19: https://www.youtube.com/watch?v=5gWsIsh4dpM | Q19: D:\Video\Колбаса_рецепты\Докторская колбаса ГОСТ 23670-79 в домашних условиях.mp19 | R19: =VLOOKUP(Рецепты[[#This Row],[Состав]],Ингредиенты[],9,0) -> Да
A20: Докторская | B20: =B19 -> Колбаса | C20: =C19 -> Вареное | D20: Полиамидная 80 | E20: =VLOOKUP(Рецепты[[#This Row],[Состав]],Ингредиенты[],2,0) -> Оболочка | F20: 0.001 | G20: =IF(Рецепты[[#This Row],[%]]*1000>0,Рецепты[[#This Row],[%]]*1000,"") -> 1 | H20: =IFERROR(VLOOKUP(Рецепты[[#This Row],[Состав]],Ингредиенты!A:I,3,0)*Рецепты[[#This Row],[г]],"") -> 9.7374533 | I20: =СводРецепт!$A$1 -> 1000 | J20: =Рецепты[[#This Row],[%]]*Рецепты[[#This Row],[Масса]] -> 1 | K20: =Рецепты[[#This Row],[Вес ингр-тов]]*VLOOKUP(Рецепты[[#This Row],[Состав]],Ингредиенты[],3,FALSE) -> 9.7374533 | L20: =IF(VLOOKUP(Рецепты[[#This Row],[Состав]],Ингредиенты[],4,0)="Основа",VLOOKUP(Рецепты[[#This Row],[Способ]],Способ[],2,0),0%) -> 0 | M20: =VLOOKUP(Рецепты[[#This Row],[Способ]],Способ[],3,0) -> 0.7 | N20: =Рецепты[[#This Row],[р]]*100%/(100%-Рецепты[[#This Row],[Потери, %]])+Рецепты[[#This Row],[Маржа]]*(Рецепты[[#This Row],[р]]*100%)/(100%-Рецепты[[#This Row],[Потери, %]]) -> 16.553671 | O20: =Рецепты[[#This Row],[Цена за 1 кг]]-(Рецепты[[#This Row],[р]]*100%/(100%-Рецепты[[#This Row],[Потери, %]])) -> 6.8162173 | P20: https://www.youtube.com/watch?v=5gWsIsh4dpM | Q20: D:\Video\Колбаса_рецепты\Докторская колбаса ГОСТ 23670-79 в домашних условиях.mp20 | R20: =VLOOKUP(Рецепты[[#This Row],[Состав]],Ингредиенты[],9,0) -> Да
A21: Куриные Сырные | B21: Сосиски | C21: =C19 -> Вареное | D21: Грудка куриная | E21: =VLOOKUP(Рецепты[[#This Row],[Состав]],Ингредиенты[],2,0) -> Птица | F21: 0.2 | G21: =IF(Рецепты[[#This Row],[%]]*1000>0,Рецепты[[#This Row],[%]]*1000,"") -> 200 | H21: =IFERROR(VLOOKUP(Рецепты[[#This Row],[Состав]],Ингредиенты!A:I,3,0)*Рецепты[[#This Row],[г]],"") -> 55.998 | I21: =СводРецепт!$A$1 -> 1000 | J21: =Рецепты[[#This Row],[%]]*Рецепты[[#This Row],[Масса]] -> 200 | K21: =Рецепты[[#This Row],[Вес ингр-тов]]*VLOOKUP(Рецепты[[#This Row],[Состав]],Ингредиенты[],3,FALSE) -> 55.998 | L21: =IF(VLOOKUP(Рецепты[[#This Row],[Состав]],Ингредиенты[],4,0)="Основа",VLOOKUP(Рецепты[[#This Row],[Способ]],Способ[],2,0),0%) -> 0.15 | M21: =VLOOKUP(Рецепты[[#This Row],[Способ]],Способ[],3,0) -> 0.7 | N21: =Рецепты[[#This Row],[р]]*100%/(100%-Рецепты[[#This Row],[Потери, %]])+Рецепты[[#This Row],[Маржа]]*(Рецепты[[#This Row],[р]]*100%)/(100%-Рецепты[[#This Row],[Потери, %]]) -> 111.996 | O21: =Рецепты[[#This Row],[Цена за 1 кг]]-(Рецепты[[#This Row],[р]]*100%/(100%-Рецепты[[#This Row],[Потери, %]])) -> 46.116 | P21: https://www.youtube.com/watch?v=WJ2KT_frzos&t=16s | Q21: D:\Video\Колбаса_рецепты\Домашние куриные сосиски с твердым сыром.mp4 | R21: =VLOOKUP(Рецепты[[#This Row],[Состав]],Ингредиенты[],9,0) -> Нет
A22: Куриные Сырные | B22: =B21 -> Сосиски | C22: =C21 -> Вареное | D22: Бедра куриные | E22: =VLOOKUP(Рецепты[[#This Row],[Состав]],Ингредиенты[],2,0) -> Птица | F22: 0.6 | G22: =IF(Рецепты[[#This Row],[%]]*1000>0,Рецепты[[#This Row],[%]]*1000,"") -> 600 | H22: =IFERROR(VLOOKUP(Рецепты[[#This Row],[Состав]],Ингредиенты!A:I,3,0)*Рецепты[[#This Row],[г]],"") -> 156.70588 | I22: =СводРецепт!$A$1 -> 1000 | J22: =Рецепты[[#This Row],[%]]*Рецепты[[#This Row],[Масса]] -> 600 | K22: =Рецепты[[#This Row],[Вес ингр-тов]]*VLOOKUP(Рецепты[[#This Row],[Состав]],Ингредиенты[],3,FALSE) -> 156.70588 | L22: =IF(VLOOKUP(Рецепты[[#This Row],[Состав]],Ингредиенты[],4,0)="Основа",VLOOKUP(Рецепты[[#This Row],[Способ]],Способ[],2,0),0%) -> 0.15 | M22: =VLOOKUP(Рецепты[[#This Row],[Способ]],Способ[],3,0) -> 0.7 | N22: =Рецепты[[#This Row],[р]]*100%/(100%-Рецепты[[#This Row],[Потери, %]])+Рецепты[[#This Row],[Маржа]]*(Рецепты[[#This Row],[р]]*100%)/(100%-Рецепты[[#This Row],[Потери, %]]) -> 313.41176 | O22: =Рецепты[[#This Row],[Цена за 1 кг]]-(Рецепты[[#This Row],[р]]*100%/(100%-Рецепты[[#This Row],[Потери, %]])) -> 129.0519 | P22: https://www.youtube.com/watch?v=WJ2KT_frzos&t=16s | Q22: D:\Video\Колбаса_рецепты\Домашние куриные сосиски с твердым сыром.mp5 | R22: =VLOOKUP(Рецепты[[#This Row],[Состав]],Ингредиенты[],9,0) -> Нет
A23: Куриные Сырные | B23: =B22 -> Сосиски | C23: =C22 -> Вареное | D23: Сыр российский | E23: =VLOOKUP(Рецепты[[#This Row],[Состав]],Ингредиенты[],2,0) -> Добавки | F23: 0.2 | G23: =IF(Рецепты[[#This Row],[%]]*1000>0,Рецепты[[#This Row],[%]]*1000,"") -> 200 | H23: =IFERROR(VLOOKUP(Рецепты[[#This Row],[Состав]],Ингредиенты!A:I,3,0)*Рецепты[[#This Row],[г]],"") -> 159.998 | I23: =СводРецепт!$A$1 -> 1000 | J23: =Рецепты[[#This Row],[%]]*Рецепты[[#This Row],[Масса]] -> 200 | K23: =Рецепты[[#This Row],[Вес ингр-тов]]*VLOOKUP(Рецепты[[#This Row],[Состав]],Ингредиенты[],3,FALSE) -> 159.998 | L23: =IF(VLOOKUP(Рецепты[[#This Row],[Состав]],Ингредиенты[],4,0)="Основа",VLOOKUP(Рецепты[[#This Row],[Способ]],Способ[],2,0),0%) -> 0 | M23: =VLOOKUP(Рецепты[[#This Row],[Способ]],Способ[],3,0) -> 0.7 | N23: =Рецепты[[#This Row],[р]]*100%/(100%-Рецепты[[#This Row],[Потери, %]])+Рецепты[[#This Row],[Маржа]]*(Рецепты[[#This Row],[р]]*100%)/(100%-Рецепты[[#This Row],[Потери, %]]) -> 271.9966 | O23: =Рецепты[[#This Row],[Цена за 1 кг]]-(Рецепты[[#This Row],[р]]*100%/(100%-Рецепты[[#This Row],[Потери, %]])) -> 111.9986 | P23: https://www.youtube.com/watch?v=WJ2KT_frzos&t=16s | Q23: D:\Video\Колбаса_рецепты\Домашние куриные сосиски с твердым сыром.mp6 | R23: =VLOOKUP(Рецепты[[#This Row],[Состав]],Ингредиенты[],9,0) -> Нет
A24: Куриные Сырные | B24: =B23 -> Сосиски | C24: =C23 -> Вареное | D24: Соль пищевая | E24: =VLOOKUP(Рецепты[[#This Row],[Состав]],Ингредиенты[],2,0) -> Специи | F24: 0.008 | G24: =IF(Рецепты[[#This Row],[%]]*1000>0,Рецепты[[#This Row],[%]]*1000,"") -> 8 | H24: =IFERROR(VLOOKUP(Рецепты[[#This Row],[Состав]],Ингредиенты!A:I,3,0)*Рецепты[[#This Row],[г]],"") -> 0.308 | I24: =СводРецепт!$A$1 -> 1000 | J24: =Рецепты[[#This Row],[%]]*Рецепты[[#This Row],[Масса]] -> 8 | K24: =Рецепты[[#This Row],[Вес ингр-тов]]*VLOOKUP(Рецепты[[#This Row],[Состав]],Ингредиенты[],3,FALSE) -> 0.308 | L24: =IF(VLOOKUP(Рецепты[[#This Row],[Состав]],Ингредиенты[],4,0)="Основа",VLOOKUP(Рецепты[[#This Row],[Способ]],Способ[],2,0),0%) -> 0 | M24: =VLOOKUP(Рецепты[[#This Row],[Способ]],Способ[],3,0) -> 0.7 | N24: =Рецепты[[#This Row],[р]]*100%/(100%-Рецепты[[#This Row],[Потери, %]])+Рецепты[[#This Row],[Маржа]]*(Рецепты[[#This Row],[р]]*100%)/(100%-Рецепты[[#This Row],[Потери, %]]) -> 0.5236 | O24: =Рецепты[[#This Row],[Цена за 1 кг]]-(Рецепты[[#This Row],[р]]*100%/(100%-Рецепты[[#This Row],[Потери, %]])) -> 0.2156 | P24: https://www.youtube.com/watch?v=WJ2KT_frzos&t=16s | Q24: D:\Video\Колбаса_рецепты\Домашние куриные сосиски с твердым сыром.mp7 | R24: =VLOOKUP(Рецепты[[#This Row],[Состав]],Ингредиенты[],9,0) -> Да
A25: Куриные Сырные | B25: =B24 -> Сосиски | C25: =C24 -> Вареное | D25: Соль нитритная | E25: =VLOOKUP(Рецепты[[#This Row],[Состав]],Ингредиенты[],2,0) -> Специи | F25: 0.008 | G25: =IF(Рецепты[[#This Row],[%]]*1000>0,Рецепты[[#This Row],[%]]*1000,"") -> 8 | H25: =IFERROR(VLOOKUP(Рецепты[[#This Row],[Состав]],Ингредиенты!A:I,3,0)*Рецепты[[#This Row],[г]],"") -> 1.024 | I25: =СводРецепт!$A$1 -> 1000 | J25: =Рецепты[[#This Row],[%]]*Рецепты[[#This Row],[Масса]] -> 8 | K25: =Рецепты[[#This Row],[Вес ингр-тов]]*VLOOKUP(Рецепты[[#This Row],[Состав]],Ингредиенты[],3,FALSE) -> 1.024 | L25: =IF(VLOOKUP(Рецепты[[#This Row],[Состав]],Ингредиенты[],4,0)="Основа",VLOOKUP(Рецепты[[#This Row],[Способ]],Способ[],2,0),0%) -> 0 | M25: =VLOOKUP(Рецепты[[#This Row],[Способ]],Способ[],3,0) -> 0.7 | N25: =Рецепты[[#This Row],[р]]*100%/(100%-Рецепты[[#This Row],[Потери, %]])+Рецепты[[#This Row],[Маржа]]*(Рецепты[[#This Row],[р]]*100%)/(100%-Рецепты[[#This Row],[Потери, %]]) -> 1.7408 | O25: =Рецепты[[#This Row],[Цена за 1 кг]]-(Рецепты[[#This Row],[р]]*100%/(100%-Рецепты[[#This Row],[Потери, %]])) -> 0.7168 | P25: https://www.youtube.com/watch?v=WJ2KT_frzos&t=16s | Q25: D:\Video\Колбаса_рецепты\Домашние куриные сосиски с твердым сыром.mp8 | R25: =VLOOKUP(Рецепты[[#This Row],[Состав]],Ингредиенты[],9,0) -> Да
A26: Куриные Сырные | B26: =B25 -> Сосиски | C26: =C25 -> Вареное | D26: Сахар | E26: =VLOOKUP(Рецепты[[#This Row],[Состав]],Ингредиенты[],2,0) -> Специи | F26: 0.001 | G26: =IF(Рецепты[[#This Row],[%]]*1000>0,Рецепты[[#This Row],[%]]*1000,"") -> 1 | H26: =IFERROR(VLOOKUP(Рецепты[[#This Row],[Состав]],Ингредиенты!A:I,3,0)*Рецепты[[#This Row],[г]],"") -> 0.080882353 | I26: =СводРецепт!$A$1 -> 1000 | J26: =Рецепты[[#This Row],[%]]*Рецепты[[#This Row],[Масса]] -> 1 | K26: =Рецепты[[#This Row],[Вес ингр-тов]]*VLOOKUP(Рецепты[[#This Row],[Состав]],Ингредиенты[],3,FALSE) -> 0.080882353 | L26: =IF(VLOOKUP(Рецепты[[#This Row],[Состав]],Ингредиенты[],4,0)="Основа",VLOOKUP(Рецепты[[#This Row],[Способ]],Способ[],2,0),0%) -> 0 | M26: =VLOOKUP(Рецепты[[#This Row],[Способ]],Способ[],3,0) -> 0.7 | N26: =Рецепты[[#This Row],[р]]*100%/(100%-Рецепты[[#This Row],[Потери, %]])+Рецепты[[#This Row],[Маржа]]*(Рецепты[[#This Row],[р]]*100%)/(100%-Рецепты[[#This Row],[Потери, %]]) -> 0.1375 | O26: =Рецепты[[#This Row],[Цена за 1 кг]]-(Рецепты[[#This Row],[р]]*100%/(100%-Рецепты[[#This Row],[Потери, %]])) -> 0.056617647 | P26: https://www.youtube.com/watch?v=WJ2KT_frzos&t=16s | Q26: D:\Video\Колбаса_рецепты\Домашние куриные сосиски с твердым сыром.mp9 | R26: =VLOOKUP(Рецепты[[#This Row],[Состав]],Ингредиенты[],9,0) -> Да
A27: Куриные Сырные | B27: =B26 -> Сосиски | C27: =C26 -> Вареное | D27: Перец черный молотый | E27: =VLOOKUP(Рецепты[[#This Row],[Состав]],Ингредиенты[],2,0) -> Специи | F27: 0.001 | G27: =IF(Рецепты[[#This Row],[%]]*1000>0,Рецепты[[#This Row],[%]]*1000,"") -> 1 | H27: =IFERROR(VLOOKUP(Рецепты[[#This Row],[Состав]],Ингредиенты!A:I,3,0)*Рецепты[[#This Row],[г]],"") -> 1.0945455 | I27: =СводРецепт!$A$1 -> 1000 | J27: =Рецепты[[#This Row],[%]]*Рецепты[[#This Row],[Масса]] -> 1 | K27: =Рецепты[[#This Row],[Вес ингр-тов]]*VLOOKUP(Рецепты[[#This Row],[Состав]],Ингредиенты[],3,FALSE) -> 1.0945455 | L27: =IF(VLOOKUP(Рецепты[[#This Row],[Состав]],Ингредиенты[],4,0)="Основа",VLOOKUP(Рецепты[[#This Row],[Способ]],Способ[],2,0),0%) -> 0 | M27: =VLOOKUP(Рецепты[[#This Row],[Способ]],Способ[],3,0) -> 0.7 | N27: =Рецепты[[#This Row],[р]]*100%/(100%-Рецепты[[#This Row],[Потери, %]])+Рецепты[[#This Row],[Маржа]]*(Рецепты[[#This Row],[р]]*100%)/(100%-Рецепты[[#This Row],[Потери, %]]) -> 1.8607273 | O27: =Рецепты[[#This Row],[Цена за 1 кг]]-(Рецепты[[#This Row],[р]]*100%/(100%-Рецепты[[#This Row],[Потери, %]])) -> 0.76618182 | P27: https://www.youtube.com/watch?v=WJ2KT_frzos&t=16s | Q27: D:\Video\Колбаса_рецепты\Домашние куриные сосиски с твердым сыром.mp10 | R27: =VLOOKUP(Рецепты[[#This Row],[Состав]],Ингредиенты[],9,0) -> Да
A28: Куриные Сырные | B28: =B27 -> Сосиски | C28: =C27 -> Вареное | D28: Мускатный орех | E28: =VLOOKUP(Рецепты[[#This Row],[Состав]],Ингредиенты[],2,0) -> Специи | F28: 0.0005 | G28: =IF(Рецепты[[#This Row],[%]]*1000>0,Рецепты[[#This Row],[%]]*1000,"") -> 0.5 | H28: =IFERROR(VLOOKUP(Рецепты[[#This Row],[Состав]],Ингредиенты!A:I,3,0)*Рецепты[[#This Row],[г]],"") -> 1.0386364 | I28: =СводРецепт!$A$1 -> 1000 | J28: =Рецепты[[#This Row],[%]]*Рецепты[[#This Row],[Масса]] -> 0.5 | K28: =Рецепты[[#This Row],[Вес ингр-тов]]*VLOOKUP(Рецепты[[#This Row],[Состав]],Ингредиенты[],3,FALSE) -> 1.0386364 | L28: =IF(VLOOKUP(Рецепты[[#This Row],[Состав]],Ингредиенты[],4,0)="Основа",VLOOKUP(Рецепты[[#This Row],[Способ]],Способ[],2,0),0%) -> 0 | M28: =VLOOKUP(Рецепты[[#This Row],[Способ]],Способ[],3,0) -> 0.7 | N28: =Рецепты[[#This Row],[р]]*100%/(100%-Рецепты[[#This Row],[Потери, %]])+Рецепты[[#This Row],[Маржа]]*(Рецепты[[#This Row],[р]]*100%)/(100%-Рецепты[[#This Row],[Потери, %]]) -> 1.7656818 | O28: =Рецепты[[#This Row],[Цена за 1 кг]]-(Рецепты[[#This Row],[р]]*100%/(100%-Рецепты[[#This Row],[Потери, %]])) -> 0.72704545 | P28: https://www.youtube.com/watch?v=WJ2KT_frzos&t=16s | Q28: D:\Video\Колбаса_рецепты\Домашние куриные сосиски с твердым сыром.mp11 | R28: =VLOOKUP(Рецепты[[#This Row],[Состав]],Ингредиенты[],9,0) -> Да
A29: Куриные Сырные | B29: =B28 -> Сосиски | C29: =C28 -> Вареное | D29: Сливки | E29: =VLOOKUP(Рецепты[[#This Row],[Состав]],Ингредиенты[],2,0) -> Добавки | F29: 0.15 | G29: =IF(Рецепты[[#This Row],[%]]*1000>0,Рецепты[[#This Row],[%]]*1000,"") -> 150 | H29: =IFERROR(VLOOKUP(Рецепты[[#This Row],[Состав]],Ингредиенты!A:I,3,0)*Рецепты[[#This Row],[г]],"") -> 75.9 | I29: =СводРецепт!$A$1 -> 1000 | J29: =Рецепты[[#This Row],[%]]*Рецепты[[#This Row],[Масса]] -> 150 | K29: =Рецепты[[#This Row],[Вес ингр-тов]]*VLOOKUP(Рецепты[[#This Row],[Состав]],Ингредиенты[],3,FALSE) -> 75.9 | L29: =IF(VLOOKUP(Рецепты[[#This Row],[Состав]],Ингредиенты[],4,0)="Основа",VLOOKUP(Рецепты[[#This Row],[Способ]],Способ[],2,0),0%) -> 0 | M29: =VLOOKUP(Рецепты[[#This Row],[Способ]],Способ[],3,0) -> 0.7 | N29: =Рецепты[[#This Row],[р]]*100%/(100%-Рецепты[[#This Row],[Потери, %]])+Рецепты[[#This Row],[Маржа]]*(Рецепты[[#This Row],[р]]*100%)/(100%-Рецепты[[#This Row],[Потери, %]]) -> 129.03 | O29: =Рецепты[[#This Row],[Цена за 1 кг]]-(Рецепты[[#This Row],[р]]*100%/(100%-Рецепты[[#This Row],[Потери, %]])) -> 53.13 | P29: https://www.youtube.com/watch?v=WJ2KT_frzos&t=16s | Q29: D:\Video\Колбаса_рецепты\Домашние куриные сосиски с твердым сыром.mp12 | R29: =VLOOKUP(Рецепты[[#This Row],[Состав]],Ингредиенты[],9,0) -> Да
A30: Куриные Сырные | B30: =B29 -> Сосиски | C30: =C29 -> Вареное | D30: Полиамидная сосисочная | E30: =VLOOKUP(Рецепты[[#This Row],[Состав]],Ингредиенты[],2,0) -> Оболочка | F30: 0.001 | G30: =IF(Рецепты[[#This Row],[%]]*1000>0,Рецепты[[#This Row],[%]]*1000,"") -> 1 | H30: =IFERROR(VLOOKUP(Рецепты[[#This Row],[Состав]],Ингредиенты!A:I,3,0)*Рецепты[[#This Row],[г]],"") -> 15.40718 | I30: =СводРецепт!$A$1 -> 1000 | J30: =Рецепты[[#This Row],[%]]*Рецепты[[#This Row],[Масса]] -> 1 | K30: =Рецепты[[#This Row],[Вес ингр-тов]]*VLOOKUP(Рецепты[[#This Row],[Состав]],Ингредиенты[],3,FALSE) -> 15.40718 | L30: =IF(VLOOKUP(Рецепты[[#This Row],[Состав]],Ингредиенты[],4,0)="Основа",VLOOKUP(Рецепты[[#This Row],[Способ]],Способ[],2,0),0%) -> 0 | M30: =VLOOKUP(Рецепты[[#This Row],[Способ]],Способ[],3,0) -> 0.7 | N30: =Рецепты[[#This Row],[р]]*100%/(100%-Рецепты[[#This Row],[Потери, %]])+Рецепты[[#This Row],[Маржа]]*(Рецепты[[#This Row],[р]]*100%)/(100%-Рецепты[[#This Row],[Потери, %]]) -> 26.192206 | O30: =Рецепты[[#This Row],[Цена за 1 кг]]-(Рецепты[[#This Row],[р]]*100%/(100%-Рецепты[[#This Row],[Потери, %]])) -> 10.785026 | P30: https://www.youtube.com/watch?v=WJ2KT_frzos&t=16s | Q30: D:\Video\Колбаса_рецепты\Домашние куриные сосиски с твердым сыром.mp13 | R30: =VLOOKUP(Рецепты[[#This Row],[Состав]],Ингредиенты[],9,0) -> Да
A31: Сардельки Свиные | B31: =B30 -> Сосиски | C31: =C29 -> Вареное | D31: Лопатка свиная | E31: =VLOOKUP(Рецепты[[#This Row],[Состав]],Ингредиенты[],2,0) -> Свинина | F31: 1 | G31: =IF(Рецепты[[#This Row],[%]]*1000>0,Рецепты[[#This Row],[%]]*1000,"") -> 1000 | H31: =IFERROR(VLOOKUP(Рецепты[[#This Row],[Состав]],Ингредиенты!A:I,3,0)*Рецепты[[#This Row],[г]],"") -> 369 | I31: =СводРецепт!$A$1 -> 1000 | J31: =Рецепты[[#This Row],[%]]*Рецепты[[#This Row],[Масса]] -> 1000 | K31: =Рецепты[[#This Row],[Вес ингр-тов]]*VLOOKUP(Рецепты[[#This Row],[Состав]],Ингредиенты[],3,FALSE) -> 369 | L31: =IF(VLOOKUP(Рецепты[[#This Row],[Состав]],Ингредиенты[],4,0)="Основа",VLOOKUP(Рецепты[[#This Row],[Способ]],Способ[],2,0),0%) -> 0.15 | M31: =VLOOKUP(Рецепты[[#This Row],[Способ]],Способ[],3,0) -> 0.7 | N31: =Рецепты[[#This Row],[р]]*100%/(100%-Рецепты[[#This Row],[Потери, %]])+Рецепты[[#This Row],[Маржа]]*(Рецепты[[#This Row],[р]]*100%)/(100%-Рецепты[[#This Row],[Потери, %]]) -> 738 | O31: =Рецепты[[#This Row],[Цена за 1 кг]]-(Рецепты[[#This Row],[р]]*100%/(100%-Рецепты[[#This Row],[Потери, %]])) -> 303.88235 | P31: https://www.youtube.com/watch?v=Mu_glCpe-Y8 | Q31: D:\Video\Колбаса_рецепты\Сочные домашние сардельки Кнакеры. Как сделать корочку, чтобы сардельки ''хрупали'' при укусе..mp4 | R31: =VLOOKUP(Рецепты[[#This Row],[Состав]],Ингредиенты[],9,0) -> Нет
A32: Сардельки Свиные | B32: =B31 -> Сосиски | C32: =C31 -> Вареное | D32: Вода | E32: =VLOOKUP(Рецепты[[#This Row],[Состав]],Ингредиенты[],2,0) -> Добавки | F32: 0.3 | G32: =IF(Рецепты[[#This Row],[%]]*1000>0,Рецепты[[#This Row],[%]]*1000,"") -> 300 | H32: =IFERROR(VLOOKUP(Рецепты[[#This Row],[Состав]],Ингредиенты!A:I,3,0)*Рецепты[[#This Row],[г]],"") -> 0.3 | I32: =СводРецепт!$A$1 -> 1000 | J32: =Рецепты[[#This Row],[%]]*Рецепты[[#This Row],[Масса]] -> 300 | K32: =Рецепты[[#This Row],[Вес ингр-тов]]*VLOOKUP(Рецепты[[#This Row],[Состав]],Ингредиенты[],3,FALSE) -> 0.3 | L32: =IF(VLOOKUP(Рецепты[[#This Row],[Состав]],Ингредиенты[],4,0)="Основа",VLOOKUP(Рецепты[[#This Row],[Способ]],Способ[],2,0),0%) -> 0 | M32: =VLOOKUP(Рецепты[[#This Row],[Способ]],Способ[],3,0) -> 0.7 | N32: =Рецепты[[#This Row],[р]]*100%/(100%-Рецепты[[#This Row],[Потери, %]])+Рецепты[[#This Row],[Маржа]]*(Рецепты[[#This Row],[р]]*100%)/(100%-Рецепты[[#This Row],[Потери, %]]) -> 0.51 | O32: =Рецепты[[#This Row],[Цена за 1 кг]]-(Рецепты[[#This Row],[р]]*100%/(100%-Рецепты[[#This Row],[Потери, %]])) -> 0.21 | P32: https://www.youtube.com/watch?v=Mu_glCpe-Y8 | Q32: D:\Video\Колбаса_рецепты\Сочные домашние сардельки Кнакеры. Как сделать корочку, чтобы сардельки ''хрупали'' при укусе..mp6 | R32: =VLOOKUP(Рецепты[[#This Row],[Состав]],Ингредиенты[],9,0) -> Да
A33: Сардельки Свиные | B33: =B32 -> Сосиски | C33: =C32 -> Вареное | D33: Соль пищевая | E33: =VLOOKUP(Рецепты[[#This Row],[Состав]],Ингредиенты[],2,0) -> Специи | F33: 0.01 | G33: =IF(Рецепты[[#This Row],[%]]*1000>0,Рецепты[[#This Row],[%]]*1000,"") -> 10 | H33: =IFERROR(VLOOKUP(Рецепты[[#This Row],[Состав]],Ингредиенты!A:I,3,0)*Рецепты[[#This Row],[г]],"") -> 0.385 | I33: =СводРецепт!$A$1 -> 1000 | J33: =Рецепты[[#This Row],[%]]*Рецепты[[#This Row],[Масса]] -> 10 | K33: =Рецепты[[#This Row],[Вес ингр-тов]]*VLOOKUP(Рецепты[[#This Row],[Состав]],Ингредиенты[],3,FALSE) -> 0.385 | L33: =IF(VLOOKUP(Рецепты[[#This Row],[Состав]],Ингредиенты[],4,0)="Основа",VLOOKUP(Рецепты[[#This Row],[Способ]],Способ[],2,0),0%) -> 0 | M33: =VLOOKUP(Рецепты[[#This Row],[Способ]],Способ[],3,0) -> 0.7 | N33: =Рецепты[[#This Row],[р]]*100%/(100%-Рецепты[[#This Row],[Потери, %]])+Рецепты[[#This Row],[Маржа]]*(Рецепты[[#This Row],[р]]*100%)/(100%-Рецепты[[#This Row],[Потери, %]]) -> 0.6545 | O33: =Рецепты[[#This Row],[Цена за 1 кг]]-(Рецепты[[#This Row],[р]]*100%/(100%-Рецепты[[#This Row],[Потери, %]])) -> 0.2695 | P33: https://www.youtube.com/watch?v=Mu_glCpe-Y8 | Q33: D:\Video\Колбаса_рецепты\Сочные домашние сардельки Кнакеры. Как сделать корочку, чтобы сардельки ''хрупали'' при укусе..mp7 | R33: =VLOOKUP(Рецепты[[#This Row],[Состав]],Ингредиенты[],9,0) -> Да
A34: Сардельки Свиные | B34: =B33 -> Сосиски | C34: =C33 -> Вареное | D34: Соль нитритная | E34: =VLOOKUP(Рецепты[[#This Row],[Состав]],Ингредиенты[],2,0) -> Специи | F34: 0.01 | G34: =IF(Рецепты[[#This Row],[%]]*1000>0,Рецепты[[#This Row],[%]]*1000,"") -> 10 | H34: =IFERROR(VLOOKUP(Рецепты[[#This Row],[Состав]],Ингредиенты!A:I,3,0)*Рецепты[[#This Row],[г]],"") -> 1.28 | I34: =СводРецепт!$A$1 -> 1000 | J34: =Рецепты[[#This Row],[%]]*Рецепты[[#This Row],[Масса]] -> 10 | K34: =Рецепты[[#This Row],[Вес ингр-тов]]*VLOOKUP(Рецепты[[#This Row],[Состав]],Ингредиенты[],3,FALSE) -> 1.28 | L34: =IF(VLOOKUP(Рецепты[[#This Row],[Состав]],Ингредиенты[],4,0)="Основа",VLOOKUP(Рецепты[[#This Row],[Способ]],Способ[],2,0),0%) -> 0 | M34: =VLOOKUP(Рецепты[[#This Row],[Способ]],Способ[],3,0) -> 0.7 | N34: =Рецепты[[#This Row],[р]]*100%/(100%-Рецепты[[#This Row],[Потери, %]])+Рецепты[[#This Row],[Маржа]]*(Рецепты[[#This Row],[р]]*100%)/(100%-Рецепты[[#This Row],[Потери, %]]) -> 2.176 | O34: =Рецепты[[#This Row],[Цена за 1 кг]]-(Рецепты[[#This Row],[р]]*100%/(100%-Рецепты[[#This Row],[Потери, %]])) -> 0.896 | P34: https://www.youtube.com/watch?v=Mu_glCpe-Y8 | Q34: D:\Video\Колбаса_рецепты\Сочные домашние сардельки Кнакеры. Как сделать корочку, чтобы сардельки ''хрупали'' при укусе..mp8 | R34: =VLOOKUP(Рецепты[[#This Row],[Состав]],Ингредиенты[],9,0) -> Да
A35: Сардельки Свиные | B35: =B34 -> Сосиски | C35: =C34 -> Вареное | D35: Сахар | E35: =VLOOKUP(Рецепты[[#This Row],[Состав]],Ингредиенты[],2,0) -> Специи | F35: 0.002 | G35: =IF(Рецепты[[#This Row],[%]]*1000>0,Рецепты[[#This Row],[%]]*1000,"") -> 2 | H35: =IFERROR(VLOOKUP(Рецепты[[#This Row],[Состав]],Ингредиенты!A:I,3,0)*Рецепты[[#This Row],[г]],"") -> 0.16176471 | I35: =СводРецепт!$A$1 -> 1000 | J35: =Рецепты[[#This Row],[%]]*Рецепты[[#This Row],[Масса]] -> 2 | K35: =Рецепты[[#This Row],[Вес ингр-тов]]*VLOOKUP(Рецепты[[#This Row],[Состав]],Ингредиенты[],3,FALSE) -> 0.16176471 | L35: =IF(VLOOKUP(Рецепты[[#This Row],[Состав]],Ингредиенты[],4,0)="Основа",VLOOKUP(Рецепты[[#This Row],[Способ]],Способ[],2,0),0%) -> 0 | M35: =VLOOKUP(Рецепты[[#This Row],[Способ]],Способ[],3,0) -> 0.7 | N35: =Рецепты[[#This Row],[р]]*100%/(100%-Рецепты[[#This Row],[Потери, %]])+Рецепты[[#This Row],[Маржа]]*(Рецепты[[#This Row],[р]]*100%)/(100%-Рецепты[[#This Row],[Потери, %]]) -> 0.275 | O35: =Рецепты[[#This Row],[Цена за 1 кг]]-(Рецепты[[#This Row],[р]]*100%/(100%-Рецепты[[#This Row],[Потери, %]])) -> 0.11323529 | P35: https://www.youtube.com/watch?v=Mu_glCpe-Y8 | Q35: D:\Video\Колбаса_рецепты\Сочные домашние сардельки Кнакеры. Как сделать корочку, чтобы сардельки ''хрупали'' при укусе..mp9 | R35: =VLOOKUP(Рецепты[[#This Row],[Состав]],Ингредиенты[],9,0) -> Да
A36: Сардельки Свиные | B36: =B35 -> Сосиски | C36: =C35 -> Вареное | D36: Перец черный молотый | E36: =VLOOKUP(Рецепты[[#This Row],[Состав]],Ингредиенты[],2,0) -> Специи | F36: 0.0013 | G36: =IF(Рецепты[[#This Row],[%]]*1000>0,Рецепты[[#This Row],[%]]*1000,"") -> 1.3 | H36: =IFERROR(VLOOKUP(Рецепты[[#This Row],[Состав]],Ингредиенты!A:I,3,0)*Рецепты[[#This Row],[г]],"") -> 1.4229091 | I36: =СводРецепт!$A$1 -> 1000 | J36: =Рецепты[[#This Row],[%]]*Рецепты[[#This Row],[Масса]] -> 1.3 | K36: =Рецепты[[#This Row],[Вес ингр-тов]]*VLOOKUP(Рецепты[[#This Row],[Состав]],Ингредиенты[],3,FALSE) -> 1.4229091 | L36: =IF(VLOOKUP(Рецепты[[#This Row],[Состав]],Ингредиенты[],4,0)="Основа",VLOOKUP(Рецепты[[#This Row],[Способ]],Способ[],2,0),0%) -> 0 | M36: =VLOOKUP(Рецепты[[#This Row],[Способ]],Способ[],3,0) -> 0.7 | N36: =Рецепты[[#This Row],[р]]*100%/(100%-Рецепты[[#This Row],[Потери, %]])+Рецепты[[#This Row],[Маржа]]*(Рецепты[[#This Row],[р]]*100%)/(100%-Рецепты[[#This Row],[Потери, %]]) -> 2.4189455 | O36: =Рецепты[[#This Row],[Цена за 1 кг]]-(Рецепты[[#This Row],[р]]*100%/(100%-Рецепты[[#This Row],[Потери, %]])) -> 0.99603636 | P36: https://www.youtube.com/watch?v=Mu_glCpe-Y8 | Q36: D:\Video\Колбаса_рецепты\Сочные домашние сардельки Кнакеры. Как сделать корочку, чтобы сардельки ''хрупали'' при укусе..mp10 | R36: =VLOOKUP(Рецепты[[#This Row],[Состав]],Ингредиенты[],9,0) -> Да
A37: Сардельки Свиные | B37: =B36 -> Сосиски | C37: =C36 -> Вареное | D37: Кориандр | E37: =VLOOKUP(Рецепты[[#This Row],[Состав]],Ингредиенты[],2,0) -> Специи | F37: 0.0013 | G37: =IF(Рецепты[[#This Row],[%]]*1000>0,Рецепты[[#This Row],[%]]*1000,"") -> 1.3 | H37: =IFERROR(VLOOKUP(Рецепты[[#This Row],[Состав]],Ингредиенты!A:I,3,0)*Рецепты[[#This Row],[г]],"") -> 0.65288889 | I37: =СводРецепт!$A$1 -> 1000 | J37: =Рецепты[[#This Row],[%]]*Рецепты[[#This Row],[Масса]] -> 1.3 | K37: =Рецепты[[#This Row],[Вес ингр-тов]]*VLOOKUP(Рецепты[[#This Row],[Состав]],Ингредиенты[],3,FALSE) -> 0.65288889 | L37: =IF(VLOOKUP(Рецепты[[#This Row],[Состав]],Ингредиенты[],4,0)="Основа",VLOOKUP(Рецепты[[#This Row],[Способ]],Способ[],2,0),0%) -> 0 | M37: =VLOOKUP(Рецепты[[#This Row],[Способ]],Способ[],3,0) -> 0.7 | N37: =Рецепты[[#This Row],[р]]*100%/(100%-Рецепты[[#This Row],[Потери, %]])+Рецепты[[#This Row],[Маржа]]*(Рецепты[[#This Row],[р]]*100%)/(100%-Рецепты[[#This Row],[Потери, %]]) -> 1.1099111 | O37: =Рецепты[[#This Row],[Цена за 1 кг]]-(Рецепты[[#This Row],[р]]*100%/(100%-Рецепты[[#This Row],[Потери, %]])) -> 0.45702222 | P37: https://www.youtube.com/watch?v=Mu_glCpe-Y8 | Q37: D:\Video\Колбаса_рецепты\Сочные домашние сардельки Кнакеры. Как сделать корочку, чтобы сардельки ''хрупали'' при укусе..mp11 | R37: =VLOOKUP(Рецепты[[#This Row],[Состав]],Ингредиенты[],9,0) -> Да
A38: Сардельки Свиные | B38: =B37 -> Сосиски | C38: =C37 -> Вареное | D38: Фосфат | E38: =VLOOKUP(Рецепты[[#This Row],[Состав]],Ингредиенты[],2,0) -> Специи | F38: 0.003 | G38: =IF(Рецепты[[#This Row],[%]]*1000>0,Рецепты[[#This Row],[%]]*1000,"") -> 3 | H38: =IFERROR(VLOOKUP(Рецепты[[#This Row],[Состав]],Ингредиенты!A:I,3,0)*Рецепты[[#This Row],[г]],"") -> 2.244 | I38: =СводРецепт!$A$1 -> 1000 | J38: =Рецепты[[#This Row],[%]]*Рецепты[[#This Row],[Масса]] -> 3 | K38: =Рецепты[[#This Row],[Вес ингр-тов]]*VLOOKUP(Рецепты[[#This Row],[Состав]],Ингредиенты[],3,FALSE) -> 2.244 | L38: =IF(VLOOKUP(Рецепты[[#This Row],[Состав]],Ингредиенты[],4,0)="Основа",VLOOKUP(Рецепты[[#This Row],[Способ]],Способ[],2,0),0%) -> 0 | M38: =VLOOKUP(Рецепты[[#This Row],[Способ]],Способ[],3,0) -> 0.7 | N38: =Рецепты[[#This Row],[р]]*100%/(100%-Рецепты[[#This Row],[Потери, %]])+Рецепты[[#This Row],[Маржа]]*(Рецепты[[#This Row],[р]]*100%)/(100%-Рецепты[[#This Row],[Потери, %]]) -> 3.8148 | O38: =Рецепты[[#This Row],[Цена за 1 кг]]-(Рецепты[[#This Row],[р]]*100%/(100%-Рецепты[[#This Row],[Потери, %]])) -> 1.5708 | P38: https://www.youtube.com/watch?v=Mu_glCpe-Y8 | Q38: D:\Video\Колбаса_рецепты\Сочные домашние сардельки Кнакеры. Как сделать корочку, чтобы сардельки ''хрупали'' при укусе..mp12 | R38: =VLOOKUP(Рецепты[[#This Row],[Состав]],Ингредиенты[],9,0) -> Да
A39: Сардельки Свиные | B39: =B38 -> Сосиски | C39: =C38 -> Вареное | D39: Чеснок сушеный | E39: =VLOOKUP(Рецепты[[#This Row],[Состав]],Ингредиенты[],2,0) -> Специи | F39: 0.0006 | G39: =IF(Рецепты[[#This Row],[%]]*1000>0,Рецепты[[#This Row],[%]]*1000,"") -> 0.6 | H39: =IFERROR(VLOOKUP(Рецепты[[#This Row],[Состав]],Ингредиенты!A:I,3,0)*Рецепты[[#This Row],[г]],"") -> 0.527 | I39: =СводРецепт!$A$1 -> 1000 | J39: =Рецепты[[#This Row],[%]]*Рецепты[[#This Row],[Масса]] -> 0.6 | K39: =Рецепты[[#This Row],[Вес ингр-тов]]*VLOOKUP(Рецепты[[#This Row],[Состав]],Ингредиенты[],3,FALSE) -> 0.527 | L39: =IF(VLOOKUP(Рецепты[[#This Row],[Состав]],Ингредиенты[],4,0)="Основа",VLOOKUP(Рецепты[[#This Row],[Способ]],Способ[],2,0),0%) -> 0 | M39: =VLOOKUP(Рецепты[[#This Row],[Способ]],Способ[],3,0) -> 0.7 | N39: =Рецепты[[#This Row],[р]]*100%/(100%-Рецепты[[#This Row],[Потери, %]])+Рецепты[[#This Row],[Маржа]]*(Рецепты[[#This Row],[р]]*100%)/(100%-Рецепты[[#This Row],[Потери, %]]) -> 0.8959 | O39: =Рецепты[[#This Row],[Цена за 1 кг]]-(Рецепты[[#This Row],[р]]*100%/(100%-Рецепты[[#This Row],[Потери, %]])) -> 0.3689 | P39: https://www.youtube.com/watch?v=Mu_glCpe-Y8 | Q39: D:\Video\Колбаса_рецепты\Сочные домашние сардельки Кнакеры. Как сделать корочку, чтобы сардельки ''хрупали'' при укусе..mp13 | R39: =VLOOKUP(Рецепты[[#This Row],[Состав]],Ингредиенты[],9,0) -> Да
A40: Сардельки Свиные | B40: =B39 -> Сосиски | C40: =C39 -> Вареное | D40: Свиная черева 32/34 | E40: =VLOOKUP(Рецепты[[#This Row],[Состав]],Ингредиенты[],2,0) -> Оболочка | F40: 0.001 | G40: =IF(Рецепты[[#This Row],[%]]*1000>0,Рецепты[[#This Row],[%]]*1000,"") -> 1 | H40: =IFERROR(VLOOKUP(Рецепты[[#This Row],[Состав]],Ингредиенты!A:I,3,0)*Рецепты[[#This Row],[г]],"") -> 39.348206 | I40: =СводРецепт!$A$1 -> 1000 | J40: =Рецепты[[#This Row],[%]]*Рецепты[[#This Row],[Масса]] -> 1 | K40: =Рецепты[[#This Row],[Вес ингр-тов]]*VLOOKUP(Рецепты[[#This Row],[Состав]],Ингредиенты[],3,FALSE) -> 39.348206 | L40: =IF(VLOOKUP(Рецепты[[#This Row],[Состав]],Ингредиенты[],4,0)="Основа",VLOOKUP(Рецепты[[#This Row],[Способ]],Способ[],2,0),0%) -> 0 | M40: =VLOOKUP(Рецепты[[#This Row],[Способ]],Способ[],3,0) -> 0.7 | N40: =Рецепты[[#This Row],[р]]*100%/(100%-Рецепты[[#This Row],[Потери, %]])+Рецепты[[#This Row],[Маржа]]*(Рецепты[[#This Row],[р]]*100%)/(100%-Рецепты[[#This Row],[Потери, %]]) -> 66.891951 | O40: =Рецепты[[#This Row],[Цена за 1 кг]]-(Рецепты[[#This Row],[р]]*100%/(100%-Рецепты[[#This Row],[Потери, %]])) -> 27.543745 | P40: https://www.youtube.com/watch?v=Mu_glCpe-Y8 | Q40: D:\Video\Колбаса_рецепты\Сочные домашние сардельки Кнакеры. Как сделать корочку, чтобы сардельки ''хрупали'' при укусе..mp14 | R40: =VLOOKUP(Рецепты[[#This Row],[Состав]],Ингредиенты[],9,0) -> Нет
A41: Курица ГК | B41: Цельное | C41: ГК | D41: Курица целая | E41: =VLOOKUP(Рецепты[[#This Row],[Состав]],Ингредиенты[],2,0) -> Птица | F41: 1 | G41: =IF(Рецепты[[#This Row],[%]]*1000>0,Рецепты[[#This Row],[%]]*1000,"") -> 1000 | H41: =IFERROR(VLOOKUP(Рецепты[[#This Row],[Состав]],Ингредиенты!A:I,3,0)*Рецепты[[#This Row],[г]],"") -> 200 | I41: =СводРецепт!$A$1 -> 1000 | J41: =Рецепты[[#This Row],[%]]*Рецепты[[#This Row],[Масса]] -> 1000 | K41: =Рецепты[[#This Row],[Вес ингр-тов]]*VLOOKUP(Рецепты[[#This Row],[Состав]],Ингредиенты[],3,FALSE) -> 200 | L41: =IF(VLOOKUP(Рецепты[[#This Row],[Состав]],Ингредиенты[],4,0)="Основа",VLOOKUP(Рецепты[[#This Row],[Способ]],Способ[],2,0),0%) -> 0.15 | M41: =VLOOKUP(Рецепты[[#This Row],[Способ]],Способ[],3,0) -> 0.9 | N41: =Рецепты[[#This Row],[р]]*100%/(100%-Рецепты[[#This Row],[Потери, %]])+Рецепты[[#This Row],[Маржа]]*(Рецепты[[#This Row],[р]]*100%)/(100%-Рецепты[[#This Row],[Потери, %]]) -> 447.05882 | O41: =Рецепты[[#This Row],[Цена за 1 кг]]-(Рецепты[[#This Row],[р]]*100%/(100%-Рецепты[[#This Row],[Потери, %]])) -> 211.76471 | P41: https://www.youtube.com/watch?v=bwqN7FZs5Ds | Q41: D:\Video\Колбаса_рецепты\КУРИЦА горячего копчения в коптильне уэк москит.mp4 | R41: =VLOOKUP(Рецепты[[#This Row],[Состав]],Ингредиенты[],9,0) -> Да
A42: Курица ГК | B42: =B41 -> Цельное | C42: =C41 -> ГК | D42: Вода | E42: =VLOOKUP(Рецепты[[#This Row],[Состав]],Ингредиенты[],2,0) -> Добавки | F42: 0.1 | G42: =IF(Рецепты[[#This Row],[%]]*1000>0,Рецепты[[#This Row],[%]]*1000,"") -> 100 | H42: =IFERROR(VLOOKUP(Рецепты[[#This Row],[Состав]],Ингредиенты!A:I,3,0)*Рецепты[[#This Row],[г]],"") -> 0.1 | I42: =СводРецепт!$A$1 -> 1000 | J42: =Рецепты[[#This Row],[%]]*Рецепты[[#This Row],[Масса]] -> 100 | K42: =Рецепты[[#This Row],[Вес ингр-тов]]*VLOOKUP(Рецепты[[#This Row],[Состав]],Ингредиенты[],3,FALSE) -> 0.1 | L42: =IF(VLOOKUP(Рецепты[[#This Row],[Состав]],Ингредиенты[],4,0)="Основа",VLOOKUP(Рецепты[[#This Row],[Способ]],Способ[],2,0),0%) -> 0 | M42: =VLOOKUP(Рецепты[[#This Row],[Способ]],Способ[],3,0) -> 0.9 | N42: =Рецепты[[#This Row],[р]]*100%/(100%-Рецепты[[#This Row],[Потери, %]])+Рецепты[[#This Row],[Маржа]]*(Рецепты[[#This Row],[р]]*100%)/(100%-Рецепты[[#This Row],[Потери, %]]) -> 0.19 | O42: =Рецепты[[#This Row],[Цена за 1 кг]]-(Рецепты[[#This Row],[р]]*100%/(100%-Рецепты[[#This Row],[Потери, %]])) -> 0.09 | P42: https://www.youtube.com/watch?v=AyC9SVj43Sg | Q42: D:\Video\Колбаса_рецепты\ХИТ!!! Курица копчено-вареная. Как правильно шприцевать и коптить. Как сделать золотистую корочку.mp4 | R42: =VLOOKUP(Рецепты[[#This Row],[Состав]],Ингредиенты[],9,0) -> Да
A43: Курица ГК | B43: =B42 -> Цельное | C43: =C42 -> ГК | D43: Соль пищевая | E43: =VLOOKUP(Рецепты[[#This Row],[Состав]],Ингредиенты[],2,0) -> Специи | F43: 0.009 | G43: =IF(Рецепты[[#This Row],[%]]*1000>0,Рецепты[[#This Row],[%]]*1000,"") -> 9 | H43: =IFERROR(VLOOKUP(Рецепты[[#This Row],[Состав]],Ингредиенты!A:I,3,0)*Рецепты[[#This Row],[г]],"") -> 0.3465 | I43: =СводРецепт!$A$1 -> 1000 | J43: =Рецепты[[#This Row],[%]]*Рецепты[[#This Row],[Масса]] -> 9 | K43: =Рецепты[[#This Row],[Вес ингр-тов]]*VLOOKUP(Рецепты[[#This Row],[Состав]],Ингредиенты[],3,FALSE) -> 0.3465 | L43: =IF(VLOOKUP(Рецепты[[#This Row],[Состав]],Ингредиенты[],4,0)="Основа",VLOOKUP(Рецепты[[#This Row],[Способ]],Способ[],2,0),0%) -> 0 | M43: =VLOOKUP(Рецепты[[#This Row],[Способ]],Способ[],3,0) -> 0.9 | N43: =Рецепты[[#This Row],[р]]*100%/(100%-Рецепты[[#This Row],[Потери, %]])+Рецепты[[#This Row],[Маржа]]*(Рецепты[[#This Row],[р]]*100%)/(100%-Рецепты[[#This Row],[Потери, %]]) -> 0.65835 | O43: =Рецепты[[#This Row],[Цена за 1 кг]]-(Рецепты[[#This Row],[р]]*100%/(100%-Рецепты[[#This Row],[Потери, %]])) -> 0.31185 | P43: https://www.youtube.com/watch?v=AyC9SVj43Sg | Q43: D:\Video\Колбаса_рецепты\ХИТ!!! Курица копчено-вареная. Как правильно шприцевать и коптить. Как сделать золотистую корочку.mp5 | R43: =VLOOKUP(Рецепты[[#This Row],[Состав]],Ингредиенты[],9,0) -> Да
A44: Курица ГК | B44: =B43 -> Цельное | C44: =C43 -> ГК | D44: Соль нитритная | E44: =VLOOKUP(Рецепты[[#This Row],[Состав]],Ингредиенты[],2,0) -> Специи | F44: 0.009 | G44: =IF(Рецепты[[#This Row],[%]]*1000>0,Рецепты[[#This Row],[%]]*1000,"") -> 9 | H44: =IFERROR(VLOOKUP(Рецепты[[#This Row],[Состав]],Ингредиенты!A:I,3,0)*Рецепты[[#This Row],[г]],"") -> 1.152 | I44: =СводРецепт!$A$1 -> 1000 | J44: =Рецепты[[#This Row],[%]]*Рецепты[[#This Row],[Масса]] -> 9 | K44: =Рецепты[[#This Row],[Вес ингр-тов]]*VLOOKUP(Рецепты[[#This Row],[Состав]],Ингредиенты[],3,FALSE) -> 1.152 | L44: =IF(VLOOKUP(Рецепты[[#This Row],[Состав]],Ингредиенты[],4,0)="Основа",VLOOKUP(Рецепты[[#This Row],[Способ]],Способ[],2,0),0%) -> 0 | M44: =VLOOKUP(Рецепты[[#This Row],[Способ]],Способ[],3,0) -> 0.9 | N44: =Рецепты[[#This Row],[р]]*100%/(100%-Рецепты[[#This Row],[Потери, %]])+Рецепты[[#This Row],[Маржа]]*(Рецепты[[#This Row],[р]]*100%)/(100%-Рецепты[[#This Row],[Потери, %]]) -> 2.1888 | O44: =Рецепты[[#This Row],[Цена за 1 кг]]-(Рецепты[[#This Row],[р]]*100%/(100%-Рецепты[[#This Row],[Потери, %]])) -> 1.0368 | P44: https://www.youtube.com/watch?v=AyC9SVj43Sg | Q44: D:\Video\Колбаса_рецепты\ХИТ!!! Курица копчено-вареная. Как правильно шприцевать и коптить. Как сделать золотистую корочку.mp6 | R44: =VLOOKUP(Рецепты[[#This Row],[Состав]],Ингредиенты[],9,0) -> Да
A45: Курица ГК | B45: =B44 -> Цельное | C45: =C44 -> ГК | D45: Сахар | E45: =VLOOKUP(Рецепты[[#This Row],[Состав]],Ингредиенты[],2,0) -> Специи | F45: 0.003 | G45: =IF(Рецепты[[#This Row],[%]]*1000>0,Рецепты[[#This Row],[%]]*1000,"") -> 3 | H45: =IFERROR(VLOOKUP(Рецепты[[#This Row],[Состав]],Ингредиенты!A:I,3,0)*Рецепты[[#This Row],[г]],"") -> 0.24264706 | I45: =СводРецепт!$A$1 -> 1000 | J45: =Рецепты[[#This Row],[%]]*Рецепты[[#This Row],[Масса]] -> 3 | K45: =Рецепты[[#This Row],[Вес ингр-тов]]*VLOOKUP(Рецепты[[#This Row],[Состав]],Ингредиенты[],3,FALSE) -> 0.24264706 | L45: =IF(VLOOKUP(Рецепты[[#This Row],[Состав]],Ингредиенты[],4,0)="Основа",VLOOKUP(Рецепты[[#This Row],[Способ]],Способ[],2,0),0%) -> 0 | M45: =VLOOKUP(Рецепты[[#This Row],[Способ]],Способ[],3,0) -> 0.9 | N45: =Рецепты[[#This Row],[р]]*100%/(100%-Рецепты[[#This Row],[Потери, %]])+Рецепты[[#This Row],[Маржа]]*(Рецепты[[#This Row],[р]]*100%)/(100%-Рецепты[[#This Row],[Потери, %]]) -> 0.46102941 | O45: =Рецепты[[#This Row],[Цена за 1 кг]]-(Рецепты[[#This Row],[р]]*100%/(100%-Рецепты[[#This Row],[Потери, %]])) -> 0.21838235 | P45: https://www.youtube.com/watch?v=AyC9SVj43Sg | Q45: D:\Video\Колбаса_рецепты\ХИТ!!! Курица копчено-вареная. Как правильно шприцевать и коптить. Как сделать золотистую корочку.mp7 | R45: =VLOOKUP(Рецепты[[#This Row],[Состав]],Ингредиенты[],9,0) -> Да
A46: Грудинка свиная ГК | B46: =B45 -> Цельное | C46: =C45 -> ГК | D46: Грудинка свиная | E46: =VLOOKUP(Рецепты[[#This Row],[Состав]],Ингредиенты[],2,0) -> Свинина | F46: 1 | G46: =IF(Рецепты[[#This Row],[%]]*1000>0,Рецепты[[#This Row],[%]]*1000,"") -> 1000 | H46: =IFERROR(VLOOKUP(Рецепты[[#This Row],[Состав]],Ингредиенты!A:I,3,0)*Рецепты[[#This Row],[г]],"") -> 429.99 | I46: =СводРецепт!$A$1 -> 1000 | J46: =Рецепты[[#This Row],[%]]*Рецепты[[#This Row],[Масса]] -> 1000 | K46: =Рецепты[[#This Row],[Вес ингр-тов]]*VLOOKUP(Рецепты[[#This Row],[Состав]],Ингредиенты[],3,FALSE) -> 429.99 | L46: =IF(VLOOKUP(Рецепты[[#This Row],[Состав]],Ингредиенты[],4,0)="Основа",VLOOKUP(Рецепты[[#This Row],[Способ]],Способ[],2,0),0%) -> 0.15 | M46: =VLOOKUP(Рецепты[[#This Row],[Способ]],Способ[],3,0) -> 0.9 | N46: =Рецепты[[#This Row],[р]]*100%/(100%-Рецепты[[#This Row],[Потери, %]])+Рецепты[[#This Row],[Маржа]]*(Рецепты[[#This Row],[р]]*100%)/(100%-Рецепты[[#This Row],[Потери, %]]) -> 961.15412 | O46: =Рецепты[[#This Row],[Цена за 1 кг]]-(Рецепты[[#This Row],[р]]*100%/(100%-Рецепты[[#This Row],[Потери, %]])) -> 455.28353 | P46: https://www.youtube.com/watch?v=VJPh2ER-Zuw | Q46: D:\Video\Колбаса_рецепты\ГРУДИНКА ЩЕКОВИНА ГОРЯЧЕГО КОПЧЕНИЯ В моските.mp4 | R46: =VLOOKUP(Рецепты[[#This Row],[Состав]],Ингредиенты[],9,0) -> Нет
A47: Грудинка свиная ГК | B47: =B46 -> Цельное | C47: =C46 -> ГК | D47: Вода | E47: =VLOOKUP(Рецепты[[#This Row],[Состав]],Ингредиенты[],2,0) -> Добавки | F47: 0.1 | G47: =IF(Рецепты[[#This Row],[%]]*1000>0,Рецепты[[#This Row],[%]]*1000,"") -> 100 | H47: =IFERROR(VLOOKUP(Рецепты[[#This Row],[Состав]],Ингредиенты!A:I,3,0)*Рецепты[[#This Row],[г]],"") -> 0.1 | I47: =СводРецепт!$A$1 -> 1000 | J47: =Рецепты[[#This Row],[%]]*Рецепты[[#This Row],[Масса]] -> 100 | K47: =Рецепты[[#This Row],[Вес ингр-тов]]*VLOOKUP(Рецепты[[#This Row],[Состав]],Ингредиенты[],3,FALSE) -> 0.1 | L47: =IF(VLOOKUP(Рецепты[[#This Row],[Состав]],Ингредиенты[],4,0)="Основа",VLOOKUP(Рецепты[[#This Row],[Способ]],Способ[],2,0),0%) -> 0 | M47: =VLOOKUP(Рецепты[[#This Row],[Способ]],Способ[],3,0) -> 0.9 | N47: =Рецепты[[#This Row],[р]]*100%/(100%-Рецепты[[#This Row],[Потери, %]])+Рецепты[[#This Row],[Маржа]]*(Рецепты[[#This Row],[р]]*100%)/(100%-Рецепты[[#This Row],[Потери, %]]) -> 0.19 | O47: =Рецепты[[#This Row],[Цена за 1 кг]]-(Рецепты[[#This Row],[р]]*100%/(100%-Рецепты[[#This Row],[Потери, %]])) -> 0.09 | P47: https://www.youtube.com/watch?v=VJPh2ER-Zuw | Q47: D:\Video\Колбаса_рецепты\ГРУДИНКА ЩЕКОВИНА ГОРЯЧЕГО КОПЧЕНИЯ В моските.mp5 | R47: =VLOOKUP(Рецепты[[#This Row],[Состав]],Ингредиенты[],9,0) -> Да
A48: Грудинка свиная ГК | B48: =B47 -> Цельное | C48: =C47 -> ГК | D48: Фосфат | E48: =VLOOKUP(Рецепты[[#This Row],[Состав]],Ингредиенты[],2,0) -> Специи | F48: 0.002 | G48: =IF(Рецепты[[#This Row],[%]]*1000>0,Рецепты[[#This Row],[%]]*1000,"") -> 2 | H48: =IFERROR(VLOOKUP(Рецепты[[#This Row],[Состав]],Ингредиенты!A:I,3,0)*Рецепты[[#This Row],[г]],"") -> 1.496 | I48: =СводРецепт!$A$1 -> 1000 | J48: =Рецепты[[#This Row],[%]]*Рецепты[[#This Row],[Масса]] -> 2 | K48: =Рецепты[[#This Row],[Вес ингр-тов]]*VLOOKUP(Рецепты[[#This Row],[Состав]],Ингредиенты[],3,FALSE) -> 1.496 | L48: =IF(VLOOKUP(Рецепты[[#This Row],[Состав]],Ингредиенты[],4,0)="Основа",VLOOKUP(Рецепты[[#This Row],[Способ]],Способ[],2,0),0%) -> 0 | M48: =VLOOKUP(Рецепты[[#This Row],[Способ]],Способ[],3,0) -> 0.9 | N48: =Рецепты[[#This Row],[р]]*100%/(100%-Рецепты[[#This Row],[Потери, %]])+Рецепты[[#This Row],[Маржа]]*(Рецепты[[#This Row],[р]]*100%)/(100%-Рецепты[[#This Row],[Потери, %]]) -> 2.8424 | O48: =Рецепты[[#This Row],[Цена за 1 кг]]-(Рецепты[[#This Row],[р]]*100%/(100%-Рецепты[[#This Row],[Потери, %]])) -> 1.3464 | P48: https://www.youtube.com/watch?v=VJPh2ER-Zuw | Q48: D:\Video\Колбаса_рецепты\ГРУДИНКА ЩЕКОВИНА ГОРЯЧЕГО КОПЧЕНИЯ В моските.mp6 | R48: =VLOOKUP(Рецепты[[#This Row],[Состав]],Ингредиенты[],9,0) -> Да
A49: Грудинка свиная ГК | B49: =B48 -> Цельное | C49: =C48 -> ГК | D49: Соль пищевая | E49: =VLOOKUP(Рецепты[[#This Row],[Состав]],Ингредиенты[],2,0) -> Специи | F49: 0.01 | G49: =IF(Рецепты[[#This Row],[%]]*1000>0,Рецепты[[#This Row],[%]]*1000,"") -> 10 | H49: =IFERROR(VLOOKUP(Рецепты[[#This Row],[Состав]],Ингредиенты!A:I,3,0)*Рецепты[[#This Row],[г]],"") -> 0.385 | I49: =СводРецепт!$A$1 -> 1000 | J49: =Рецепты[[#This Row],[%]]*Рецепты[[#This Row],[Масса]] -> 10 | K49: =Рецепты[[#This Row],[Вес ингр-тов]]*VLOOKUP(Рецепты[[#This Row],[Состав]],Ингредиенты[],3,FALSE) -> 0.385 | L49: =IF(VLOOKUP(Рецепты[[#This Row],[Состав]],Ингредиенты[],4,0)="Основа",VLOOKUP(Рецепты[[#This Row],[Способ]],Способ[],2,0),0%) -> 0 | M49: =VLOOKUP(Рецепты[[#This Row],[Способ]],Способ[],3,0) -> 0.9 | N49: =Рецепты[[#This Row],[р]]*100%/(100%-Рецепты[[#This Row],[Потери, %]])+Рецепты[[#This Row],[Маржа]]*(Рецепты[[#This Row],[р]]*100%)/(100%-Рецепты[[#This Row],[Потери, %]]) -> 0.7315 | O49: =Рецепты[[#This Row],[Цена за 1 кг]]-(Рецепты[[#This Row],[р]]*100%/(100%-Рецепты[[#This Row],[Потери, %]])) -> 0.3465 | P49: https://www.youtube.com/watch?v=VJPh2ER-Zuw | Q49: D:\Video\Колбаса_рецепты\ГРУДИНКА ЩЕКОВИНА ГОРЯЧЕГО КОПЧЕНИЯ В моските.mp7 | R49: =VLOOKUP(Рецепты[[#This Row],[Состав]],Ингредиенты[],9,0) -> Да
A50: Грудинка свиная ГК | B50: =B49 -> Цельное | C50: =C49 -> ГК | D50: Соль нитритная | E50: =VLOOKUP(Рецепты[[#This Row],[Состав]],Ингредиенты[],2,0) -> Специи | F50: 0.01 | G50: =IF(Рецепты[[#This Row],[%]]*1000>0,Рецепты[[#This Row],[%]]*1000,"") -> 10 | H50: =IFERROR(VLOOKUP(Рецепты[[#This Row],[Состав]],Ингредиенты!A:I,3,0)*Рецепты[[#This Row],[г]],"") -> 1.28 | I50: =СводРецепт!$A$1 -> 1000 | J50: =Рецепты[[#This Row],[%]]*Рецепты[[#This Row],[Масса]] -> 10 | K50: =Рецепты[[#This Row],[Вес ингр-тов]]*VLOOKUP(Рецепты[[#This Row],[Состав]],Ингредиенты[],3,FALSE) -> 1.28 | L50: =IF(VLOOKUP(Рецепты[[#This Row],[Состав]],Ингредиенты[],4,0)="Основа",VLOOKUP(Рецепты[[#This Row],[Способ]],Способ[],2,0),0%) -> 0 | M50: =VLOOKUP(Рецепты[[#This Row],[Способ]],Способ[],3,0) -> 0.9 | N50: =Рецепты[[#This Row],[р]]*100%/(100%-Рецепты[[#This Row],[Потери, %]])+Рецепты[[#This Row],[Маржа]]*(Рецепты[[#This Row],[р]]*100%)/(100%-Рецепты[[#This Row],[Потери, %]]) -> 2.432 | O50: =Рецепты[[#This Row],[Цена за 1 кг]]-(Рецепты[[#This Row],[р]]*100%/(100%-Рецепты[[#This Row],[Потери, %]])) -> 1.152 | P50: https://www.youtube.com/watch?v=VJPh2ER-Zuw | Q50: D:\Video\Колбаса_рецепты\ГРУДИНКА ЩЕКОВИНА ГОРЯЧЕГО КОПЧЕНИЯ В моските.mp8 | R50: =VLOOKUP(Рецепты[[#This Row],[Состав]],Ингредиенты[],9,0) -> Да
A51: Грудинка свиная ГК | B51: =B50 -> Цельное | C51: =C50 -> ГК | D51: Сахар | E51: =VLOOKUP(Рецепты[[#This Row],[Состав]],Ингредиенты[],2,0) -> Специи | F51: 0.002 | G51: =IF(Рецепты[[#This Row],[%]]*1000>0,Рецепты[[#This Row],[%]]*1000,"") -> 2 | H51: =IFERROR(VLOOKUP(Рецепты[[#This Row],[Состав]],Ингредиенты!A:I,3,0)*Рецепты[[#This Row],[г]],"") -> 0.16176471 | I51: =СводРецепт!$A$1 -> 1000 | J51: =Рецепты[[#This Row],[%]]*Рецепты[[#This Row],[Масса]] -> 2 | K51: =Рецепты[[#This Row],[Вес ингр-тов]]*VLOOKUP(Рецепты[[#This Row],[Состав]],Ингредиенты[],3,FALSE) -> 0.16176471 | L51: =IF(VLOOKUP(Рецепты[[#This Row],[Состав]],Ингредиенты[],4,0)="Основа",VLOOKUP(Рецепты[[#This Row],[Способ]],Способ[],2,0),0%) -> 0 | M51: =VLOOKUP(Рецепты[[#This Row],[Способ]],Способ[],3,0) -> 0.9 | N51: =Рецепты[[#This Row],[р]]*100%/(100%-Рецепты[[#This Row],[Потери, %]])+Рецепты[[#This Row],[Маржа]]*(Рецепты[[#This Row],[р]]*100%)/(100%-Рецепты[[#This Row],[Потери, %]]) -> 0.30735294 | O51: =Рецепты[[#This Row],[Цена за 1 кг]]-(Рецепты[[#This Row],[р]]*100%/(100%-Рецепты[[#This Row],[Потери, %]])) -> 0.14558824 | P51: https://www.youtube.com/watch?v=VJPh2ER-Zuw | Q51: D:\Video\Колбаса_рецепты\ГРУДИНКА ЩЕКОВИНА ГОРЯЧЕГО КОПЧЕНИЯ В моските.mp9 | R51: =VLOOKUP(Рецепты[[#This Row],[Состав]],Ингредиенты[],9,0) -> Да
A52: Грудинка свиная ГК | B52: =B51 -> Цельное | C52: =C51 -> ГК | D52: Аскорбиновая кислота | E52: =VLOOKUP(Рецепты[[#This Row],[Состав]],Ингредиенты[],2,0) -> Специи | F52: 0.0005 | G52: =IF(Рецепты[[#This Row],[%]]*1000>0,Рецепты[[#This Row],[%]]*1000,"") -> 0.5 | H52: =IFERROR(VLOOKUP(Рецепты[[#This Row],[Состав]],Ингредиенты!A:I,3,0)*Рецепты[[#This Row],[г]],"") -> 0.851 | I52: =СводРецепт!$A$1 -> 1000 | J52: =Рецепты[[#This Row],[%]]*Рецепты[[#This Row],[Масса]] -> 0.5 | K52: =Рецепты[[#This Row],[Вес ингр-тов]]*VLOOKUP(Рецепты[[#This Row],[Состав]],Ингредиенты[],3,FALSE) -> 0.851 | L52: =IF(VLOOKUP(Рецепты[[#This Row],[Состав]],Ингредиенты[],4,0)="Основа",VLOOKUP(Рецепты[[#This Row],[Способ]],Способ[],2,0),0%) -> 0 | M52: =VLOOKUP(Рецепты[[#This Row],[Способ]],Способ[],3,0) -> 0.9 | N52: =Рецепты[[#This Row],[р]]*100%/(100%-Рецепты[[#This Row],[Потери, %]])+Рецепты[[#This Row],[Маржа]]*(Рецепты[[#This Row],[р]]*100%)/(100%-Рецепты[[#This Row],[Потери, %]]) -> 1.6169 | O52: =Рецепты[[#This Row],[Цена за 1 кг]]-(Рецепты[[#This Row],[р]]*100%/(100%-Рецепты[[#This Row],[Потери, %]])) -> 0.7659 | P52: https://www.youtube.com/watch?v=VJPh2ER-Zuw | Q52: D:\Video\Колбаса_рецепты\ГРУДИНКА ЩЕКОВИНА ГОРЯЧЕГО КОПЧЕНИЯ В моските.mp10 | R52: =VLOOKUP(Рецепты[[#This Row],[Состав]],Ингредиенты[],9,0) -> Да
A53: Грудинка свиная ГК | B53: =B52 -> Цельное | C53: =C52 -> ГК | D53: Глютамат натрия | E53: =VLOOKUP(Рецепты[[#This Row],[Состав]],Ингредиенты[],2,0) -> Специи | F53: 0.001 | G53: =IF(Рецепты[[#This Row],[%]]*1000>0,Рецепты[[#This Row],[%]]*1000,"") -> 1 | H53: =IFERROR(VLOOKUP(Рецепты[[#This Row],[Состав]],Ингредиенты!A:I,3,0)*Рецепты[[#This Row],[г]],"") -> 0.555 | I53: =СводРецепт!$A$1 -> 1000 | J53: =Рецепты[[#This Row],[%]]*Рецепты[[#This Row],[Масса]] -> 1 | K53: =Рецепты[[#This Row],[Вес ингр-тов]]*VLOOKUP(Рецепты[[#This Row],[Состав]],Ингредиенты[],3,FALSE) -> 0.555 | L53: =IF(VLOOKUP(Рецепты[[#This Row],[Состав]],Ингредиенты[],4,0)="Основа",VLOOKUP(Рецепты[[#This Row],[Способ]],Способ[],2,0),0%) -> 0 | M53: =VLOOKUP(Рецепты[[#This Row],[Способ]],Способ[],3,0) -> 0.9 | N53: =Рецепты[[#This Row],[р]]*100%/(100%-Рецепты[[#This Row],[Потери, %]])+Рецепты[[#This Row],[Маржа]]*(Рецепты[[#This Row],[р]]*100%)/(100%-Рецепты[[#This Row],[Потери, %]]) -> 1.0545 | O53: =Рецепты[[#This Row],[Цена за 1 кг]]-(Рецепты[[#This Row],[р]]*100%/(100%-Рецепты[[#This Row],[Потери, %]])) -> 0.4995 | P53: https://www.youtube.com/watch?v=VJPh2ER-Zuw | Q53: D:\Video\Колбаса_рецепты\ГРУДИНКА ЩЕКОВИНА ГОРЯЧЕГО КОПЧЕНИЯ В моските.mp11 | R53: =VLOOKUP(Рецепты[[#This Row],[Состав]],Ингредиенты[],9,0) -> Да
A54: Скумбрия ХК | B54: Рыба | C54: ХК | D54: Скумбрия | E54: =VLOOKUP(Рецепты[[#This Row],[Состав]],Ингредиенты[],2,0) -> Рыба | F54: 1 | G54: =IF(Рецепты[[#This Row],[%]]*1000>0,Рецепты[[#This Row],[%]]*1000,"") -> 1000 | H54: =IFERROR(VLOOKUP(Рецепты[[#This Row],[Состав]],Ингредиенты!A:I,3,0)*Рецепты[[#This Row],[г]],"") -> 425 | I54: =СводРецепт!$A$1 -> 1000 | J54: =Рецепты[[#This Row],[%]]*Рецепты[[#This Row],[Масса]] -> 1000 | K54: =Рецепты[[#This Row],[Вес ингр-тов]]*VLOOKUP(Рецепты[[#This Row],[Состав]],Ингредиенты[],3,FALSE) -> 425 | L54: =IF(VLOOKUP(Рецепты[[#This Row],[Состав]],Ингредиенты[],4,0)="Основа",VLOOKUP(Рецепты[[#This Row],[Способ]],Способ[],2,0),0%) -> 0.15 | M54: =VLOOKUP(Рецепты[[#This Row],[Способ]],Способ[],3,0) -> 1 | N54: =Рецепты[[#This Row],[р]]*100%/(100%-Рецепты[[#This Row],[Потери, %]])+Рецепты[[#This Row],[Маржа]]*(Рецепты[[#This Row],[р]]*100%)/(100%-Рецепты[[#This Row],[Потери, %]]) -> 1000 | O54: =Рецепты[[#This Row],[Цена за 1 кг]]-(Рецепты[[#This Row],[р]]*100%/(100%-Рецепты[[#This Row],[Потери, %]])) -> 500 | P54: https://youtu.be/dqZj1rANEhA | R54: =VLOOKUP(Рецепты[[#This Row],[Состав]],Ингредиенты[],9,0) -> Нет
A55: Скумбрия ХК | B55: =B54 -> Рыба | C55: =C54 -> ХК | D55: Вода | E55: =VLOOKUP(Рецепты[[#This Row],[Состав]],Ингредиенты[],2,0) -> Добавки | F55: 1 | G55: =IF(Рецепты[[#This Row],[%]]*1000>0,Рецепты[[#This Row],[%]]*1000,"") -> 1000 | H55: =IFERROR(VLOOKUP(Рецепты[[#This Row],[Состав]],Ингредиенты!A:I,3,0)*Рецепты[[#This Row],[г]],"") -> 1 | I55: =СводРецепт!$A$1 -> 1000 | J55: =Рецепты[[#This Row],[%]]*Рецепты[[#This Row],[Масса]] -> 1000 | K55: =Рецепты[[#This Row],[Вес ингр-тов]]*VLOOKUP(Рецепты[[#This Row],[Состав]],Ингредиенты[],3,FALSE) -> 1 | L55: =IF(VLOOKUP(Рецепты[[#This Row],[Состав]],Ингредиенты[],4,0)="Основа",VLOOKUP(Рецепты[[#This Row],[Способ]],Способ[],2,0),0%) -> 0 | M55: =VLOOKUP(Рецепты[[#This Row],[Способ]],Способ[],3,0) -> 1 | N55: =Рецепты[[#This Row],[р]]*100%/(100%-Рецепты[[#This Row],[Потери, %]])+Рецепты[[#This Row],[Маржа]]*(Рецепты[[#This Row],[р]]*100%)/(100%-Рецепты[[#This Row],[Потери, %]]) -> 2 | O55: =Рецепты[[#This Row],[Цена за 1 кг]]-(Рецепты[[#This Row],[р]]*100%/(100%-Рецепты[[#This Row],[Потери, %]])) -> 1 | P55: https://youtu.be/dqZj1rANEhA | R55: =VLOOKUP(Рецепты[[#This Row],[Состав]],Ингредиенты[],9,0) -> Да
A56: Скумбрия ХК | B56: =B55 -> Рыба | C56: =C55 -> ХК | D56: Соль пищевая | E56: =VLOOKUP(Рецепты[[#This Row],[Состав]],Ингредиенты[],2,0) -> Специи | F56: 0.2 | G56: =IF(Рецепты[[#This Row],[%]]*1000>0,Рецепты[[#This Row],[%]]*1000,"") -> 200 | H56: =IFERROR(VLOOKUP(Рецепты[[#This Row],[Состав]],Ингредиенты!A:I,3,0)*Рецепты[[#This Row],[г]],"") -> 7.7 | I56: =СводРецепт!$A$1 -> 1000 | J56: =Рецепты[[#This Row],[%]]*Рецепты[[#This Row],[Масса]] -> 200 | K56: =Рецепты[[#This Row],[Вес ингр-тов]]*VLOOKUP(Рецепты[[#This Row],[Состав]],Ингредиенты[],3,FALSE) -> 7.7 | L56: =IF(VLOOKUP(Рецепты[[#This Row],[Состав]],Ингредиенты[],4,0)="Основа",VLOOKUP(Рецепты[[#This Row],[Способ]],Способ[],2,0),0%) -> 0 | M56: =VLOOKUP(Рецепты[[#This Row],[Способ]],Способ[],3,0) -> 1 | N56: =Рецепты[[#This Row],[р]]*100%/(100%-Рецепты[[#This Row],[Потери, %]])+Рецепты[[#This Row],[Маржа]]*(Рецепты[[#This Row],[р]]*100%)/(100%-Рецепты[[#This Row],[Потери, %]]) -> 15.4 | O56: =Рецепты[[#This Row],[Цена за 1 кг]]-(Рецепты[[#This Row],[р]]*100%/(100%-Рецепты[[#This Row],[Потери, %]])) -> 7.7 | P56: https://youtu.be/dqZj1rANEhA | R56: =VLOOKUP(Рецепты[[#This Row],[Состав]],Ингредиенты[],9,0) -> Да
A57: Карась ХК | B57: =B56 -> Рыба | C57: =C56 -> ХК | D57: Карась | E57: =VLOOKUP(Рецепты[[#This Row],[Состав]],Ингредиенты[],2,0) -> Рыба | F57: 1 | G57: =IF(Рецепты[[#This Row],[%]]*1000>0,Рецепты[[#This Row],[%]]*1000,"") -> 1000 | H57: =IFERROR(VLOOKUP(Рецепты[[#This Row],[Состав]],Ингредиенты!A:I,3,0)*Рецепты[[#This Row],[г]],"") -> 250 | I57: =СводРецепт!$A$1 -> 1000 | J57: =Рецепты[[#This Row],[%]]*Рецепты[[#This Row],[Масса]] -> 1000 | K57: =Рецепты[[#This Row],[Вес ингр-тов]]*VLOOKUP(Рецепты[[#This Row],[Состав]],Ингредиенты[],3,FALSE) -> 250 | L57: =IF(VLOOKUP(Рецепты[[#This Row],[Состав]],Ингредиенты[],4,0)="Основа",VLOOKUP(Рецепты[[#This Row],[Способ]],Способ[],2,0),0%) -> 0.15 | M57: =VLOOKUP(Рецепты[[#This Row],[Способ]],Способ[],3,0) -> 1 | N57: =Рецепты[[#This Row],[р]]*100%/(100%-Рецепты[[#This Row],[Потери, %]])+Рецепты[[#This Row],[Маржа]]*(Рецепты[[#This Row],[р]]*100%)/(100%-Рецепты[[#This Row],[Потери, %]]) -> 588.23529 | O57: =Рецепты[[#This Row],[Цена за 1 кг]]-(Рецепты[[#This Row],[р]]*100%/(100%-Рецепты[[#This Row],[Потери, %]])) -> 294.11765 | P57: https://www.youtube.com/watch?v=74iIMezDsSk | Q57: D:\Video\Колбаса_рецепты\КАРАСЬ холодного копчения по казахски от ИГОРЯ в коптильне москит.mp4 | R57: =VLOOKUP(Рецепты[[#This Row],[Состав]],Ингредиенты[],9,0) -> Да
A58: Карась ХК | B58: =B57 -> Рыба | C58: =C57 -> ХК | D58: Соль пищевая | E58: =VLOOKUP(Рецепты[[#This Row],[Состав]],Ингредиенты[],2,0) -> Специи | F58: 0.05 | G58: =IF(Рецепты[[#This Row],[%]]*1000>0,Рецепты[[#This Row],[%]]*1000,"") -> 50 | H58: =IFERROR(VLOOKUP(Рецепты[[#This Row],[Состав]],Ингредиенты!A:I,3,0)*Рецепты[[#This Row],[г]],"") -> 1.925 | I58: =СводРецепт!$A$1 -> 1000 | J58: =Рецепты[[#This Row],[%]]*Рецепты[[#This Row],[Масса]] -> 50 | K58: =Рецепты[[#This Row],[Вес ингр-тов]]*VLOOKUP(Рецепты[[#This Row],[Состав]],Ингредиенты[],3,FALSE) -> 1.925 | L58: =IF(VLOOKUP(Рецепты[[#This Row],[Состав]],Ингредиенты[],4,0)="Основа",VLOOKUP(Рецепты[[#This Row],[Способ]],Способ[],2,0),0%) -> 0 | M58: =VLOOKUP(Рецепты[[#This Row],[Способ]],Способ[],3,0) -> 1 | N58: =Рецепты[[#This Row],[р]]*100%/(100%-Рецепты[[#This Row],[Потери, %]])+Рецепты[[#This Row],[Маржа]]*(Рецепты[[#This Row],[р]]*100%)/(100%-Рецепты[[#This Row],[Потери, %]]) -> 3.85 | O58: =Рецепты[[#This Row],[Цена за 1 кг]]-(Рецепты[[#This Row],[р]]*100%/(100%-Рецепты[[#This Row],[Потери, %]])) -> 1.925 | P58: https://www.youtube.com/watch?v=74iIMezDsSk | Q58: D:\Video\Колбаса_рецепты\КАРАСЬ холодного копчения по казахски от ИГОРЯ в коптильне москит.mp5 | R58: =VLOOKUP(Рецепты[[#This Row],[Состав]],Ингредиенты[],9,0) -> Да
A59: Карась ХК | B59: =B58 -> Рыба | C59: =C58 -> ХК | D59: Сахар | E59: =VLOOKUP(Рецепты[[#This Row],[Состав]],Ингредиенты[],2,0) -> Специи | F59: 0.01 | G59: =IF(Рецепты[[#This Row],[%]]*1000>0,Рецепты[[#This Row],[%]]*1000,"") -> 10 | H59: =IFERROR(VLOOKUP(Рецепты[[#This Row],[Состав]],Ингредиенты!A:I,3,0)*Рецепты[[#This Row],[г]],"") -> 0.80882353 | I59: =СводРецепт!$A$1 -> 1000 | J59: =Рецепты[[#This Row],[%]]*Рецепты[[#This Row],[Масса]] -> 10 | K59: =Рецепты[[#This Row],[Вес ингр-тов]]*VLOOKUP(Рецепты[[#This Row],[Состав]],Ингредиенты[],3,FALSE) -> 0.80882353 | L59: =IF(VLOOKUP(Рецепты[[#This Row],[Состав]],Ингредиенты[],4,0)="Основа",VLOOKUP(Рецепты[[#This Row],[Способ]],Способ[],2,0),0%) -> 0 | M59: =VLOOKUP(Рецепты[[#This Row],[Способ]],Способ[],3,0) -> 1 | N59: =Рецепты[[#This Row],[р]]*100%/(100%-Рецепты[[#This Row],[Потери, %]])+Рецепты[[#This Row],[Маржа]]*(Рецепты[[#This Row],[р]]*100%)/(100%-Рецепты[[#This Row],[Потери, %]]) -> 1.6176471 | O59: =Рецепты[[#This Row],[Цена за 1 кг]]-(Рецепты[[#This Row],[р]]*100%/(100%-Рецепты[[#This Row],[Потери, %]])) -> 0.80882353 | P59: https://www.youtube.com/watch?v=74iIMezDsSk | Q59: D:\Video\Колбаса_рецепты\КАРАСЬ холодного копчения по казахски от ИГОРЯ в коптильне москит.mp6 | R59: =VLOOKUP(Рецепты[[#This Row],[Состав]],Ингредиенты[],9,0) -> Да
A60: Карась ХК | B60: =B59 -> Рыба | C60: =C59 -> ХК | D60: Перец чили молотый | E60: =VLOOKUP(Рецепты[[#This Row],[Состав]],Ингредиенты[],2,0) -> Специи | F60: 0.001 | G60: =IF(Рецепты[[#This Row],[%]]*1000>0,Рецепты[[#This Row],[%]]*1000,"") -> 1 | H60: =IFERROR(VLOOKUP(Рецепты[[#This Row],[Состав]],Ингредиенты!A:I,3,0)*Рецепты[[#This Row],[г]],"") -> 0.77636364 | I60: =СводРецепт!$A$1 -> 1000 | J60: =Рецепты[[#This Row],[%]]*Рецепты[[#This Row],[Масса]] -> 1 | K60: =Рецепты[[#This Row],[Вес ингр-тов]]*VLOOKUP(Рецепты[[#This Row],[Состав]],Ингредиенты[],3,FALSE) -> 0.77636364 | L60: =IF(VLOOKUP(Рецепты[[#This Row],[Состав]],Ингредиенты[],4,0)="Основа",VLOOKUP(Рецепты[[#This Row],[Способ]],Способ[],2,0),0%) -> 0 | M60: =VLOOKUP(Рецепты[[#This Row],[Способ]],Способ[],3,0) -> 1 | N60: =Рецепты[[#This Row],[р]]*100%/(100%-Рецепты[[#This Row],[Потери, %]])+Рецепты[[#This Row],[Маржа]]*(Рецепты[[#This Row],[р]]*100%)/(100%-Рецепты[[#This Row],[Потери, %]]) -> 1.5527273 | O60: =Рецепты[[#This Row],[Цена за 1 кг]]-(Рецепты[[#This Row],[р]]*100%/(100%-Рецепты[[#This Row],[Потери, %]])) -> 0.77636364 | P60: https://www.youtube.com/watch?v=74iIMezDsSk | Q60: D:\Video\Колбаса_рецепты\КАРАСЬ холодного копчения по казахски от ИГОРЯ в коптильне москит.mp7 | R60: =VLOOKUP(Рецепты[[#This Row],[Состав]],Ингредиенты[],9,0) -> Нет
A61: Карась ХК | B61: =B60 -> Рыба | C61: =C60 -> ХК | D61: Паприка красная молотая | E61: =VLOOKUP(Рецепты[[#This Row],[Состав]],Ингредиенты[],2,0) -> Специи | F61: 0.003 | G61: =IF(Рецепты[[#This Row],[%]]*1000>0,Рецепты[[#This Row],[%]]*1000,"") -> 3 | H61: =IFERROR(VLOOKUP(Рецепты[[#This Row],[Состав]],Ингредиенты!A:I,3,0)*Рецепты[[#This Row],[г]],"") -> 2.3454545 | I61: =СводРецепт!$A$1 -> 1000 | J61: =Рецепты[[#This Row],[%]]*Рецепты[[#This Row],[Масса]] -> 3 | K61: =Рецепты[[#This Row],[Вес ингр-тов]]*VLOOKUP(Рецепты[[#This Row],[Состав]],Ингредиенты[],3,FALSE) -> 2.3454545 | L61: =IF(VLOOKUP(Рецепты[[#This Row],[Состав]],Ингредиенты[],4,0)="Основа",VLOOKUP(Рецепты[[#This Row],[Способ]],Способ[],2,0),0%) -> 0 | M61: =VLOOKUP(Рецепты[[#This Row],[Способ]],Способ[],3,0) -> 1 | N61: =Рецепты[[#This Row],[р]]*100%/(100%-Рецепты[[#This Row],[Потери, %]])+Рецепты[[#This Row],[Маржа]]*(Рецепты[[#This Row],[р]]*100%)/(100%-Рецепты[[#This Row],[Потери, %]]) -> 4.6909091 | O61: =Рецепты[[#This Row],[Цена за 1 кг]]-(Рецепты[[#This Row],[р]]*100%/(100%-Рецепты[[#This Row],[Потери, %]])) -> 2.3454545 | P61: https://www.youtube.com/watch?v=74iIMezDsSk | Q61: D:\Video\Колбаса_рецепты\КАРАСЬ холодного копчения по казахски от ИГОРЯ в коптильне москит.mp8 | R61: =VLOOKUP(Рецепты[[#This Row],[Состав]],Ингредиенты[],9,0) -> Нет
A62: Карась ХК | B62: =B61 -> Рыба | C62: =C61 -> ХК | D62: Чеснок сушеный | E62: =VLOOKUP(Рецепты[[#This Row],[Состав]],Ингредиенты[],2,0) -> Специи | F62: 0.002 | G62: =IF(Рецепты[[#This Row],[%]]*1000>0,Рецепты[[#This Row],[%]]*1000,"") -> 2 | H62: =IFERROR(VLOOKUP(Рецепты[[#This Row],[Состав]],Ингредиенты!A:I,3,0)*Рецепты[[#This Row],[г]],"") -> 1.7566667 | I62: =СводРецепт!$A$1 -> 1000 | J62: =Рецепты[[#This Row],[%]]*Рецепты[[#This Row],[Масса]] -> 2 | K62: =Рецепты[[#This Row],[Вес ингр-тов]]*VLOOKUP(Рецепты[[#This Row],[Состав]],Ингредиенты[],3,FALSE) -> 1.7566667 | L62: =IF(VLOOKUP(Рецепты[[#This Row],[Состав]],Ингредиенты[],4,0)="Основа",VLOOKUP(Рецепты[[#This Row],[Способ]],Способ[],2,0),0%) -> 0 | M62: =VLOOKUP(Рецепты[[#This Row],[Способ]],Способ[],3,0) -> 1 | N62: =Рецепты[[#This Row],[р]]*100%/(100%-Рецепты[[#This Row],[Потери, %]])+Рецепты[[#This Row],[Маржа]]*(Рецепты[[#This Row],[р]]*100%)/(100%-Рецепты[[#This Row],[Потери, %]]) -> 3.5133333 | O62: =Рецепты[[#This Row],[Цена за 1 кг]]-(Рецепты[[#This Row],[р]]*100%/(100%-Рецепты[[#This Row],[Потери, %]])) -> 1.7566667 | P62: https://www.youtube.com/watch?v=74iIMezDsSk | Q62: D:\Video\Колбаса_рецепты\КАРАСЬ холодного копчения по казахски от ИГОРЯ в коптильне москит.mp9 | R62: =VLOOKUP(Рецепты[[#This Row],[Состав]],Ингредиенты[],9,0) -> Да
A63: Карась ХК | B63: =B62 -> Рыба | C63: =C62 -> ХК | D63: Бадьян | E63: =VLOOKUP(Рецепты[[#This Row],[Состав]],Ингредиенты[],2,0) -> Специи | F63: 0.0001 | G63: =IF(Рецепты[[#This Row],[%]]*1000>0,Рецепты[[#This Row],[%]]*1000,"") -> 0.1 | H63: =IFERROR(VLOOKUP(Рецепты[[#This Row],[Состав]],Ингредиенты!A:I,3,0)*Рецепты[[#This Row],[г]],"") -> 0.394 | I63: =СводРецепт!$A$1 -> 1000 | J63: =Рецепты[[#This Row],[%]]*Рецепты[[#This Row],[Масса]] -> 0.1 | K63: =Рецепты[[#This Row],[Вес ингр-тов]]*VLOOKUP(Рецепты[[#This Row],[Состав]],Ингредиенты[],3,FALSE) -> 0.394 | L63: =IF(VLOOKUP(Рецепты[[#This Row],[Состав]],Ингредиенты[],4,0)="Основа",VLOOKUP(Рецепты[[#This Row],[Способ]],Способ[],2,0),0%) -> 0 | M63: =VLOOKUP(Рецепты[[#This Row],[Способ]],Способ[],3,0) -> 1 | N63: =Рецепты[[#This Row],[р]]*100%/(100%-Рецепты[[#This Row],[Потери, %]])+Рецепты[[#This Row],[Маржа]]*(Рецепты[[#This Row],[р]]*100%)/(100%-Рецепты[[#This Row],[Потери, %]]) -> 0.788 | O63: =Рецепты[[#This Row],[Цена за 1 кг]]-(Рецепты[[#This Row],[р]]*100%/(100%-Рецепты[[#This Row],[Потери, %]])) -> 0.394 | P63: https://www.youtube.com/watch?v=74iIMezDsSk | Q63: D:\Video\Колбаса_рецепты\КАРАСЬ холодного копчения по казахски от ИГОРЯ в коптильне москит.mp10 | R63: =VLOOKUP(Рецепты[[#This Row],[Состав]],Ингредиенты[],9,0) -> Нет
A64: Карась ХК | B64: =B63 -> Рыба | C64: =C63 -> ХК | D64: Кориандр | E64: =VLOOKUP(Рецепты[[#This Row],[Состав]],Ингредиенты[],2,0) -> Специи | F64: 0.003 | G64: =IF(Рецепты[[#This Row],[%]]*1000>0,Рецепты[[#This Row],[%]]*1000,"") -> 3 | H64: =IFERROR(VLOOKUP(Рецепты[[#This Row],[Состав]],Ингредиенты!A:I,3,0)*Рецепты[[#This Row],[г]],"") -> 1.5066667 | I64: =СводРецепт!$A$1 -> 1000 | J64: =Рецепты[[#This Row],[%]]*Рецепты[[#This Row],[Масса]] -> 3 | K64: =Рецепты[[#This Row],[Вес ингр-тов]]*VLOOKUP(Рецепты[[#This Row],[Состав]],Ингредиенты[],3,FALSE) -> 1.5066667 | L64: =IF(VLOOKUP(Рецепты[[#This Row],[Состав]],Ингредиенты[],4,0)="Основа",VLOOKUP(Рецепты[[#This Row],[Способ]],Способ[],2,0),0%) -> 0 | M64: =VLOOKUP(Рецепты[[#This Row],[Способ]],Способ[],3,0) -> 1 | N64: =Рецепты[[#This Row],[р]]*100%/(100%-Рецепты[[#This Row],[Потери, %]])+Рецепты[[#This Row],[Маржа]]*(Рецепты[[#This Row],[р]]*100%)/(100%-Рецепты[[#This Row],[Потери, %]]) -> 3.0133333 | O64: =Рецепты[[#This Row],[Цена за 1 кг]]-(Рецепты[[#This Row],[р]]*100%/(100%-Рецепты[[#This Row],[Потери, %]])) -> 1.5066667 | P64: https://www.youtube.com/watch?v=74iIMezDsSk | Q64: D:\Video\Колбаса_рецепты\КАРАСЬ холодного копчения по казахски от ИГОРЯ в коптильне москит.mp11 | R64: =VLOOKUP(Рецепты[[#This Row],[Состав]],Ингредиенты[],9,0) -> Да
A65: Горбуша ХК | B65: =B64 -> Рыба | C65: =C64 -> ХК | D65: Горбуша | E65: =VLOOKUP(Рецепты[[#This Row],[Состав]],Ингредиенты[],2,0) -> Рыба | F65: 1 | G65: =IF(Рецепты[[#This Row],[%]]*1000>0,Рецепты[[#This Row],[%]]*1000,"") -> 1000 | H65: =IFERROR(VLOOKUP(Рецепты[[#This Row],[Состав]],Ингредиенты!A:I,3,0)*Рецепты[[#This Row],[г]],"") -> 378.55714 | I65: =СводРецепт!$A$1 -> 1000 | J65: =Рецепты[[#This Row],[%]]*Рецепты[[#This Row],[Масса]] -> 1000 | K65: =Рецепты[[#This Row],[Вес ингр-тов]]*VLOOKUP(Рецепты[[#This Row],[Состав]],Ингредиенты[],3,FALSE) -> 378.55714 | L65: =IF(VLOOKUP(Рецепты[[#This Row],[Состав]],Ингредиенты[],4,0)="Основа",VLOOKUP(Рецепты[[#This Row],[Способ]],Способ[],2,0),0%) -> 0.15 | M65: =VLOOKUP(Рецепты[[#This Row],[Способ]],Способ[],3,0) -> 1 | N65: =Рецепты[[#This Row],[р]]*100%/(100%-Рецепты[[#This Row],[Потери, %]])+Рецепты[[#This Row],[Маржа]]*(Рецепты[[#This Row],[р]]*100%)/(100%-Рецепты[[#This Row],[Потери, %]]) -> 890.72269 | O65: =Рецепты[[#This Row],[Цена за 1 кг]]-(Рецепты[[#This Row],[р]]*100%/(100%-Рецепты[[#This Row],[Потери, %]])) -> 445.36134 | P65: https://www.youtube.com/watch?v=ynKD-Uz8MzQ | Q65: D:\Video\Колбаса_рецепты\горбуша холодного копчения в коптильне москит.mp4 | R65: =VLOOKUP(Рецепты[[#This Row],[Состав]],Ингредиенты[],9,0) -> Нет
A66: Горбуша ХК | B66: =B65 -> Рыба | C66: =C65 -> ХК | D66: Вода | E66: =VLOOKUP(Рецепты[[#This Row],[Состав]],Ингредиенты[],2,0) -> Добавки | F66: 1 | G66: =IF(Рецепты[[#This Row],[%]]*1000>0,Рецепты[[#This Row],[%]]*1000,"") -> 1000 | H66: =IFERROR(VLOOKUP(Рецепты[[#This Row],[Состав]],Ингредиенты!A:I,3,0)*Рецепты[[#This Row],[г]],"") -> 1 | I66: =СводРецепт!$A$1 -> 1000 | J66: =Рецепты[[#This Row],[%]]*Рецепты[[#This Row],[Масса]] -> 1000 | K66: =Рецепты[[#This Row],[Вес ингр-тов]]*VLOOKUP(Рецепты[[#This Row],[Состав]],Ингредиенты[],3,FALSE) -> 1 | L66: =IF(VLOOKUP(Рецепты[[#This Row],[Состав]],Ингредиенты[],4,0)="Основа",VLOOKUP(Рецепты[[#This Row],[Способ]],Способ[],2,0),0%) -> 0 | M66: =VLOOKUP(Рецепты[[#This Row],[Способ]],Способ[],3,0) -> 1 | N66: =Рецепты[[#This Row],[р]]*100%/(100%-Рецепты[[#This Row],[Потери, %]])+Рецепты[[#This Row],[Маржа]]*(Рецепты[[#This Row],[р]]*100%)/(100%-Рецепты[[#This Row],[Потери, %]]) -> 2 | O66: =Рецепты[[#This Row],[Цена за 1 кг]]-(Рецепты[[#This Row],[р]]*100%/(100%-Рецепты[[#This Row],[Потери, %]])) -> 1 | P66: https://www.youtube.com/watch?v=ynKD-Uz8MzQ | Q66: D:\Video\Колбаса_рецепты\горбуша холодного копчения в коптильне москит.mp5 | R66: =VLOOKUP(Рецепты[[#This Row],[Состав]],Ингредиенты[],9,0) -> Да
A67: Горбуша ХК | B67: =B66 -> Рыба | C67: =C66 -> ХК | D67: Соль пищевая | E67: =VLOOKUP(Рецепты[[#This Row],[Состав]],Ингредиенты[],2,0) -> Специи | F67: 0.25 | G67: =IF(Рецепты[[#This Row],[%]]*1000>0,Рецепты[[#This Row],[%]]*1000,"") -> 250 | H67: =IFERROR(VLOOKUP(Рецепты[[#This Row],[Состав]],Ингредиенты!A:I,3,0)*Рецепты[[#This Row],[г]],"") -> 9.625 | I67: =СводРецепт!$A$1 -> 1000 | J67: =Рецепты[[#This Row],[%]]*Рецепты[[#This Row],[Масса]] -> 250 | K67: =Рецепты[[#This Row],[Вес ингр-тов]]*VLOOKUP(Рецепты[[#This Row],[Состав]],Ингредиенты[],3,FALSE) -> 9.625 | L67: =IF(VLOOKUP(Рецепты[[#This Row],[Состав]],Ингредиенты[],4,0)="Основа",VLOOKUP(Рецепты[[#This Row],[Способ]],Способ[],2,0),0%) -> 0 | M67: =VLOOKUP(Рецепты[[#This Row],[Способ]],Способ[],3,0) -> 1 | N67: =Рецепты[[#This Row],[р]]*100%/(100%-Рецепты[[#This Row],[Потери, %]])+Рецепты[[#This Row],[Маржа]]*(Рецепты[[#This Row],[р]]*100%)/(100%-Рецепты[[#This Row],[Потери, %]]) -> 19.25 | O67: =Рецепты[[#This Row],[Цена за 1 кг]]-(Рецепты[[#This Row],[р]]*100%/(100%-Рецепты[[#This Row],[Потери, %]])) -> 9.625 | P67: https://www.youtube.com/watch?v=ynKD-Uz8MzQ | Q67: D:\Video\Колбаса_рецепты\горбуша холодного копчения в коптильне москит.mp6 | R67: =VLOOKUP(Рецепты[[#This Row],[Состав]],Ингредиенты[],9,0) -> Да
A68: Горбуша ХК | B68: =B67 -> Рыба | C68: =C67 -> ХК | D68: Сахар | E68: =VLOOKUP(Рецепты[[#This Row],[Состав]],Ингредиенты[],2,0) -> Специи | F68: 0.002 | G68: =IF(Рецепты[[#This Row],[%]]*1000>0,Рецепты[[#This Row],[%]]*1000,"") -> 2 | H68: =IFERROR(VLOOKUP(Рецепты[[#This Row],[Состав]],Ингредиенты!A:I,3,0)*Рецепты[[#This Row],[г]],"") -> 0.16176471 | I68: =СводРецепт!$A$1 -> 1000 | J68: =Рецепты[[#This Row],[%]]*Рецепты[[#This Row],[Масса]] -> 2 | K68: =Рецепты[[#This Row],[Вес ингр-тов]]*VLOOKUP(Рецепты[[#This Row],[Состав]],Ингредиенты[],3,FALSE) -> 0.16176471 | L68: =IF(VLOOKUP(Рецепты[[#This Row],[Состав]],Ингредиенты[],4,0)="Основа",VLOOKUP(Рецепты[[#This Row],[Способ]],Способ[],2,0),0%) -> 0 | M68: =VLOOKUP(Рецепты[[#This Row],[Способ]],Способ[],3,0) -> 1 | N68: =Рецепты[[#This Row],[р]]*100%/(100%-Рецепты[[#This Row],[Потери, %]])+Рецепты[[#This Row],[Маржа]]*(Рецепты[[#This Row],[р]]*100%)/(100%-Рецепты[[#This Row],[Потери, %]]) -> 0.32352941 | O68: =Рецепты[[#This Row],[Цена за 1 кг]]-(Рецепты[[#This Row],[р]]*100%/(100%-Рецепты[[#This Row],[Потери, %]])) -> 0.16176471 | P68: https://www.youtube.com/watch?v=ynKD-Uz8MzQ | Q68: D:\Video\Колбаса_рецепты\горбуша холодного копчения в коптильне москит.mp7 | R68: =VLOOKUP(Рецепты[[#This Row],[Состав]],Ингредиенты[],9,0) -> Да
A69: Еврейская | B69: Колбаса | C69: Сырокопченое | D69: Говядина | E69: =VLOOKUP(Рецепты[[#This Row],[Состав]],Ингредиенты[],2,0) -> Говядина | F69: 0.75 | G69: =IF(Рецепты[[#This Row],[%]]*1000>0,Рецепты[[#This Row],[%]]*1000,"") -> 750 | H69: =IFERROR(VLOOKUP(Рецепты[[#This Row],[Состав]],Ингредиенты!A:I,3,0)*Рецепты[[#This Row],[г]],"") -> 532.4925 | I69: =СводРецепт!$A$1 -> 1000 | J69: =Рецепты[[#This Row],[%]]*Рецепты[[#This Row],[Масса]] -> 750 | K69: =Рецепты[[#This Row],[Вес ингр-тов]]*VLOOKUP(Рецепты[[#This Row],[Состав]],Ингредиенты[],3,FALSE) -> 532.4925 | L69: =IF(VLOOKUP(Рецепты[[#This Row],[Состав]],Ингредиенты[],4,0)="Основа",VLOOKUP(Рецепты[[#This Row],[Способ]],Способ[],2,0),0%) -> 0.35 | M69: =VLOOKUP(Рецепты[[#This Row],[Способ]],Способ[],3,0) -> 2 | N69: =Рецепты[[#This Row],[р]]*100%/(100%-Рецепты[[#This Row],[Потери, %]])+Рецепты[[#This Row],[Маржа]]*(Рецепты[[#This Row],[р]]*100%)/(100%-Рецепты[[#This Row],[Потери, %]]) -> 2457.6577 | O69: =Рецепты[[#This Row],[Цена за 1 кг]]-(Рецепты[[#This Row],[р]]*100%/(100%-Рецепты[[#This Row],[Потери, %]])) -> 1638.4385 | P69: https://www.youtube.com/watch?v=VLTAbx7vvAo | Q69: D:\Video\Колбаса_рецепты\Еврейская копчёная колбаса в домашних условиях. Стандарт 1938г.mp4 | R69: =VLOOKUP(Рецепты[[#This Row],[Состав]],Ингредиенты[],9,0) -> Да
A70: Еврейская | B70: =B69 -> Колбаса | C70: =C69 -> Сырокопченое | D70: Жир говяжий | E70: =VLOOKUP(Рецепты[[#This Row],[Состав]],Ингредиенты[],2,0) -> Говядина | F70: 0.25 | G70: =IF(Рецепты[[#This Row],[%]]*1000>0,Рецепты[[#This Row],[%]]*1000,"") -> 250 | H70: =IFERROR(VLOOKUP(Рецепты[[#This Row],[Состав]],Ингредиенты!A:I,3,0)*Рецепты[[#This Row],[г]],"") -> 62.5 | I70: =СводРецепт!$A$1 -> 1000 | J70: =Рецепты[[#This Row],[%]]*Рецепты[[#This Row],[Масса]] -> 250 | K70: =Рецепты[[#This Row],[Вес ингр-тов]]*VLOOKUP(Рецепты[[#This Row],[Состав]],Ингредиенты[],3,FALSE) -> 62.5 | L70: =IF(VLOOKUP(Рецепты[[#This Row],[Состав]],Ингредиенты[],4,0)="Основа",VLOOKUP(Рецепты[[#This Row],[Способ]],Способ[],2,0),0%) -> 0.35 | M70: =VLOOKUP(Рецепты[[#This Row],[Способ]],Способ[],3,0) -> 2 | N70: =Рецепты[[#This Row],[р]]*100%/(100%-Рецепты[[#This Row],[Потери, %]])+Рецепты[[#This Row],[Маржа]]*(Рецепты[[#This Row],[р]]*100%)/(100%-Рецепты[[#This Row],[Потери, %]]) -> 288.46154 | O70: =Рецепты[[#This Row],[Цена за 1 кг]]-(Рецепты[[#This Row],[р]]*100%/(100%-Рецепты[[#This Row],[Потери, %]])) -> 192.30769 | P70: https://www.youtube.com/watch?v=VLTAbx7vvAo | Q70: D:\Video\Колбаса_рецепты\Еврейская копчёная колбаса в домашних условиях. Стандарт 1938г.mp5 | R70: =VLOOKUP(Рецепты[[#This Row],[Состав]],Ингредиенты[],9,0) -> Нет
A71: Еврейская | B71: =B70 -> Колбаса | C71: =C70 -> Сырокопченое | D71: Соль нитритная | E71: =VLOOKUP(Рецепты[[#This Row],[Состав]],Ингредиенты[],2,0) -> Специи | F71: 0.028 | G71: =IF(Рецепты[[#This Row],[%]]*1000>0,Рецепты[[#This Row],[%]]*1000,"") -> 28 | H71: =IFERROR(VLOOKUP(Рецепты[[#This Row],[Состав]],Ингредиенты!A:I,3,0)*Рецепты[[#This Row],[г]],"") -> 3.584 | I71: =СводРецепт!$A$1 -> 1000 | J71: =Рецепты[[#This Row],[%]]*Рецепты[[#This Row],[Масса]] -> 28 | K71: =Рецепты[[#This Row],[Вес ингр-тов]]*VLOOKUP(Рецепты[[#This Row],[Состав]],Ингредиенты[],3,FALSE) -> 3.584 | L71: =IF(VLOOKUP(Рецепты[[#This Row],[Состав]],Ингредиенты[],4,0)="Основа",VLOOKUP(Рецепты[[#This Row],[Способ]],Способ[],2,0),0%) -> 0 | M71: =VLOOKUP(Рецепты[[#This Row],[Способ]],Способ[],3,0) -> 2 | N71: =Рецепты[[#This Row],[р]]*100%/(100%-Рецепты[[#This Row],[Потери, %]])+Рецепты[[#This Row],[Маржа]]*(Рецепты[[#This Row],[р]]*100%)/(100%-Рецепты[[#This Row],[Потери, %]]) -> 10.752 | O71: =Рецепты[[#This Row],[Цена за 1 кг]]-(Рецепты[[#This Row],[р]]*100%/(100%-Рецепты[[#This Row],[Потери, %]])) -> 7.168 | P71: https://www.youtube.com/watch?v=VLTAbx7vvAo | Q71: D:\Video\Колбаса_рецепты\Еврейская копчёная колбаса в домашних условиях. Стандарт 1938г.mp6 | R71: =VLOOKUP(Рецепты[[#This Row],[Состав]],Ингредиенты[],9,0) -> Да
A72: Еврейская | B72: =B71 -> Колбаса | C72: =C71 -> Сырокопченое | D72: Сахар | E72: =VLOOKUP(Рецепты[[#This Row],[Состав]],Ингредиенты[],2,0) -> Специи | F72: 0.001 | G72: =IF(Рецепты[[#This Row],[%]]*1000>0,Рецепты[[#This Row],[%]]*1000,"") -> 1 | H72: =IFERROR(VLOOKUP(Рецепты[[#This Row],[Состав]],Ингредиенты!A:I,3,0)*Рецепты[[#This Row],[г]],"") -> 0.080882353 | I72: =СводРецепт!$A$1 -> 1000 | J72: =Рецепты[[#This Row],[%]]*Рецепты[[#This Row],[Масса]] -> 1 | K72: =Рецепты[[#This Row],[Вес ингр-тов]]*VLOOKUP(Рецепты[[#This Row],[Состав]],Ингредиенты[],3,FALSE) -> 0.080882353 | L72: =IF(VLOOKUP(Рецепты[[#This Row],[Состав]],Ингредиенты[],4,0)="Основа",VLOOKUP(Рецепты[[#This Row],[Способ]],Способ[],2,0),0%) -> 0 | M72: =VLOOKUP(Рецепты[[#This Row],[Способ]],Способ[],3,0) -> 2 | N72: =Рецепты[[#This Row],[р]]*100%/(100%-Рецепты[[#This Row],[Потери, %]])+Рецепты[[#This Row],[Маржа]]*(Рецепты[[#This Row],[р]]*100%)/(100%-Рецепты[[#This Row],[Потери, %]]) -> 0.24264706 | O72: =Рецепты[[#This Row],[Цена за 1 кг]]-(Рецепты[[#This Row],[р]]*100%/(100%-Рецепты[[#This Row],[Потери, %]])) -> 0.16176471 | P72: https://www.youtube.com/watch?v=VLTAbx7vvAo | Q72: D:\Video\Колбаса_рецепты\Еврейская копчёная колбаса в домашних условиях. Стандарт 1938г.mp7 | R72: =VLOOKUP(Рецепты[[#This Row],[Состав]],Ингредиенты[],9,0) -> Да
A73: Еврейская | B73: =B72 -> Колбаса | C73: =C72 -> Сырокопченое | D73: Перец черный молотый | E73: =VLOOKUP(Рецепты[[#This Row],[Состав]],Ингредиенты[],2,0) -> Специи | F73: 0.002 | G73: =IF(Рецепты[[#This Row],[%]]*1000>0,Рецепты[[#This Row],[%]]*1000,"") -> 2 | H73: =IFERROR(VLOOKUP(Рецепты[[#This Row],[Состав]],Ингредиенты!A:I,3,0)*Рецепты[[#This Row],[г]],"") -> 2.1890909 | I73: =СводРецепт!$A$1 -> 1000 | J73: =Рецепты[[#This Row],[%]]*Рецепты[[#This Row],[Масса]] -> 2 | K73: =Рецепты[[#This Row],[Вес ингр-тов]]*VLOOKUP(Рецепты[[#This Row],[Состав]],Ингредиенты[],3,FALSE) -> 2.1890909 | L73: =IF(VLOOKUP(Рецепты[[#This Row],[Состав]],Ингредиенты[],4,0)="Основа",VLOOKUP(Рецепты[[#This Row],[Способ]],Способ[],2,0),0%) -> 0 | M73: =VLOOKUP(Рецепты[[#This Row],[Способ]],Способ[],3,0) -> 2 | N73: =Рецепты[[#This Row],[р]]*100%/(100%-Рецепты[[#This Row],[Потери, %]])+Рецепты[[#This Row],[Маржа]]*(Рецепты[[#This Row],[р]]*100%)/(100%-Рецепты[[#This Row],[Потери, %]]) -> 6.5672727 | O73: =Рецепты[[#This Row],[Цена за 1 кг]]-(Рецепты[[#This Row],[р]]*100%/(100%-Рецепты[[#This Row],[Потери, %]])) -> 4.3781818 | P73: https://www.youtube.com/watch?v=VLTAbx7vvAo | Q73: D:\Video\Колбаса_рецепты\Еврейская копчёная колбаса в домашних условиях. Стандарт 1938г.mp8 | R73: =VLOOKUP(Рецепты[[#This Row],[Состав]],Ингредиенты[],9,0) -> Да
A74: Еврейская | B74: =B73 -> Колбаса | C74: =C73 -> Сырокопченое | D74: Чеснок сушеный | E74: =VLOOKUP(Рецепты[[#This Row],[Состав]],Ингредиенты[],2,0) -> Специи | F74: 0.001 | G74: =IF(Рецепты[[#This Row],[%]]*1000>0,Рецепты[[#This Row],[%]]*1000,"") -> 1 | H74: =IFERROR(VLOOKUP(Рецепты[[#This Row],[Состав]],Ингредиенты!A:I,3,0)*Рецепты[[#This Row],[г]],"") -> 0.87833333 | I74: =СводРецепт!$A$1 -> 1000 | J74: =Рецепты[[#This Row],[%]]*Рецепты[[#This Row],[Масса]] -> 1 | K74: =Рецепты[[#This Row],[Вес ингр-тов]]*VLOOKUP(Рецепты[[#This Row],[Состав]],Ингредиенты[],3,FALSE) -> 0.87833333 | L74: =IF(VLOOKUP(Рецепты[[#This Row],[Состав]],Ингредиенты[],4,0)="Основа",VLOOKUP(Рецепты[[#This Row],[Способ]],Способ[],2,0),0%) -> 0 | M74: =VLOOKUP(Рецепты[[#This Row],[Способ]],Способ[],3,0) -> 2 | N74: =Рецепты[[#This Row],[р]]*100%/(100%-Рецепты[[#This Row],[Потери, %]])+Рецепты[[#This Row],[Маржа]]*(Рецепты[[#This Row],[р]]*100%)/(100%-Рецепты[[#This Row],[Потери, %]]) -> 2.635 | O74: =Рецепты[[#This Row],[Цена за 1 кг]]-(Рецепты[[#This Row],[р]]*100%/(100%-Рецепты[[#This Row],[Потери, %]])) -> 1.7566667 | P74: https://www.youtube.com/watch?v=VLTAbx7vvAo | Q74: D:\Video\Колбаса_рецепты\Еврейская копчёная колбаса в домашних условиях. Стандарт 1938г.mp9 | R74: =VLOOKUP(Рецепты[[#This Row],[Состав]],Ингредиенты[],9,0) -> Да
A75: Еврейская | B75: =B74 -> Колбаса | C75: =C74 -> Сырокопченое | D75: Нало Ферм 45/50 | E75: =VLOOKUP(Рецепты[[#This Row],[Состав]],Ингредиенты[],2,0) -> Оболочка | F75: 0.001 | G75: =IF(Рецепты[[#This Row],[%]]*1000>0,Рецепты[[#This Row],[%]]*1000,"") -> 1 | H75: =IFERROR(VLOOKUP(Рецепты[[#This Row],[Состав]],Ингредиенты!A:I,3,0)*Рецепты[[#This Row],[г]],"") -> 32.760033 | I75: =СводРецепт!$A$1 -> 1000 | J75: =Рецепты[[#This Row],[%]]*Рецепты[[#This Row],[Масса]] -> 1 | K75: =Рецепты[[#This Row],[Вес ингр-тов]]*VLOOKUP(Рецепты[[#This Row],[Состав]],Ингредиенты[],3,FALSE) -> 32.760033 | L75: =IF(VLOOKUP(Рецепты[[#This Row],[Состав]],Ингредиенты[],4,0)="Основа",VLOOKUP(Рецепты[[#This Row],[Способ]],Способ[],2,0),0%) -> 0 | M75: =VLOOKUP(Рецепты[[#This Row],[Способ]],Способ[],3,0) -> 2 | N75: =Рецепты[[#This Row],[р]]*100%/(100%-Рецепты[[#This Row],[Потери, %]])+Рецепты[[#This Row],[Маржа]]*(Рецепты[[#This Row],[р]]*100%)/(100%-Рецепты[[#This Row],[Потери, %]]) -> 98.280098 | O75: =Рецепты[[#This Row],[Цена за 1 кг]]-(Рецепты[[#This Row],[р]]*100%/(100%-Рецепты[[#This Row],[Потери, %]])) -> 65.520066 | P75: https://www.youtube.com/watch?v=VLTAbx7vvAo | Q75: D:\Video\Колбаса_рецепты\Еврейская копчёная колбаса в домашних условиях. Стандарт 1938г.mp10 | R75: =VLOOKUP(Рецепты[[#This Row],[Состав]],Ингредиенты[],9,0) -> Да
A76: Московская | B76: =B74 -> Колбаса | C76: =C74 -> Сырокопченое | D76: Говядина | E76: =VLOOKUP(Рецепты[[#This Row],[Состав]],Ингредиенты[],2,0) -> Говядина | F76: 0.75 | G76: =IF(Рецепты[[#This Row],[%]]*1000>0,Рецепты[[#This Row],[%]]*1000,"") -> 750 | H76: =IFERROR(VLOOKUP(Рецепты[[#This Row],[Состав]],Ингредиенты!A:I,3,0)*Рецепты[[#This Row],[г]],"") -> 532.4925 | I76: =СводРецепт!$A$1 -> 1000 | J76: =Рецепты[[#This Row],[%]]*Рецепты[[#This Row],[Масса]] -> 750 | K76: =Рецепты[[#This Row],[Вес ингр-тов]]*VLOOKUP(Рецепты[[#This Row],[Состав]],Ингредиенты[],3,FALSE) -> 532.4925 | L76: =IF(VLOOKUP(Рецепты[[#This Row],[Состав]],Ингредиенты[],4,0)="Основа",VLOOKUP(Рецепты[[#This Row],[Способ]],Способ[],2,0),0%) -> 0.35 | M76: =VLOOKUP(Рецепты[[#This Row],[Способ]],Способ[],3,0) -> 2 | N76: =Рецепты[[#This Row],[р]]*100%/(100%-Рецепты[[#This Row],[Потери, %]])+Рецепты[[#This Row],[Маржа]]*(Рецепты[[#This Row],[р]]*100%)/(100%-Рецепты[[#This Row],[Потери, %]]) -> 2457.6577 | O76: =Рецепты[[#This Row],[Цена за 1 кг]]-(Рецепты[[#This Row],[р]]*100%/(100%-Рецепты[[#This Row],[Потери, %]])) -> 1638.4385 | P76: https://www.youtube.com/watch?v=m5Jg6Oz8stE | Q76: D:\Video\Колбаса_рецепты\МОСКОВСКАЯ КОПЧЕНАЯ домашняя колбаса ГОСТ 1938.mp4 | R76: =VLOOKUP(Рецепты[[#This Row],[Состав]],Ингредиенты[],9,0) -> Да
A77: Московская | B77: =B76 -> Колбаса | C77: =C76 -> Сырокопченое | D77: Шпик | E77: =VLOOKUP(Рецепты[[#This Row],[Состав]],Ингредиенты[],2,0) -> Свинина | F77: 0.25 | G77: =IF(Рецепты[[#This Row],[%]]*1000>0,Рецепты[[#This Row],[%]]*1000,"") -> 250 | H77: =IFERROR(VLOOKUP(Рецепты[[#This Row],[Состав]],Ингредиенты!A:I,3,0)*Рецепты[[#This Row],[г]],"") -> 75 | I77: =СводРецепт!$A$1 -> 1000 | J77: =Рецепты[[#This Row],[%]]*Рецепты[[#This Row],[Масса]] -> 250 | K77: =Рецепты[[#This Row],[Вес ингр-тов]]*VLOOKUP(Рецепты[[#This Row],[Состав]],Ингредиенты[],3,FALSE) -> 75 | L77: =IF(VLOOKUP(Рецепты[[#This Row],[Состав]],Ингредиенты[],4,0)="Основа",VLOOKUP(Рецепты[[#This Row],[Способ]],Способ[],2,0),0%) -> 0.35 | M77: =VLOOKUP(Рецепты[[#This Row],[Способ]],Способ[],3,0) -> 2 | N77: =Рецепты[[#This Row],[р]]*100%/(100%-Рецепты[[#This Row],[Потери, %]])+Рецепты[[#This Row],[Маржа]]*(Рецепты[[#This Row],[р]]*100%)/(100%-Рецепты[[#This Row],[Потери, %]]) -> 346.15385 | O77: =Рецепты[[#This Row],[Цена за 1 кг]]-(Рецепты[[#This Row],[р]]*100%/(100%-Рецепты[[#This Row],[Потери, %]])) -> 230.76923 | P77: https://www.youtube.com/watch?v=m5Jg6Oz8stE | Q77: D:\Video\Колбаса_рецепты\МОСКОВСКАЯ КОПЧЕНАЯ домашняя колбаса ГОСТ 1938.mp5 | R77: =VLOOKUP(Рецепты[[#This Row],[Состав]],Ингредиенты[],9,0) -> Нет
A78: Московская | B78: =B77 -> Колбаса | C78: =C77 -> Сырокопченое | D78: Соль нитритная | E78: =VLOOKUP(Рецепты[[#This Row],[Состав]],Ингредиенты[],2,0) -> Специи | F78: 0.026 | G78: =IF(Рецепты[[#This Row],[%]]*1000>0,Рецепты[[#This Row],[%]]*1000,"") -> 26 | H78: =IFERROR(VLOOKUP(Рецепты[[#This Row],[Состав]],Ингредиенты!A:I,3,0)*Рецепты[[#This Row],[г]],"") -> 3.328 | I78: =СводРецепт!$A$1 -> 1000 | J78: =Рецепты[[#This Row],[%]]*Рецепты[[#This Row],[Масса]] -> 26 | K78: =Рецепты[[#This Row],[Вес ингр-тов]]*VLOOKUP(Рецепты[[#This Row],[Состав]],Ингредиенты[],3,FALSE) -> 3.328 | L78: =IF(VLOOKUP(Рецепты[[#This Row],[Состав]],Ингредиенты[],4,0)="Основа",VLOOKUP(Рецепты[[#This Row],[Способ]],Способ[],2,0),0%) -> 0 | M78: =VLOOKUP(Рецепты[[#This Row],[Способ]],Способ[],3,0) -> 2 | N78: =Рецепты[[#This Row],[р]]*100%/(100%-Рецепты[[#This Row],[Потери, %]])+Рецепты[[#This Row],[Маржа]]*(Рецепты[[#This Row],[р]]*100%)/(100%-Рецепты[[#This Row],[Потери, %]]) -> 9.984 | O78: =Рецепты[[#This Row],[Цена за 1 кг]]-(Рецепты[[#This Row],[р]]*100%/(100%-Рецепты[[#This Row],[Потери, %]])) -> 6.656 | P78: https://www.youtube.com/watch?v=m5Jg6Oz8stE | Q78: D:\Video\Колбаса_рецепты\МОСКОВСКАЯ КОПЧЕНАЯ домашняя колбаса ГОСТ 1938.mp6 | R78: =VLOOKUP(Рецепты[[#This Row],[Состав]],Ингредиенты[],9,0) -> Да
A79: Московская | B79: =B78 -> Колбаса | C79: =C78 -> Сырокопченое | D79: Перец черный молотый | E79: =VLOOKUP(Рецепты[[#This Row],[Состав]],Ингредиенты[],2,0) -> Специи | F79: 0.001 | G79: =IF(Рецепты[[#This Row],[%]]*1000>0,Рецепты[[#This Row],[%]]*1000,"") -> 1 | H79: =IFERROR(VLOOKUP(Рецепты[[#This Row],[Состав]],Ингредиенты!A:I,3,0)*Рецепты[[#This Row],[г]],"") -> 1.0945455 | I79: =СводРецепт!$A$1 -> 1000 | J79: =Рецепты[[#This Row],[%]]*Рецепты[[#This Row],[Масса]] -> 1 | K79: =Рецепты[[#This Row],[Вес ингр-тов]]*VLOOKUP(Рецепты[[#This Row],[Состав]],Ингредиенты[],3,FALSE) -> 1.0945455 | L79: =IF(VLOOKUP(Рецепты[[#This Row],[Состав]],Ингредиенты[],4,0)="Основа",VLOOKUP(Рецепты[[#This Row],[Способ]],Способ[],2,0),0%) -> 0 | M79: =VLOOKUP(Рецепты[[#This Row],[Способ]],Способ[],3,0) -> 2 | N79: =Рецепты[[#This Row],[р]]*100%/(100%-Рецепты[[#This Row],[Потери, %]])+Рецепты[[#This Row],[Маржа]]*(Рецепты[[#This Row],[р]]*100%)/(100%-Рецепты[[#This Row],[Потери, %]]) -> 3.2836364 | O79: =Рецепты[[#This Row],[Цена за 1 кг]]-(Рецепты[[#This Row],[р]]*100%/(100%-Рецепты[[#This Row],[Потери, %]])) -> 2.1890909 | P79: https://www.youtube.com/watch?v=m5Jg6Oz8stE | Q79: D:\Video\Колбаса_рецепты\МОСКОВСКАЯ КОПЧЕНАЯ домашняя колбаса ГОСТ 1938.mp7 | R79: =VLOOKUP(Рецепты[[#This Row],[Состав]],Ингредиенты[],9,0) -> Да
A80: Московская | B80: =B79 -> Колбаса | C80: =C79 -> Сырокопченое | D80: Перец черный горошек | E80: =VLOOKUP(Рецепты[[#This Row],[Состав]],Ингредиенты[],2,0) -> Специи | F80: 0.001 | G80: =IF(Рецепты[[#This Row],[%]]*1000>0,Рецепты[[#This Row],[%]]*1000,"") -> 1 | H80: =IFERROR(VLOOKUP(Рецепты[[#This Row],[Состав]],Ингредиенты!A:I,3,0)*Рецепты[[#This Row],[г]],"") -> 1.14 | I80: =СводРецепт!$A$1 -> 1000 | J80: =Рецепты[[#This Row],[%]]*Рецепты[[#This Row],[Масса]] -> 1 | K80: =Рецепты[[#This Row],[Вес ингр-тов]]*VLOOKUP(Рецепты[[#This Row],[Состав]],Ингредиенты[],3,FALSE) -> 1.14 | L80: =IF(VLOOKUP(Рецепты[[#This Row],[Состав]],Ингредиенты[],4,0)="Основа",VLOOKUP(Рецепты[[#This Row],[Способ]],Способ[],2,0),0%) -> 0 | M80: =VLOOKUP(Рецепты[[#This Row],[Способ]],Способ[],3,0) -> 2 | N80: =Рецепты[[#This Row],[р]]*100%/(100%-Рецепты[[#This Row],[Потери, %]])+Рецепты[[#This Row],[Маржа]]*(Рецепты[[#This Row],[р]]*100%)/(100%-Рецепты[[#This Row],[Потери, %]]) -> 3.42 | O80: =Рецепты[[#This Row],[Цена за 1 кг]]-(Рецепты[[#This Row],[р]]*100%/(100%-Рецепты[[#This Row],[Потери, %]])) -> 2.28 | P80: https://www.youtube.com/watch?v=m5Jg6Oz8stE | Q80: D:\Video\Колбаса_рецепты\МОСКОВСКАЯ КОПЧЕНАЯ домашняя колбаса ГОСТ 1938.mp8 | R80: =VLOOKUP(Рецепты[[#This Row],[Состав]],Ингредиенты[],9,0) -> Да
A81: Московская | B81: =B80 -> Колбаса | C81: =C80 -> Сырокопченое | D81: Кардамон | E81: =VLOOKUP(Рецепты[[#This Row],[Состав]],Ингредиенты[],2,0) -> Специи | F81: 0.001 | G81: =IF(Рецепты[[#This Row],[%]]*1000>0,Рецепты[[#This Row],[%]]*1000,"") -> 1 | H81: =IFERROR(VLOOKUP(Рецепты[[#This Row],[Состав]],Ингредиенты!A:I,3,0)*Рецепты[[#This Row],[г]],"") -> 1.5133333 | I81: =СводРецепт!$A$1 -> 1000 | J81: =Рецепты[[#This Row],[%]]*Рецепты[[#This Row],[Масса]] -> 1 | K81: =Рецепты[[#This Row],[Вес ингр-тов]]*VLOOKUP(Рецепты[[#This Row],[Состав]],Ингредиенты[],3,FALSE) -> 1.5133333 | L81: =IF(VLOOKUP(Рецепты[[#This Row],[Состав]],Ингредиенты[],4,0)="Основа",VLOOKUP(Рецепты[[#This Row],[Способ]],Способ[],2,0),0%) -> 0 | M81: =VLOOKUP(Рецепты[[#This Row],[Способ]],Способ[],3,0) -> 2 | N81: =Рецепты[[#This Row],[р]]*100%/(100%-Рецепты[[#This Row],[Потери, %]])+Рецепты[[#This Row],[Маржа]]*(Рецепты[[#This Row],[р]]*100%)/(100%-Рецепты[[#This Row],[Потери, %]]) -> 4.54 | O81: =Рецепты[[#This Row],[Цена за 1 кг]]-(Рецепты[[#This Row],[р]]*100%/(100%-Рецепты[[#This Row],[Потери, %]])) -> 3.0266667 | P81: https://www.youtube.com/watch?v=m5Jg6Oz8stE | Q81: D:\Video\Колбаса_рецепты\МОСКОВСКАЯ КОПЧЕНАЯ домашняя колбаса ГОСТ 1938.mp9 | R81: =VLOOKUP(Рецепты[[#This Row],[Состав]],Ингредиенты[],9,0) -> Да
A82: Московская | B82: =B81 -> Колбаса | C82: =C81 -> Сырокопченое | D82: Сахар | E82: =VLOOKUP(Рецепты[[#This Row],[Состав]],Ингредиенты[],2,0) -> Специи | F82: 0.002 | G82: =IF(Рецепты[[#This Row],[%]]*1000>0,Рецепты[[#This Row],[%]]*1000,"") -> 2 | H82: =IFERROR(VLOOKUP(Рецепты[[#This Row],[Состав]],Ингредиенты!A:I,3,0)*Рецепты[[#This Row],[г]],"") -> 0.16176471 | I82: =СводРецепт!$A$1 -> 1000 | J82: =Рецепты[[#This Row],[%]]*Рецепты[[#This Row],[Масса]] -> 2 | K82: =Рецепты[[#This Row],[Вес ингр-тов]]*VLOOKUP(Рецепты[[#This Row],[Состав]],Ингредиенты[],3,FALSE) -> 0.16176471 | L82: =IF(VLOOKUP(Рецепты[[#This Row],[Состав]],Ингредиенты[],4,0)="Основа",VLOOKUP(Рецепты[[#This Row],[Способ]],Способ[],2,0),0%) -> 0 | M82: =VLOOKUP(Рецепты[[#This Row],[Способ]],Способ[],3,0) -> 2 | N82: =Рецепты[[#This Row],[р]]*100%/(100%-Рецепты[[#This Row],[Потери, %]])+Рецепты[[#This Row],[Маржа]]*(Рецепты[[#This Row],[р]]*100%)/(100%-Рецепты[[#This Row],[Потери, %]]) -> 0.48529412 | O82: =Рецепты[[#This Row],[Цена за 1 кг]]-(Рецепты[[#This Row],[р]]*100%/(100%-Рецепты[[#This Row],[Потери, %]])) -> 0.32352941 | P82: https://www.youtube.com/watch?v=m5Jg6Oz8stE | Q82: D:\Video\Колбаса_рецепты\МОСКОВСКАЯ КОПЧЕНАЯ домашняя колбаса ГОСТ 1938.mp10 | R82: =VLOOKUP(Рецепты[[#This Row],[Состав]],Ингредиенты[],9,0) -> Да
A83: Московская | B83: =B82 -> Колбаса | C83: =C82 -> Сырокопченое | D83: Нало Ферм 45/50 | E83: =VLOOKUP(Рецепты[[#This Row],[Состав]],Ингредиенты[],2,0) -> Оболочка | F83: 0.001 | G83: =IF(Рецепты[[#This Row],[%]]*1000>0,Рецепты[[#This Row],[%]]*1000,"") -> 1 | H83: =IFERROR(VLOOKUP(Рецепты[[#This Row],[Состав]],Ингредиенты!A:I,3,0)*Рецепты[[#This Row],[г]],"") -> 32.760033 | I83: =СводРецепт!$A$1 -> 1000 | J83: =Рецепты[[#This Row],[%]]*Рецепты[[#This Row],[Масса]] -> 1 | K83: =Рецепты[[#This Row],[Вес ингр-тов]]*VLOOKUP(Рецепты[[#This Row],[Состав]],Ингредиенты[],3,FALSE) -> 32.760033 | L83: =IF(VLOOKUP(Рецепты[[#This Row],[Состав]],Ингредиенты[],4,0)="Основа",VLOOKUP(Рецепты[[#This Row],[Способ]],Способ[],2,0),0%) -> 0 | M83: =VLOOKUP(Рецепты[[#This Row],[Способ]],Способ[],3,0) -> 2 | N83: =Рецепты[[#This Row],[р]]*100%/(100%-Рецепты[[#This Row],[Потери, %]])+Рецепты[[#This Row],[Маржа]]*(Рецепты[[#This Row],[р]]*100%)/(100%-Рецепты[[#This Row],[Потери, %]]) -> 98.280098 | O83: =Рецепты[[#This Row],[Цена за 1 кг]]-(Рецепты[[#This Row],[р]]*100%/(100%-Рецепты[[#This Row],[Потери, %]])) -> 65.520066 | P83: https://www.youtube.com/watch?v=m5Jg6Oz8stE | Q83: D:\Video\Колбаса_рецепты\МОСКОВСКАЯ КОПЧЕНАЯ домашняя колбаса ГОСТ 1938.mp11 | R83: =VLOOKUP(Рецепты[[#This Row],[Состав]],Ингредиенты[],9,0) -> Да
A84: Салями Милано | B84: =B82 -> Колбаса | C84: Сыровяленное | D84: Окорок свиной | E84: =VLOOKUP(Рецепты[[#This Row],[Состав]],Ингредиенты[],2,0) -> Свинина | F84: 0.8 | G84: =IF(Рецепты[[#This Row],[%]]*1000>0,Рецепты[[#This Row],[%]]*1000,"") -> 800 | H84: =IFERROR(VLOOKUP(Рецепты[[#This Row],[Состав]],Ингредиенты!A:I,3,0)*Рецепты[[#This Row],[г]],"") -> 295.2 | I84: =СводРецепт!$A$1 -> 1000 | J84: =Рецепты[[#This Row],[%]]*Рецепты[[#This Row],[Масса]] -> 800 | K84: =Рецепты[[#This Row],[Вес ингр-тов]]*VLOOKUP(Рецепты[[#This Row],[Состав]],Ингредиенты[],3,FALSE) -> 295.2 | L84: =IF(VLOOKUP(Рецепты[[#This Row],[Состав]],Ингредиенты[],4,0)="Основа",VLOOKUP(Рецепты[[#This Row],[Способ]],Способ[],2,0),0%) -> 0.35 | M84: =VLOOKUP(Рецепты[[#This Row],[Способ]],Способ[],3,0) -> 2 | N84: =Рецепты[[#This Row],[р]]*100%/(100%-Рецепты[[#This Row],[Потери, %]])+Рецепты[[#This Row],[Маржа]]*(Рецепты[[#This Row],[р]]*100%)/(100%-Рецепты[[#This Row],[Потери, %]]) -> 1362.4615 | O84: =Рецепты[[#This Row],[Цена за 1 кг]]-(Рецепты[[#This Row],[р]]*100%/(100%-Рецепты[[#This Row],[Потери, %]])) -> 908.30769 | P84: https://www.youtube.com/watch?v=NcF15xTHz-U | Q84: D:\Video\Колбаса_рецепты\Салями Милано со стартовыми культурами.mp4 | R84: =VLOOKUP(Рецепты[[#This Row],[Состав]],Ингредиенты[],9,0) -> Да
A85: Салями Милано | B85: =B84 -> Колбаса | C85: =C84 -> Сыровяленное | D85: Шпик | E85: =VLOOKUP(Рецепты[[#This Row],[Состав]],Ингредиенты[],2,0) -> Свинина | F85: 0.2 | G85: =IF(Рецепты[[#This Row],[%]]*1000>0,Рецепты[[#This Row],[%]]*1000,"") -> 200 | H85: =IFERROR(VLOOKUP(Рецепты[[#This Row],[Состав]],Ингредиенты!A:I,3,0)*Рецепты[[#This Row],[г]],"") -> 60 | I85: =СводРецепт!$A$1 -> 1000 | J85: =Рецепты[[#This Row],[%]]*Рецепты[[#This Row],[Масса]] -> 200 | K85: =Рецепты[[#This Row],[Вес ингр-тов]]*VLOOKUP(Рецепты[[#This Row],[Состав]],Ингредиенты[],3,FALSE) -> 60 | L85: =IF(VLOOKUP(Рецепты[[#This Row],[Состав]],Ингредиенты[],4,0)="Основа",VLOOKUP(Рецепты[[#This Row],[Способ]],Способ[],2,0),0%) -> 0.35 | M85: =VLOOKUP(Рецепты[[#This Row],[Способ]],Способ[],3,0) -> 2 | N85: =Рецепты[[#This Row],[р]]*100%/(100%-Рецепты[[#This Row],[Потери, %]])+Рецепты[[#This Row],[Маржа]]*(Рецепты[[#This Row],[р]]*100%)/(100%-Рецепты[[#This Row],[Потери, %]]) -> 276.92308 | O85: =Рецепты[[#This Row],[Цена за 1 кг]]-(Рецепты[[#This Row],[р]]*100%/(100%-Рецепты[[#This Row],[Потери, %]])) -> 184.61538 | P85: https://www.youtube.com/watch?v=NcF15xTHz-U | Q85: D:\Video\Колбаса_рецепты\Салями Милано со стартовыми культурами.mp5 | R85: =VLOOKUP(Рецепты[[#This Row],[Состав]],Ингредиенты[],9,0) -> Нет
A86: Салями Милано | B86: =B85 -> Колбаса | C86: =C85 -> Сыровяленное | D86: Соль нитритная | E86: =VLOOKUP(Рецепты[[#This Row],[Состав]],Ингредиенты[],2,0) -> Специи | F86: 0.026 | G86: =IF(Рецепты[[#This Row],[%]]*1000>0,Рецепты[[#This Row],[%]]*1000,"") -> 26 | H86: =IFERROR(VLOOKUP(Рецепты[[#This Row],[Состав]],Ингредиенты!A:I,3,0)*Рецепты[[#This Row],[г]],"") -> 3.328 | I86: =СводРецепт!$A$1 -> 1000 | J86: =Рецепты[[#This Row],[%]]*Рецепты[[#This Row],[Масса]] -> 26 | K86: =Рецепты[[#This Row],[Вес ингр-тов]]*VLOOKUP(Рецепты[[#This Row],[Состав]],Ингредиенты[],3,FALSE) -> 3.328 | L86: =IF(VLOOKUP(Рецепты[[#This Row],[Состав]],Ингредиенты[],4,0)="Основа",VLOOKUP(Рецепты[[#This Row],[Способ]],Способ[],2,0),0%) -> 0 | M86: =VLOOKUP(Рецепты[[#This Row],[Способ]],Способ[],3,0) -> 2 | N86: =Рецепты[[#This Row],[р]]*100%/(100%-Рецепты[[#This Row],[Потери, %]])+Рецепты[[#This Row],[Маржа]]*(Рецепты[[#This Row],[р]]*100%)/(100%-Рецепты[[#This Row],[Потери, %]]) -> 9.984 | O86: =Рецепты[[#This Row],[Цена за 1 кг]]-(Рецепты[[#This Row],[р]]*100%/(100%-Рецепты[[#This Row],[Потери, %]])) -> 6.656 | P86: https://www.youtube.com/watch?v=NcF15xTHz-U | Q86: D:\Video\Колбаса_рецепты\Салями Милано со стартовыми культурами.mp6 | R86: =VLOOKUP(Рецепты[[#This Row],[Состав]],Ингредиенты[],9,0) -> Да
A87: Салями Милано | B87: =B86 -> Колбаса | C87: =C86 -> Сыровяленное | D87: Перец душистый горошек | E87: =VLOOKUP(Рецепты[[#This Row],[Состав]],Ингредиенты[],2,0) -> Специи | F87: 0.002 | G87: =IF(Рецепты[[#This Row],[%]]*1000>0,Рецепты[[#This Row],[%]]*1000,"") -> 2 | H87: =IFERROR(VLOOKUP(Рецепты[[#This Row],[Состав]],Ингредиенты!A:I,3,0)*Рецепты[[#This Row],[г]],"") -> 3.992 | I87: =СводРецепт!$A$1 -> 1000 | J87: =Рецепты[[#This Row],[%]]*Рецепты[[#This Row],[Масса]] -> 2 | K87: =Рецепты[[#This Row],[Вес ингр-тов]]*VLOOKUP(Рецепты[[#This Row],[Состав]],Ингредиенты[],3,FALSE) -> 3.992 | L87: =IF(VLOOKUP(Рецепты[[#This Row],[Состав]],Ингредиенты[],4,0)="Основа",VLOOKUP(Рецепты[[#This Row],[Способ]],Способ[],2,0),0%) -> 0 | M87: =VLOOKUP(Рецепты[[#This Row],[Способ]],Способ[],3,0) -> 2 | N87: =Рецепты[[#This Row],[р]]*100%/(100%-Рецепты[[#This Row],[Потери, %]])+Рецепты[[#This Row],[Маржа]]*(Рецепты[[#This Row],[р]]*100%)/(100%-Рецепты[[#This Row],[Потери, %]]) -> 11.976 | O87: =Рецепты[[#This Row],[Цена за 1 кг]]-(Рецепты[[#This Row],[р]]*100%/(100%-Рецепты[[#This Row],[Потери, %]])) -> 7.984 | P87: https://www.youtube.com/watch?v=NcF15xTHz-U | Q87: D:\Video\Колбаса_рецепты\Салями Милано со стартовыми культурами.mp7 | R87: =VLOOKUP(Рецепты[[#This Row],[Состав]],Ингредиенты[],9,0) -> Да
A88: Салями Милано | B88: =B87 -> Колбаса | C88: =C87 -> Сыровяленное | D88: Чеснок сушеный | E88: =VLOOKUP(Рецепты[[#This Row],[Состав]],Ингредиенты[],2,0) -> Специи | F88: 0.001 | G88: =IF(Рецепты[[#This Row],[%]]*1000>0,Рецепты[[#This Row],[%]]*1000,"") -> 1 | H88: =IFERROR(VLOOKUP(Рецепты[[#This Row],[Состав]],Ингредиенты!A:I,3,0)*Рецепты[[#This Row],[г]],"") -> 0.87833333 | I88: =СводРецепт!$A$1 -> 1000 | J88: =Рецепты[[#This Row],[%]]*Рецепты[[#This Row],[Масса]] -> 1 | K88: =Рецепты[[#This Row],[Вес ингр-тов]]*VLOOKUP(Рецепты[[#This Row],[Состав]],Ингредиенты[],3,FALSE) -> 0.87833333 | L88: =IF(VLOOKUP(Рецепты[[#This Row],[Состав]],Ингредиенты[],4,0)="Основа",VLOOKUP(Рецепты[[#This Row],[Способ]],Способ[],2,0),0%) -> 0 | M88: =VLOOKUP(Рецепты[[#This Row],[Способ]],Способ[],3,0) -> 2 | N88: =Рецепты[[#This Row],[р]]*100%/(100%-Рецепты[[#This Row],[Потери, %]])+Рецепты[[#This Row],[Маржа]]*(Рецепты[[#This Row],[р]]*100%)/(100%-Рецепты[[#This Row],[Потери, %]]) -> 2.635 | O88: =Рецепты[[#This Row],[Цена за 1 кг]]-(Рецепты[[#This Row],[р]]*100%/(100%-Рецепты[[#This Row],[Потери, %]])) -> 1.7566667 | P88: https://www.youtube.com/watch?v=NcF15xTHz-U | Q88: D:\Video\Колбаса_рецепты\Салями Милано со стартовыми культурами.mp8 | R88: =VLOOKUP(Рецепты[[#This Row],[Состав]],Ингредиенты[],9,0) -> Да
A89: Салями Милано | B89: =B88 -> Колбаса | C89: =C88 -> Сыровяленное | D89: Мускатный орех | E89: =VLOOKUP(Рецепты[[#This Row],[Состав]],Ингредиенты[],2,0) -> Специи | F89: 0.001 | G89: =IF(Рецепты[[#This Row],[%]]*1000>0,Рецепты[[#This Row],[%]]*1000,"") -> 1 | H89: =IFERROR(VLOOKUP(Рецепты[[#This Row],[Состав]],Ингредиенты!A:I,3,0)*Рецепты[[#This Row],[г]],"") -> 2.0772727 | I89: =СводРецепт!$A$1 -> 1000 | J89: =Рецепты[[#This Row],[%]]*Рецепты[[#This Row],[Масса]] -> 1 | K89: =Рецепты[[#This Row],[Вес ингр-тов]]*VLOOKUP(Рецепты[[#This Row],[Состав]],Ингредиенты[],3,FALSE) -> 2.0772727 | L89: =IF(VLOOKUP(Рецепты[[#This Row],[Состав]],Ингредиенты[],4,0)="Основа",VLOOKUP(Рецепты[[#This Row],[Способ]],Способ[],2,0),0%) -> 0 | M89: =VLOOKUP(Рецепты[[#This Row],[Способ]],Способ[],3,0) -> 2 | N89: =Рецепты[[#This Row],[р]]*100%/(100%-Рецепты[[#This Row],[Потери, %]])+Рецепты[[#This Row],[Маржа]]*(Рецепты[[#This Row],[р]]*100%)/(100%-Рецепты[[#This Row],[Потери, %]]) -> 6.2318182 | O89: =Рецепты[[#This Row],[Цена за 1 кг]]-(Рецепты[[#This Row],[р]]*100%/(100%-Рецепты[[#This Row],[Потери, %]])) -> 4.1545455 | P89: https://www.youtube.com/watch?v=NcF15xTHz-U | Q89: D:\Video\Колбаса_рецепты\Салями Милано со стартовыми культурами.mp9 | R89: =VLOOKUP(Рецепты[[#This Row],[Состав]],Ингредиенты[],9,0) -> Да
A90: Салями Милано | B90: =B89 -> Колбаса | C90: =C89 -> Сыровяленное | D90: Фенхель | E90: =VLOOKUP(Рецепты[[#This Row],[Состав]],Ингредиенты[],2,0) -> Специи | F90: 0.001 | G90: =IF(Рецепты[[#This Row],[%]]*1000>0,Рецепты[[#This Row],[%]]*1000,"") -> 1 | H90: =IFERROR(VLOOKUP(Рецепты[[#This Row],[Состав]],Ингредиенты!A:I,3,0)*Рецепты[[#This Row],[г]],"") -> 1.4105263 | I90: =СводРецепт!$A$1 -> 1000 | J90: =Рецепты[[#This Row],[%]]*Рецепты[[#This Row],[Масса]] -> 1 | K90: =Рецепты[[#This Row],[Вес ингр-тов]]*VLOOKUP(Рецепты[[#This Row],[Состав]],Ингредиенты[],3,FALSE) -> 1.4105263 | L90: =IF(VLOOKUP(Рецепты[[#This Row],[Состав]],Ингредиенты[],4,0)="Основа",VLOOKUP(Рецепты[[#This Row],[Способ]],Способ[],2,0),0%) -> 0 | M90: =VLOOKUP(Рецепты[[#This Row],[Способ]],Способ[],3,0) -> 2 | N90: =Рецепты[[#This Row],[р]]*100%/(100%-Рецепты[[#This Row],[Потери, %]])+Рецепты[[#This Row],[Маржа]]*(Рецепты[[#This Row],[р]]*100%)/(100%-Рецепты[[#This Row],[Потери, %]]) -> 4.2315789 | O90: =Рецепты[[#This Row],[Цена за 1 кг]]-(Рецепты[[#This Row],[р]]*100%/(100%-Рецепты[[#This Row],[Потери, %]])) -> 2.8210526 | P90: https://www.youtube.com/watch?v=NcF15xTHz-U | Q90: D:\Video\Колбаса_рецепты\Салями Милано со стартовыми культурами.mp10 | R90: =VLOOKUP(Рецепты[[#This Row],[Состав]],Ингредиенты[],9,0) -> Да
A91: Салями Милано | B91: =B90 -> Колбаса | C91: =C90 -> Сыровяленное | D91: Вино красное сухое | E91: =VLOOKUP(Рецепты[[#This Row],[Состав]],Ингредиенты[],2,0) -> Добавки | F91: 0.03 | G91: =IF(Рецепты[[#This Row],[%]]*1000>0,Рецепты[[#This Row],[%]]*1000,"") -> 30 | H91: =IFERROR(VLOOKUP(Рецепты[[#This Row],[Состав]],Ингредиенты!A:I,3,0)*Рецепты[[#This Row],[г]],"") -> 15.51 | I91: =СводРецепт!$A$1 -> 1000 | J91: =Рецепты[[#This Row],[%]]*Рецепты[[#This Row],[Масса]] -> 30 | K91: =Рецепты[[#This Row],[Вес ингр-тов]]*VLOOKUP(Рецепты[[#This Row],[Состав]],Ингредиенты[],3,FALSE) -> 15.51 | L91: =IF(VLOOKUP(Рецепты[[#This Row],[Состав]],Ингредиенты[],4,0)="Основа",VLOOKUP(Рецепты[[#This Row],[Способ]],Способ[],2,0),0%) -> 0 | M91: =VLOOKUP(Рецепты[[#This Row],[Способ]],Способ[],3,0) -> 2 | N91: =Рецепты[[#This Row],[р]]*100%/(100%-Рецепты[[#This Row],[Потери, %]])+Рецепты[[#This Row],[Маржа]]*(Рецепты[[#This Row],[р]]*100%)/(100%-Рецепты[[#This Row],[Потери, %]]) -> 46.53 | O91: =Рецепты[[#This Row],[Цена за 1 кг]]-(Рецепты[[#This Row],[р]]*100%/(100%-Рецепты[[#This Row],[Потери, %]])) -> 31.02 | P91: https://www.youtube.com/watch?v=NcF15xTHz-U | Q91: D:\Video\Колбаса_рецепты\Салями Милано со стартовыми культурами.mp11 | R91: =VLOOKUP(Рецепты[[#This Row],[Состав]],Ингредиенты[],9,0) -> Да
A92: Салями Милано | B92: =B91 -> Колбаса | C92: =C91 -> Сыровяленное | D92: Стартовые культуры | E92: =VLOOKUP(Рецепты[[#This Row],[Состав]],Ингредиенты[],2,0) -> Специи | F92: 0.0005 | G92: =IF(Рецепты[[#This Row],[%]]*1000>0,Рецепты[[#This Row],[%]]*1000,"") -> 0.5 | H92: =IFERROR(VLOOKUP(Рецепты[[#This Row],[Состав]],Ингредиенты!A:I,3,0)*Рецепты[[#This Row],[г]],"") -> 2.48 | I92: =СводРецепт!$A$1 -> 1000 | J92: =Рецепты[[#This Row],[%]]*Рецепты[[#This Row],[Масса]] -> 0.5 | K92: =Рецепты[[#This Row],[Вес ингр-тов]]*VLOOKUP(Рецепты[[#This Row],[Состав]],Ингредиенты[],3,FALSE) -> 2.48 | L92: =IF(VLOOKUP(Рецепты[[#This Row],[Состав]],Ингредиенты[],4,0)="Основа",VLOOKUP(Рецепты[[#This Row],[Способ]],Способ[],2,0),0%) -> 0 | M92: =VLOOKUP(Рецепты[[#This Row],[Способ]],Способ[],3,0) -> 2 | N92: =Рецепты[[#This Row],[р]]*100%/(100%-Рецепты[[#This Row],[Потери, %]])+Рецепты[[#This Row],[Маржа]]*(Рецепты[[#This Row],[р]]*100%)/(100%-Рецепты[[#This Row],[Потери, %]]) -> 7.44 | O92: =Рецепты[[#This Row],[Цена за 1 кг]]-(Рецепты[[#This Row],[р]]*100%/(100%-Рецепты[[#This Row],[Потери, %]])) -> 4.96 | P92: https://www.youtube.com/watch?v=NcF15xTHz-U | Q92: D:\Video\Колбаса_рецепты\Салями Милано со стартовыми культурами.mp12 | R92: =VLOOKUP(Рецепты[[#This Row],[Состав]],Ингредиенты[],9,0) -> Да
A93: Салями Милано | B93: =B92 -> Колбаса | C93: =C92 -> Сыровяленное | D93: Моносахара | E93: =VLOOKUP(Рецепты[[#This Row],[Состав]],Ингредиенты[],2,0) -> Специи | F93: 0.005 | G93: =IF(Рецепты[[#This Row],[%]]*1000>0,Рецепты[[#This Row],[%]]*1000,"") -> 5 | H93: =IFERROR(VLOOKUP(Рецепты[[#This Row],[Состав]],Ингредиенты!A:I,3,0)*Рецепты[[#This Row],[г]],"") -> 9.55 | I93: =СводРецепт!$A$1 -> 1000 | J93: =Рецепты[[#This Row],[%]]*Рецепты[[#This Row],[Масса]] -> 5 | K93: =Рецепты[[#This Row],[Вес ингр-тов]]*VLOOKUP(Рецепты[[#This Row],[Состав]],Ингредиенты[],3,FALSE) -> 9.55 | L93: =IF(VLOOKUP(Рецепты[[#This Row],[Состав]],Ингредиенты[],4,0)="Основа",VLOOKUP(Рецепты[[#This Row],[Способ]],Способ[],2,0),0%) -> 0 | M93: =VLOOKUP(Рецепты[[#This Row],[Способ]],Способ[],3,0) -> 2 | N93: =Рецепты[[#This Row],[р]]*100%/(100%-Рецепты[[#This Row],[Потери, %]])+Рецепты[[#This Row],[Маржа]]*(Рецепты[[#This Row],[р]]*100%)/(100%-Рецепты[[#This Row],[Потери, %]]) -> 28.65 | O93: =Рецепты[[#This Row],[Цена за 1 кг]]-(Рецепты[[#This Row],[р]]*100%/(100%-Рецепты[[#This Row],[Потери, %]])) -> 19.1 | P93: https://www.youtube.com/watch?v=NcF15xTHz-U | Q93: D:\Video\Колбаса_рецепты\Салями Милано со стартовыми культурами.mp13 | R93: =VLOOKUP(Рецепты[[#This Row],[Состав]],Ингредиенты[],9,0) -> Да
A94: Салями Милано | B94: =B93 -> Колбаса | C94: =C93 -> Сыровяленное | D94: Нало Ферм 45/50 | E94: =VLOOKUP(Рецепты[[#This Row],[Состав]],Ингредиенты[],2,0) -> Оболочка | F94: 0.001 | G94: =IF(Рецепты[[#This Row],[%]]*1000>0,Рецепты[[#This Row],[%]]*1000,"") -> 1 | H94: =IFERROR(VLOOKUP(Рецепты[[#This Row],[Состав]],Ингредиенты!A:I,3,0)*Рецепты[[#This Row],[г]],"") -> 32.760033 | I94: =СводРецепт!$A$1 -> 1000 | J94: =Рецепты[[#This Row],[%]]*Рецепты[[#This Row],[Масса]] -> 1 | K94: =Рецепты[[#This Row],[Вес ингр-тов]]*VLOOKUP(Рецепты[[#This Row],[Состав]],Ингредиенты[],3,FALSE) -> 32.760033 | L94: =IF(VLOOKUP(Рецепты[[#This Row],[Состав]],Ингредиенты[],4,0)="Основа",VLOOKUP(Рецепты[[#This Row],[Способ]],Способ[],2,0),0%) -> 0 | M94: =VLOOKUP(Рецепты[[#This Row],[Способ]],Способ[],3,0) -> 2 | N94: =Рецепты[[#This Row],[р]]*100%/(100%-Рецепты[[#This Row],[Потери, %]])+Рецепты[[#This Row],[Маржа]]*(Рецепты[[#This Row],[р]]*100%)/(100%-Рецепты[[#This Row],[Потери, %]]) -> 98.280098 | O94: =Рецепты[[#This Row],[Цена за 1 кг]]-(Рецепты[[#This Row],[р]]*100%/(100%-Рецепты[[#This Row],[Потери, %]])) -> 65.520066 | P94: https://www.youtube.com/watch?v=NcF15xTHz-U | Q94: D:\Video\Колбаса_рецепты\Салями Милано со стартовыми культурами.mp14 | R94: =VLOOKUP(Рецепты[[#This Row],[Состав]],Ингредиенты[],9,0) -> Да
A95: Сельдь пряная | B95: Рыба | C95: Соленое | D95: Сельдь | E95: =VLOOKUP(Рецепты[[#This Row],[Состав]],Ингредиенты[],2,0) -> Рыба | F95: 1 | G95: =IF(Рецепты[[#This Row],[%]]*1000>0,Рецепты[[#This Row],[%]]*1000,"") -> 1000 | H95: =IFERROR(VLOOKUP(Рецепты[[#This Row],[Состав]],Ингредиенты!A:I,3,0)*Рецепты[[#This Row],[г]],"") -> 342.85714 | I95: =СводРецепт!$A$1 -> 1000 | J95: =Рецепты[[#This Row],[%]]*Рецепты[[#This Row],[Масса]] -> 1000 | K95: =Рецепты[[#This Row],[Вес ингр-тов]]*VLOOKUP(Рецепты[[#This Row],[Состав]],Ингредиенты[],3,FALSE) -> 342.85714 | L95: =IF(VLOOKUP(Рецепты[[#This Row],[Состав]],Ингредиенты[],4,0)="Основа",VLOOKUP(Рецепты[[#This Row],[Способ]],Способ[],2,0),0%) -> 0.05 | M95: =VLOOKUP(Рецепты[[#This Row],[Способ]],Способ[],3,0) -> 0.5 | N95: =Рецепты[[#This Row],[р]]*100%/(100%-Рецепты[[#This Row],[Потери, %]])+Рецепты[[#This Row],[Маржа]]*(Рецепты[[#This Row],[р]]*100%)/(100%-Рецепты[[#This Row],[Потери, %]]) -> 541.35338 | O95: =Рецепты[[#This Row],[Цена за 1 кг]]-(Рецепты[[#This Row],[р]]*100%/(100%-Рецепты[[#This Row],[Потери, %]])) -> 180.45113 | P95: https://www.youtube.com/watch?v=Ci5-qEbJGXQ | Q95: D:\Video\Колбаса_рецепты\Сельдь пряного посола. Рецептура для рассола. Отделение филе от костей.mp4 | R95: =VLOOKUP(Рецепты[[#This Row],[Состав]],Ингредиенты[],9,0) -> Нет
A96: Сельдь пряная | B96: =B95 -> Рыба | C96: =C95 -> Соленое | D96: Вода | E96: =VLOOKUP(Рецепты[[#This Row],[Состав]],Ингредиенты[],2,0) -> Добавки | F96: 1.43 | G96: =IF(Рецепты[[#This Row],[%]]*1000>0,Рецепты[[#This Row],[%]]*1000,"") -> 1430 | H96: =IFERROR(VLOOKUP(Рецепты[[#This Row],[Состав]],Ингредиенты!A:I,3,0)*Рецепты[[#This Row],[г]],"") -> 1.43 | I96: =СводРецепт!$A$1 -> 1000 | J96: =Рецепты[[#This Row],[%]]*Рецепты[[#This Row],[Масса]] -> 1430 | K96: =Рецепты[[#This Row],[Вес ингр-тов]]*VLOOKUP(Рецепты[[#This Row],[Состав]],Ингредиенты[],3,FALSE) -> 1.43 | L96: =IF(VLOOKUP(Рецепты[[#This Row],[Состав]],Ингредиенты[],4,0)="Основа",VLOOKUP(Рецепты[[#This Row],[Способ]],Способ[],2,0),0%) -> 0 | M96: =VLOOKUP(Рецепты[[#This Row],[Способ]],Способ[],3,0) -> 0.5 | N96: =Рецепты[[#This Row],[р]]*100%/(100%-Рецепты[[#This Row],[Потери, %]])+Рецепты[[#This Row],[Маржа]]*(Рецепты[[#This Row],[р]]*100%)/(100%-Рецепты[[#This Row],[Потери, %]]) -> 2.145 | O96: =Рецепты[[#This Row],[Цена за 1 кг]]-(Рецепты[[#This Row],[р]]*100%/(100%-Рецепты[[#This Row],[Потери, %]])) -> 0.715 | P96: https://www.youtube.com/watch?v=Ci5-qEbJGXQ | Q96: D:\Video\Колбаса_рецепты\Сельдь пряного посола. Рецептура для рассола. Отделение филе от костей.mp5 | R96: =VLOOKUP(Рецепты[[#This Row],[Состав]],Ингредиенты[],9,0) -> Да
A97: Сельдь пряная | B97: =B96 -> Рыба | C97: =C96 -> Соленое | D97: Соль пищевая | E97: =VLOOKUP(Рецепты[[#This Row],[Состав]],Ингредиенты[],2,0) -> Специи | F97: 0.13 | G97: =IF(Рецепты[[#This Row],[%]]*1000>0,Рецепты[[#This Row],[%]]*1000,"") -> 130 | H97: =IFERROR(VLOOKUP(Рецепты[[#This Row],[Состав]],Ингредиенты!A:I,3,0)*Рецепты[[#This Row],[г]],"") -> 5.005 | I97: =СводРецепт!$A$1 -> 1000 | J97: =Рецепты[[#This Row],[%]]*Рецепты[[#This Row],[Масса]] -> 130 | K97: =Рецепты[[#This Row],[Вес ингр-тов]]*VLOOKUP(Рецепты[[#This Row],[Состав]],Ингредиенты[],3,FALSE) -> 5.005 | L97: =IF(VLOOKUP(Рецепты[[#This Row],[Состав]],Ингредиенты[],4,0)="Основа",VLOOKUP(Рецепты[[#This Row],[Способ]],Способ[],2,0),0%) -> 0 | M97: =VLOOKUP(Рецепты[[#This Row],[Способ]],Способ[],3,0) -> 0.5 | N97: =Рецепты[[#This Row],[р]]*100%/(100%-Рецепты[[#This Row],[Потери, %]])+Рецепты[[#This Row],[Маржа]]*(Рецепты[[#This Row],[р]]*100%)/(100%-Рецепты[[#This Row],[Потери, %]]) -> 7.5075 | O97: =Рецепты[[#This Row],[Цена за 1 кг]]-(Рецепты[[#This Row],[р]]*100%/(100%-Рецепты[[#This Row],[Потери, %]])) -> 2.5025 | P97: https://www.youtube.com/watch?v=Ci5-qEbJGXQ | Q97: D:\Video\Колбаса_рецепты\Сельдь пряного посола. Рецептура для рассола. Отделение филе от костей.mp6 | R97: =VLOOKUP(Рецепты[[#This Row],[Состав]],Ингредиенты[],9,0) -> Да
A98: Сельдь пряная | B98: =B97 -> Рыба | C98: =C97 -> Соленое | D98: Лавровый лист | E98: =VLOOKUP(Рецепты[[#This Row],[Состав]],Ингредиенты[],2,0) -> Специи | F98: 0.0002 | G98: =IF(Рецепты[[#This Row],[%]]*1000>0,Рецепты[[#This Row],[%]]*1000,"") -> 0.2 | H98: =IFERROR(VLOOKUP(Рецепты[[#This Row],[Состав]],Ингредиенты!A:I,3,0)*Рецепты[[#This Row],[г]],"") -> 0.936 | I98: =СводРецепт!$A$1 -> 1000 | J98: =Рецепты[[#This Row],[%]]*Рецепты[[#This Row],[Масса]] -> 0.2 | K98: =Рецепты[[#This Row],[Вес ингр-тов]]*VLOOKUP(Рецепты[[#This Row],[Состав]],Ингредиенты[],3,FALSE) -> 0.936 | L98: =IF(VLOOKUP(Рецепты[[#This Row],[Состав]],Ингредиенты[],4,0)="Основа",VLOOKUP(Рецепты[[#This Row],[Способ]],Способ[],2,0),0%) -> 0 | M98: =VLOOKUP(Рецепты[[#This Row],[Способ]],Способ[],3,0) -> 0.5 | N98: =Рецепты[[#This Row],[р]]*100%/(100%-Рецепты[[#This Row],[Потери, %]])+Рецепты[[#This Row],[Маржа]]*(Рецепты[[#This Row],[р]]*100%)/(100%-Рецепты[[#This Row],[Потери, %]]) -> 1.404 | O98: =Рецепты[[#This Row],[Цена за 1 кг]]-(Рецепты[[#This Row],[р]]*100%/(100%-Рецепты[[#This Row],[Потери, %]])) -> 0.468 | P98: https://www.youtube.com/watch?v=Ci5-qEbJGXQ | Q98: D:\Video\Колбаса_рецепты\Сельдь пряного посола. Рецептура для рассола. Отделение филе от костей.mp7 | R98: =VLOOKUP(Рецепты[[#This Row],[Состав]],Ингредиенты[],9,0) -> Да
A99: Сельдь пряная | B99: =B98 -> Рыба | C99: =C98 -> Соленое | D99: Мускатный орех | E99: =VLOOKUP(Рецепты[[#This Row],[Состав]],Ингредиенты[],2,0) -> Специи | F99: 0.0003 | G99: =IF(Рецепты[[#This Row],[%]]*1000>0,Рецепты[[#This Row],[%]]*1000,"") -> 0.3 | H99: =IFERROR(VLOOKUP(Рецепты[[#This Row],[Состав]],Ингредиенты!A:I,3,0)*Рецепты[[#This Row],[г]],"") -> 0.62318182 | I99: =СводРецепт!$A$1 -> 1000 | J99: =Рецепты[[#This Row],[%]]*Рецепты[[#This Row],[Масса]] -> 0.3 | K99: =Рецепты[[#This Row],[Вес ингр-тов]]*VLOOKUP(Рецепты[[#This Row],[Состав]],Ингредиенты[],3,FALSE) -> 0.62318182 | L99: =IF(VLOOKUP(Рецепты[[#This Row],[Состав]],Ингредиенты[],4,0)="Основа",VLOOKUP(Рецепты[[#This Row],[Способ]],Способ[],2,0),0%) -> 0 | M99: =VLOOKUP(Рецепты[[#This Row],[Способ]],Способ[],3,0) -> 0.5 | N99: =Рецепты[[#This Row],[р]]*100%/(100%-Рецепты[[#This Row],[Потери, %]])+Рецепты[[#This Row],[Маржа]]*(Рецепты[[#This Row],[р]]*100%)/(100%-Рецепты[[#This Row],[Потери, %]]) -> 0.93477273 | O99: =Рецепты[[#This Row],[Цена за 1 кг]]-(Рецепты[[#This Row],[р]]*100%/(100%-Рецепты[[#This Row],[Потери, %]])) -> 0.31159091 | P99: https://www.youtube.com/watch?v=Ci5-qEbJGXQ | Q99: D:\Video\Колбаса_рецепты\Сельдь пряного посола. Рецептура для рассола. Отделение филе от костей.mp8 | R99: =VLOOKUP(Рецепты[[#This Row],[Состав]],Ингредиенты[],9,0) -> Да
A100: Сельдь пряная | B100: =B99 -> Рыба | C100: =C99 -> Соленое | D100: Перец черный горошек | E100: =VLOOKUP(Рецепты[[#This Row],[Состав]],Ингредиенты[],2,0) -> Специи | F100: 0.0009 | G100: =IF(Рецепты[[#This Row],[%]]*1000>0,Рецепты[[#This Row],[%]]*1000,"") -> 0.9 | H100: =IFERROR(VLOOKUP(Рецепты[[#This Row],[Состав]],Ингредиенты!A:I,3,0)*Рецепты[[#This Row],[г]],"") -> 1.026 | I100: =СводРецепт!$A$1 -> 1000 | J100: =Рецепты[[#This Row],[%]]*Рецепты[[#This Row],[Масса]] -> 0.9 | K100: =Рецепты[[#This Row],[Вес ингр-тов]]*VLOOKUP(Рецепты[[#This Row],[Состав]],Ингредиенты[],3,FALSE) -> 1.026 | L100: =IF(VLOOKUP(Рецепты[[#This Row],[Состав]],Ингредиенты[],4,0)="Основа",VLOOKUP(Рецепты[[#This Row],[Способ]],Способ[],2,0),0%) -> 0 | M100: =VLOOKUP(Рецепты[[#This Row],[Способ]],Способ[],3,0) -> 0.5 | N100: =Рецепты[[#This Row],[р]]*100%/(100%-Рецепты[[#This Row],[Потери, %]])+Рецепты[[#This Row],[Маржа]]*(Рецепты[[#This Row],[р]]*100%)/(100%-Рецепты[[#This Row],[Потери, %]]) -> 1.539 | O100: =Рецепты[[#This Row],[Цена за 1 кг]]-(Рецепты[[#This Row],[р]]*100%/(100%-Рецепты[[#This Row],[Потери, %]])) -> 0.513 | P100: https://www.youtube.com/watch?v=Ci5-qEbJGXQ | Q100: D:\Video\Колбаса_рецепты\Сельдь пряного посола. Рецептура для рассола. Отделение филе от костей.mp9 | R100: =VLOOKUP(Рецепты[[#This Row],[Состав]],Ингредиенты[],9,0) -> Да
A101: Сельдь пряная | B101: =B100 -> Рыба | C101: =C100 -> Соленое | D101: Сахар | E101: =VLOOKUP(Рецепты[[#This Row],[Состав]],Ингредиенты[],2,0) -> Специи | F101: 0.0286 | G101: =IF(Рецепты[[#This Row],[%]]*1000>0,Рецепты[[#This Row],[%]]*1000,"") -> 28.6 | H101: =IFERROR(VLOOKUP(Рецепты[[#This Row],[Состав]],Ингредиенты!A:I,3,0)*Рецепты[[#This Row],[г]],"") -> 2.3132353 | I101: =СводРецепт!$A$1 -> 1000 | J101: =Рецепты[[#This Row],[%]]*Рецепты[[#This Row],[Масса]] -> 28.6 | K101: =Рецепты[[#This Row],[Вес ингр-тов]]*VLOOKUP(Рецепты[[#This Row],[Состав]],Ингредиенты[],3,FALSE) -> 2.3132353 | L101: =IF(VLOOKUP(Рецепты[[#This Row],[Состав]],Ингредиенты[],4,0)="Основа",VLOOKUP(Рецепты[[#This Row],[Способ]],Способ[],2,0),0%) -> 0 | M101: =VLOOKUP(Рецепты[[#This Row],[Способ]],Способ[],3,0) -> 0.5 | N101: =Рецепты[[#This Row],[р]]*100%/(100%-Рецепты[[#This Row],[Потери, %]])+Рецепты[[#This Row],[Маржа]]*(Рецепты[[#This Row],[р]]*100%)/(100%-Рецепты[[#This Row],[Потери, %]]) -> 3.4698529 | O101: =Рецепты[[#This Row],[Цена за 1 кг]]-(Рецепты[[#This Row],[р]]*100%/(100%-Рецепты[[#This Row],[Потери, %]])) -> 1.1566176 | P101: https://www.youtube.com/watch?v=Ci5-qEbJGXQ | Q101: D:\Video\Колбаса_рецепты\Сельдь пряного посола. Рецептура для рассола. Отделение филе от костей.mp10 | R101: =VLOOKUP(Рецепты[[#This Row],[Состав]],Ингредиенты[],9,0) -> Да
A102: Сельдь пряная | B102: =B101 -> Рыба | C102: =C101 -> Соленое | D102: Гвоздика | E102: =VLOOKUP(Рецепты[[#This Row],[Состав]],Ингредиенты[],2,0) -> Специи | F102: 0.0011 | G102: =IF(Рецепты[[#This Row],[%]]*1000>0,Рецепты[[#This Row],[%]]*1000,"") -> 1.1 | H102: =IFERROR(VLOOKUP(Рецепты[[#This Row],[Состав]],Ингредиенты!A:I,3,0)*Рецепты[[#This Row],[г]],"") -> 3.0726667 | I102: =СводРецепт!$A$1 -> 1000 | J102: =Рецепты[[#This Row],[%]]*Рецепты[[#This Row],[Масса]] -> 1.1 | K102: =Рецепты[[#This Row],[Вес ингр-тов]]*VLOOKUP(Рецепты[[#This Row],[Состав]],Ингредиенты[],3,FALSE) -> 3.0726667 | L102: =IF(VLOOKUP(Рецепты[[#This Row],[Состав]],Ингредиенты[],4,0)="Основа",VLOOKUP(Рецепты[[#This Row],[Способ]],Способ[],2,0),0%) -> 0 | M102: =VLOOKUP(Рецепты[[#This Row],[Способ]],Способ[],3,0) -> 0.5 | N102: =Рецепты[[#This Row],[р]]*100%/(100%-Рецепты[[#This Row],[Потери, %]])+Рецепты[[#This Row],[Маржа]]*(Рецепты[[#This Row],[р]]*100%)/(100%-Рецепты[[#This Row],[Потери, %]]) -> 4.609 | O102: =Рецепты[[#This Row],[Цена за 1 кг]]-(Рецепты[[#This Row],[р]]*100%/(100%-Рецепты[[#This Row],[Потери, %]])) -> 1.5363333 | P102: https://www.youtube.com/watch?v=Ci5-qEbJGXQ | Q102: D:\Video\Колбаса_рецепты\Сельдь пряного посола. Рецептура для рассола. Отделение филе от костей.mp11 | R102: =VLOOKUP(Рецепты[[#This Row],[Состав]],Ингредиенты[],9,0) -> Да
A103: Сельдь пряная | B103: =B102 -> Рыба | C103: =C102 -> Соленое | D103: Корица молотая | E103: =VLOOKUP(Рецепты[[#This Row],[Состав]],Ингредиенты[],2,0) -> Специи | F103: 0.0009 | G103: =IF(Рецепты[[#This Row],[%]]*1000>0,Рецепты[[#This Row],[%]]*1000,"") -> 0.9 | H103: =IFERROR(VLOOKUP(Рецепты[[#This Row],[Состав]],Ингредиенты!A:I,3,0)*Рецепты[[#This Row],[г]],"") -> 0.708 | I103: =СводРецепт!$A$1 -> 1000 | J103: =Рецепты[[#This Row],[%]]*Рецепты[[#This Row],[Масса]] -> 0.9 | K103: =Рецепты[[#This Row],[Вес ингр-тов]]*VLOOKUP(Рецепты[[#This Row],[Состав]],Ингредиенты[],3,FALSE) -> 0.708 | L103: =IF(VLOOKUP(Рецепты[[#This Row],[Состав]],Ингредиенты[],4,0)="Основа",VLOOKUP(Рецепты[[#This Row],[Способ]],Способ[],2,0),0%) -> 0 | M103: =VLOOKUP(Рецепты[[#This Row],[Способ]],Способ[],3,0) -> 0.5 | N103: =Рецепты[[#This Row],[р]]*100%/(100%-Рецепты[[#This Row],[Потери, %]])+Рецепты[[#This Row],[Маржа]]*(Рецепты[[#This Row],[р]]*100%)/(100%-Рецепты[[#This Row],[Потери, %]]) -> 1.062 | O103: =Рецепты[[#This Row],[Цена за 1 кг]]-(Рецепты[[#This Row],[р]]*100%/(100%-Рецепты[[#This Row],[Потери, %]])) -> 0.354 | P103: https://www.youtube.com/watch?v=Ci5-qEbJGXQ | Q103: D:\Video\Колбаса_рецепты\Сельдь пряного посола. Рецептура для рассола. Отделение филе от костей.mp12 | R103: =VLOOKUP(Рецепты[[#This Row],[Состав]],Ингредиенты[],9,0) -> Да
A104: Сельдь пряная | B104: =B103 -> Рыба | C104: =C103 -> Соленое | D104: Мята сухая | E104: =VLOOKUP(Рецепты[[#This Row],[Состав]],Ингредиенты[],2,0) -> Специи | F104: 0.0002 | G104: =IF(Рецепты[[#This Row],[%]]*1000>0,Рецепты[[#This Row],[%]]*1000,"") -> 0.2 | H104: =IFERROR(VLOOKUP(Рецепты[[#This Row],[Состав]],Ингредиенты!A:I,3,0)*Рецепты[[#This Row],[г]],"") -> 0.1386 | I104: =СводРецепт!$A$1 -> 1000 | J104: =Рецепты[[#This Row],[%]]*Рецепты[[#This Row],[Масса]] -> 0.2 | K104: =Рецепты[[#This Row],[Вес ингр-тов]]*VLOOKUP(Рецепты[[#This Row],[Состав]],Ингредиенты[],3,FALSE) -> 0.1386 | L104: =IF(VLOOKUP(Рецепты[[#This Row],[Состав]],Ингредиенты[],4,0)="Основа",VLOOKUP(Рецепты[[#This Row],[Способ]],Способ[],2,0),0%) -> 0 | M104: =VLOOKUP(Рецепты[[#This Row],[Способ]],Способ[],3,0) -> 0.5 | N104: =Рецепты[[#This Row],[р]]*100%/(100%-Рецепты[[#This Row],[Потери, %]])+Рецепты[[#This Row],[Маржа]]*(Рецепты[[#This Row],[р]]*100%)/(100%-Рецепты[[#This Row],[Потери, %]]) -> 0.2079 | O104: =Рецепты[[#This Row],[Цена за 1 кг]]-(Рецепты[[#This Row],[р]]*100%/(100%-Рецепты[[#This Row],[Потери, %]])) -> 0.0693 | P104: https://www.youtube.com/watch?v=Ci5-qEbJGXQ | Q104: D:\Video\Колбаса_рецепты\Сельдь пряного посола. Рецептура для рассола. Отделение филе от костей.mp13 | R104: =VLOOKUP(Рецепты[[#This Row],[Состав]],Ингредиенты[],9,0) -> Да
A105: Сельдь пряная | B105: =B104 -> Рыба | C105: =C104 -> Соленое | D105: Перец душистый горошек | E105: =VLOOKUP(Рецепты[[#This Row],[Состав]],Ингредиенты[],2,0) -> Специи | F105: 0.0027 | G105: =IF(Рецепты[[#This Row],[%]]*1000>0,Рецепты[[#This Row],[%]]*1000,"") -> 2.7 | H105: =IFERROR(VLOOKUP(Рецепты[[#This Row],[Состав]],Ингредиенты!A:I,3,0)*Рецепты[[#This Row],[г]],"") -> 5.3892 | I105: =СводРецепт!$A$1 -> 1000 | J105: =Рецепты[[#This Row],[%]]*Рецепты[[#This Row],[Масса]] -> 2.7 | K105: =Рецепты[[#This Row],[Вес ингр-тов]]*VLOOKUP(Рецепты[[#This Row],[Состав]],Ингредиенты[],3,FALSE) -> 5.3892 | L105: =IF(VLOOKUP(Рецепты[[#This Row],[Состав]],Ингредиенты[],4,0)="Основа",VLOOKUP(Рецепты[[#This Row],[Способ]],Способ[],2,0),0%) -> 0 | M105: =VLOOKUP(Рецепты[[#This Row],[Способ]],Способ[],3,0) -> 0.5 | N105: =Рецепты[[#This Row],[р]]*100%/(100%-Рецепты[[#This Row],[Потери, %]])+Рецепты[[#This Row],[Маржа]]*(Рецепты[[#This Row],[р]]*100%)/(100%-Рецепты[[#This Row],[Потери, %]]) -> 8.0838 | O105: =Рецепты[[#This Row],[Цена за 1 кг]]-(Рецепты[[#This Row],[р]]*100%/(100%-Рецепты[[#This Row],[Потери, %]])) -> 2.6946 | P105: https://www.youtube.com/watch?v=Ci5-qEbJGXQ | Q105: D:\Video\Колбаса_рецепты\Сельдь пряного посола. Рецептура для рассола. Отделение филе от костей.mp14 | R105: =VLOOKUP(Рецепты[[#This Row],[Состав]],Ингредиенты[],9,0) -> Да
A106: Сельдь пряная | B106: =B105 -> Рыба | C106: =C105 -> Соленое | D106: Перец чили молотый | E106: =VLOOKUP(Рецепты[[#This Row],[Состав]],Ингредиенты[],2,0) -> Специи | F106: 0.0004 | G106: =IF(Рецепты[[#This Row],[%]]*1000>0,Рецепты[[#This Row],[%]]*1000,"") -> 0.4 | H106: =IFERROR(VLOOKUP(Рецепты[[#This Row],[Состав]],Ингредиенты!A:I,3,0)*Рецепты[[#This Row],[г]],"") -> 0.31054545 | I106: =СводРецепт!$A$1 -> 1000 | J106: =Рецепты[[#This Row],[%]]*Рецепты[[#This Row],[Масса]] -> 0.4 | K106: =Рецепты[[#This Row],[Вес ингр-тов]]*VLOOKUP(Рецепты[[#This Row],[Состав]],Ингредиенты[],3,FALSE) -> 0.31054545 | L106: =IF(VLOOKUP(Рецепты[[#This Row],[Состав]],Ингредиенты[],4,0)="Основа",VLOOKUP(Рецепты[[#This Row],[Способ]],Способ[],2,0),0%) -> 0 | M106: =VLOOKUP(Рецепты[[#This Row],[Способ]],Способ[],3,0) -> 0.5 | N106: =Рецепты[[#This Row],[р]]*100%/(100%-Рецепты[[#This Row],[Потери, %]])+Рецепты[[#This Row],[Маржа]]*(Рецепты[[#This Row],[р]]*100%)/(100%-Рецепты[[#This Row],[Потери, %]]) -> 0.46581818 | O106: =Рецепты[[#This Row],[Цена за 1 кг]]-(Рецепты[[#This Row],[р]]*100%/(100%-Рецепты[[#This Row],[Потери, %]])) -> 0.15527273 | P106: https://www.youtube.com/watch?v=Ci5-qEbJGXQ | Q106: D:\Video\Колбаса_рецепты\Сельдь пряного посола. Рецептура для рассола. Отделение филе от костей.mp15 | R106: =VLOOKUP(Рецепты[[#This Row],[Состав]],Ингредиенты[],9,0) -> Нет
A107: Сельдь пряная | B107: =B106 -> Рыба | C107: =C106 -> Соленое | D107: Кориандр | E107: =VLOOKUP(Рецепты[[#This Row],[Состав]],Ингредиенты[],2,0) -> Специи | F107: 0.0015 | G107: =IF(Рецепты[[#This Row],[%]]*1000>0,Рецепты[[#This Row],[%]]*1000,"") -> 1.5 | H107: =IFERROR(VLOOKUP(Рецепты[[#This Row],[Состав]],Ингредиенты!A:I,3,0)*Рецепты[[#This Row],[г]],"") -> 0.75333333 | I107: =СводРецепт!$A$1 -> 1000 | J107: =Рецепты[[#This Row],[%]]*Рецепты[[#This Row],[Масса]] -> 1.5 | K107: =Рецепты[[#This Row],[Вес ингр-тов]]*VLOOKUP(Рецепты[[#This Row],[Состав]],Ингредиенты[],3,FALSE) -> 0.75333333 | L107: =IF(VLOOKUP(Рецепты[[#This Row],[Состав]],Ингредиенты[],4,0)="Основа",VLOOKUP(Рецепты[[#This Row],[Способ]],Способ[],2,0),0%) -> 0 | M107: =VLOOKUP(Рецепты[[#This Row],[Способ]],Способ[],3,0) -> 0.5 | N107: =Рецепты[[#This Row],[р]]*100%/(100%-Рецепты[[#This Row],[Потери, %]])+Рецепты[[#This Row],[Маржа]]*(Рецепты[[#This Row],[р]]*100%)/(100%-Рецепты[[#This Row],[Потери, %]]) -> 1.13 | O107: =Рецепты[[#This Row],[Цена за 1 кг]]-(Рецепты[[#This Row],[р]]*100%/(100%-Рецепты[[#This Row],[Потери, %]])) -> 0.37666667 | P107: https://www.youtube.com/watch?v=Ci5-qEbJGXQ | Q107: D:\Video\Колбаса_рецепты\Сельдь пряного посола. Рецептура для рассола. Отделение филе от костей.mp16 | R107: =VLOOKUP(Рецепты[[#This Row],[Состав]],Ингредиенты[],9,0) -> Да
A108: Языковая кровяная | B108: Колбаса | C108: Вареное | D108: Язык говяжий | E108: =VLOOKUP(Рецепты[[#This Row],[Состав]],Ингредиенты[],2,0) -> Говядина | F108: 0.25 | G108: =IF(Рецепты[[#This Row],[%]]*1000>0,Рецепты[[#This Row],[%]]*1000,"") -> 250 | H108: =IFERROR(VLOOKUP(Рецепты[[#This Row],[Состав]],Ингредиенты!A:I,3,0)*Рецепты[[#This Row],[г]],"") -> 274.9975 | I108: =СводРецепт!$A$1 -> 1000 | J108: =Рецепты[[#This Row],[%]]*Рецепты[[#This Row],[Масса]] -> 250 | K108: =Рецепты[[#This Row],[Вес ингр-тов]]*VLOOKUP(Рецепты[[#This Row],[Состав]],Ингредиенты[],3,FALSE) -> 274.9975 | L108: =IF(VLOOKUP(Рецепты[[#This Row],[Состав]],Ингредиенты[],4,0)="Основа",VLOOKUP(Рецепты[[#This Row],[Способ]],Способ[],2,0),0%) -> 0.15 | M108: =VLOOKUP(Рецепты[[#This Row],[Способ]],Способ[],3,0) -> 0.7 | N108: =Рецепты[[#This Row],[р]]*100%/(100%-Рецепты[[#This Row],[Потери, %]])+Рецепты[[#This Row],[Маржа]]*(Рецепты[[#This Row],[р]]*100%)/(100%-Рецепты[[#This Row],[Потери, %]]) -> 549.995 | O108: =Рецепты[[#This Row],[Цена за 1 кг]]-(Рецепты[[#This Row],[р]]*100%/(100%-Рецепты[[#This Row],[Потери, %]])) -> 226.46853 | P108: САМАЯ ВКУСНАЯ КРОВЯНКА - Языковая кровяная колбаса! РОЗЫГРЫШ ПРИЗОВ. - YouTube | Q108: D:\Video\Колбаса_рецепты\САМАЯ ВКУСНАЯ КРОВЯНКА - Языковая кровяная колбаса! РОЗЫГРЫШ ПРИЗОВ.mp4 | R108: =VLOOKUP(Рецепты[[#This Row],[Состав]],Ингредиенты[],9,0) -> Нет
A109: Языковая кровяная | B109: =B108 -> Колбаса | C109: =C108 -> Вареное | D109: Грудинка свиная | E109: =VLOOKUP(Рецепты[[#This Row],[Состав]],Ингредиенты[],2,0) -> Свинина | F109: 0.25 | G109: =IF(Рецепты[[#This Row],[%]]*1000>0,Рецепты[[#This Row],[%]]*1000,"") -> 250 | H109: =IFERROR(VLOOKUP(Рецепты[[#This Row],[Состав]],Ингредиенты!A:I,3,0)*Рецепты[[#This Row],[г]],"") -> 107.4975 | I109: =СводРецепт!$A$1 -> 1000 | J109: =Рецепты[[#This Row],[%]]*Рецепты[[#This Row],[Масса]] -> 250 | K109: =Рецепты[[#This Row],[Вес ингр-тов]]*VLOOKUP(Рецепты[[#This Row],[Состав]],Ингредиенты[],3,FALSE) -> 107.4975 | L109: =IF(VLOOKUP(Рецепты[[#This Row],[Состав]],Ингредиенты[],4,0)="Основа",VLOOKUP(Рецепты[[#This Row],[Способ]],Способ[],2,0),0%) -> 0.15 | M109: =VLOOKUP(Рецепты[[#This Row],[Способ]],Способ[],3,0) -> 0.7 | N109: =Рецепты[[#This Row],[р]]*100%/(100%-Рецепты[[#This Row],[Потери, %]])+Рецепты[[#This Row],[Маржа]]*(Рецепты[[#This Row],[р]]*100%)/(100%-Рецепты[[#This Row],[Потери, %]]) -> 214.995 | O109: =Рецепты[[#This Row],[Цена за 1 кг]]-(Рецепты[[#This Row],[р]]*100%/(100%-Рецепты[[#This Row],[Потери, %]])) -> 88.527353 | P109: САМАЯ ВКУСНАЯ КРОВЯНКА - Языковая кровяная колбаса! РОЗЫГРЫШ ПРИЗОВ. - YouTube | Q109: D:\Video\Колбаса_рецепты\САМАЯ ВКУСНАЯ КРОВЯНКА - Языковая кровяная колбаса! РОЗЫГРЫШ ПРИЗОВ.mp5 | R109: =VLOOKUP(Рецепты[[#This Row],[Состав]],Ингредиенты[],9,0) -> Нет
A110: Языковая кровяная | B110: =B109 -> Колбаса | C110: =C109 -> Вареное | D110: Окорок свиной | E110: =VLOOKUP(Рецепты[[#This Row],[Состав]],Ингредиенты[],2,0) -> Свинина | F110: 0.25 | G110: =IF(Рецепты[[#This Row],[%]]*1000>0,Рецепты[[#This Row],[%]]*1000,"") -> 250 | H110: =IFERROR(VLOOKUP(Рецепты[[#This Row],[Состав]],Ингредиенты!A:I,3,0)*Рецепты[[#This Row],[г]],"") -> 92.25 | I110: =СводРецепт!$A$1 -> 1000 | J110: =Рецепты[[#This Row],[%]]*Рецепты[[#This Row],[Масса]] -> 250 | K110: =Рецепты[[#This Row],[Вес ингр-тов]]*VLOOKUP(Рецепты[[#This Row],[Состав]],Ингредиенты[],3,FALSE) -> 92.25 | L110: =IF(VLOOKUP(Рецепты[[#This Row],[Состав]],Ингредиенты[],4,0)="Основа",VLOOKUP(Рецепты[[#This Row],[Способ]],Способ[],2,0),0%) -> 0.15 | M110: =VLOOKUP(Рецепты[[#This Row],[Способ]],Способ[],3,0) -> 0.7 | N110: =Рецепты[[#This Row],[р]]*100%/(100%-Рецепты[[#This Row],[Потери, %]])+Рецепты[[#This Row],[Маржа]]*(Рецепты[[#This Row],[р]]*100%)/(100%-Рецепты[[#This Row],[Потери, %]]) -> 184.5 | O110: =Рецепты[[#This Row],[Цена за 1 кг]]-(Рецепты[[#This Row],[р]]*100%/(100%-Рецепты[[#This Row],[Потери, %]])) -> 75.970588 | P110: САМАЯ ВКУСНАЯ КРОВЯНКА - Языковая кровяная колбаса! РОЗЫГРЫШ ПРИЗОВ. - YouTube | Q110: D:\Video\Колбаса_рецепты\САМАЯ ВКУСНАЯ КРОВЯНКА - Языковая кровяная колбаса! РОЗЫГРЫШ ПРИЗОВ.mp6 | R110: =VLOOKUP(Рецепты[[#This Row],[Состав]],Ингредиенты[],9,0) -> Да
...

Sheet СводРецепт
A1: 1000 | B1: =VLOOKUP($A$4,Рецепты[],16,0) -> ВЕТЧИНА МРАМОРНАЯ НАСТОЯЩАЯ в домашних условиях (youtube.com) | C1: =VLOOKUP($A$4,Рецепты[],17,0) -> D:\Video\Колбаса_рецепты\ВЕТЧИНА МРАМОРНАЯ НАСТОЯЩАЯ в домашних условиях.mp4 | D1: =VLOOKUP($A$4,Рецепты[],19,0) -> 0
A3: Названия строк | B3: Вес
A4: Ветчина Мраморная
A5: Окорок свиной | B5: 860
A6: Вода | B6: 150
A7: Грудинка свиная | B7: 140
A8: Соль нитритная | B8: 10
A9: Соль пищевая | B9: 10
A10: Чеснок сушеный | B10: 5
A11: Фосфат | B11: 3
A12: Перец черный молотый | B12: 1.5
A13: Сахар | B13: 1.5
A14: Полиамидная 80 | B14: 1
A15: Мускатный орех | B15: 0.5
A16: Ветчина Семейная
A17: Грудка куриная | B17: 500
A18: Бедра куриные | B18: 500
A19: Вода | B19: 130
A20: Соль пищевая | B20: 9
A21: Соль нитритная | B21: 9
A22: Фосфат | B22: 3
A23: Сахар | B23: 2
A24: Чеснок сушеный | B24: 1.5
A25: Перец черный молотый | B25: 1
A26: Полиамидная 80 | B26: 1
A27: Мускатный орех | B27: 0.7
A28: Ветчинно-рубленная
A29: Окорок свиной | B29: 600
A30: Говядина | B30: 400
A31: Вода | B31: 130
A32: Соль пищевая | B32: 10
A33: Соль нитритная | B33: 10
A34: Фосфат | B34: 3
A35: Сахар | B35: 2
A36: Перец черный молотый | B36: 2
A37: Кориандр | B37: 1
A38: Чеснок сушеный | B38: 1
A39: Полиамидная 80 | B39: 1
A40: Докторская
A41: Лопатка свиная | B41: 700
A42: Говядина | B42: 250
A43: Вода | B43: 100
A44: Яйцо | B44: 30
A45: Сухое молоко | B45: 20
A46: Соль нитритная | B46: 20
A47: Фосфат | B47: 2
A48: Полиамидная 80 | B48: 1
A49: Кардамон | B49: 0.5
A50: Дрогобычская
A51: Окорок свиной | B51: 1000
A52: Вода | B52: 130
A53: Соль нитритная | B53: 20
A54: Чеснок сушеный | B54: 3
A55: Тмин | B55: 2
A56: Фосфат | B56: 2
A57: Сахар | B57: 2
A58: Перец черный молотый | B58: 2
A59: Перец душистый горошек | B59: 1
A60: Коллагеновая 45/50 | B60: 1
A61: Зельц
A62: Шкуры, голова, обрезь | B62: 1000
A63: Вода | B63: 800
A64: Чеснок сушеный | B64: 10
A65: Соль нитритная | B65: 10
A66: Соль пищевая | B66: 5
A67: Перец черный молотый | B67: 4
A68: Кориандр | B68: 3
A69: Полиамидная 80 | B69: 1
A70: Кабаносси
A71: Грудинка свиная | B71: 500
A72: Окорок свиной | B72: 500
A73: Вода | B73: 175
A74: Соль пищевая | B74: 10
A75: Соль нитритная | B75: 10
A76: Чеснок сушеный | B76: 2
A77: Горчица семена | B77: 2
A78: Перец черный молотый | B78: 2
A79: Фосфат | B79: 1.5
A80: Перец белый молотый | B80: 1
A81: Свиная черева 32/34 | B81: 1
A82: Тмин | B82: 1
A83: Краковская
A84: Окорок свиной | B84: 400
A85: Грудинка свиная | B85: 300
A86: Говядина | B86: 300
A87: Соль пищевая | B87: 10
A88: Соль нитритная | B88: 10
A89: Свиная черева 38/40 | B89: 1
A90: Сахар | B90: 1
A91: Чеснок сушеный | B91: 0.5
A92: Перец душистый горошек | B92: 0.5
A93: Перец черный молотый | B93: 0.5
A94: Любительская
A95: Окорок свиной | B95: 400
A96: Говядина | B96: 350
A97: Шпик | B97: 250
A98: Вода | B98: 120
A99: Сухое молоко | B99: 20
A100: Соль пищевая | B100: 10
A101: Соль нитритная | B101: 10
...

Sheet СводЦена
A1: Названия строк | B1: Затраты | C1: Наценка | D1: Потери | E1: Прибыль | F1: Цена/кг
A2: Еда
A3: Пельмени свин/гов | B3: 607.22303 | C3: 0.5 | D3: 0.05 | E3: 317.80875 | F3: 960
A4: Плов казан | B4: 472.59006 | C4: 0.7 | D4: 0.15 | E4: 377.9074 | F4: 920
A5: Холодец | B5: 297.14525 | C5: 0.5 | D5: 0.05 | E5: 155.51978 | F5: 470
A6: Суп Э Джо | B6: 213.59862 | C6: 0.5 | D6: 0.05 | E6: 110.73889 | F6: 340
A7: Бешамель | B7: 139.77538 | C7: 0.5 | D7: 0.05 | E7: 71.343684 | F7: 220
A8: Морковь по-корейски | B8: 93.047807 | C8: 0.5 | D8: 0 | E8: 46.523904 | F8: 140
A9: Блины на молоке | B9: 79.916657 | C9: 0.5 | D9: 0.05 | E9: 41.186276 | F9: 130
A10: Пирожки тесто | B10: 56.810716 | C10: 0.5 | D10: 0.05 | E10: 28.931621 | F10: 90
A11: Пицца тесто | B11: 51.103758 | C11: 0.5 | D11: 0 | E11: 25.551879 | F11: 80
A12: Колбаса
A13: Московская | B13: 647.49018 | C13: 2 | D13: 0.35 | E13: 1949.203 | F13: 2930
A14: Еврейская | B14: 634.48484 | C14: 2 | D14: 0.35 | E14: 1909.7308 | F14: 2870
A15: Луканка | B15: 609.61337 | C15: 2 | D15: 0.35 | E15: 1816.6417 | F15: 2730
A16: Пеперони | B16: 594.24727 | C16: 2 | D16: 0.35 | E16: 1724.2584 | F16: 2590
A17: Брауншвейгская | B17: 557.06793 | C17: 2 | D17: 0.35 | E17: 1658.1926 | F17: 2490
A18: Чоризо | B18: 465.67431 | C18: 2 | D18: 0.35 | E18: 1341.8695 | F18: 2020
A19: Фуэт | B19: 473.84046 | C19: 2 | D19: 0.35 | E19: 1337.6348 | F19: 2010
A20: Финоккьона | B20: 433.31464 | C20: 2 | D20: 0.35 | E20: 1264.0139 | F20: 1900
A21: Салями Милано | B21: 427.18617 | C21: 2 | D21: 0.35 | E21: 1236.8954 | F21: 1860
A22: Языковая кровяная | B22: 602.71815 | C22: 0.7 | D22: 0.15 | E22: 480.54768 | F22: 1170
A23: Краковская | B23: 519.33865 | C23: 0.9 | D23: 0.15 | E23: 545.16383 | F23: 1160
A24: Полтавская | B24: 534.19347 | C24: 0.7 | D24: 0.15 | E24: 435.16809 | F24: 1060
... A36: Зельц | B36: 126.67814 | C36: 0.7 | D36: 0.15 | E36: 101.02764 | F36: 250
A37: Рыба
A38: Белый амур вяленый | B38: 675.98431 | C38: 2 | D38: 0.35 | E38: 2069.9173 | F38: 3110
A39: Форель слабосолёная | B39: 1378.7459 | C39: 0.5 | D39: 0.05 | E39: 725.52425 | F39: 2180
A40: Сельдь вяленая "Киперс" | B40: 373.3892 | C40: 2 | D40: 0.35 | E40: 1116.0092 | F40: 1680
A41: Скумбрия ХК | B41: 428.31 | C41: 1 | D41: 0.15 | E41: 503.31 | F41: 1010
A42: Скумбрия провесная | B42: 438.19765 | C42: 0.9 | D42: 0.1 | E42: 436.87788 | F42: 930
A43: Горбуша ХК | B43: 389.34391 | C43: 1 | D43: 0.15 | E43: 456.14811 | F43: 920
A44: Сельдь провесная | B44: 359.82981 | C44: 0.9 | D44: 0.1 | E44: 358.13254 | F44: 760
A45: Карась ХК | B45: 259.51298 | C45: 1 | D45: 0.15 | E45: 303.63062 | F45: 610
A46: Сельдь пряная | B46: 364.56291 | C46: 0.5 | D46: 0.05 | E46: 191.30401 | F46: 580
A47: Сосиски
A48: Крепыш | B48: 619.49018 | C48: 0.7 | D48: 0.15 | E48: 504.05366 | F48: 1230
A49: Детские Молочные | B49: 604.91359 | C49: 0.7 | D49: 0.15 | E49: 482.58436 | F49: 1180
A50: Венские | B50: 445.31876 | C50: 0.9 | D50: 0.15 | E50: 461.07566 | F50: 980
A51: Куриные Сырные | B51: 467.55513 | C51: 0.7 | D51: 0.15 | E51: 353.56377 | F51: 860
A52: Хотдожные к пиву | B52: 430.4453 | C52: 0.7 | D52: 0.15 | E52: 346.89406 | F52: 850
A53: Сардельки Свиные | B53: 415.32177 | C53: 0.7 | D53: 0.15 | E53: 336.30759 | F53: 820
A54: Куриные сливочные | B54: 384.17357 | C54: 0.7 | D54: 0.15 | E54: 301.18448 | F54: 740
A55: Сыр
A56: Чечил косичка | B56: 76.2 | C56: 3 | D56: 0.92 | E56: 2528.37 | F56: 3380
A57: Панир | B57: 67.015 | C57: 3 | D57: 0.92 | E57: 2500.815 | F57: 3340
A58: Цельное
A59: Бекон мокрый посол | B59: 470.91148 | C59: 2 | D59: 0.35 | E59: 1404.8891 | F59: 2110
A60: Бекон сухой посол | B60: 466.02 | C60: 2 | D60: 0.35 | E60: 1395.1062 | F60: 2100
A61: Панчетта Арротолатта | B61: 446.7206 | C61: 2 | D61: 0.35 | E61: 1356.5073 | F61: 2040
A62: Шашлык свиной | B62: 598.80281 | C62: 0.7 | D62: 0.15 | E62: 490.80902 | F62: 1200
A63: Грудинка свиная ГК | B63: 434.81876 | C63: 0.9 | D63: 0.15 | E63: 459.62942 | F63: 980
A64: Корейка ГК | B64: 402.32591 | C64: 0.9 | D64: 0.15 | E64: 425.62114 | F64: 900
A65: Свиные ребра ГК | B65: 305.23817 | C65: 0.9 | D65: 0.15 | E65: 320.77158 | F65: 680
A66: Рулька | B66: 282.41441 | C66: 0.9 | D66: 0.15 | E66: 298.64197 | F66: 640
A67: Сало ГОСТ | B67: 310.085 | C67: 0.5 | D67: 0.05 | E67: 162.93724 | F67: 490
A68: Курица ГК | B68: 201.84115 | C68: 0.9 | D68: 0.15 | E68: 213.42174 | F68: 460

Sheet Делаю
A1: Дата | B1: Вид | C1: Название | D1: Масса | E1: Масса готов | F1: Потери факт | G1: Потери прогноз | H1: Траты/кг | I1: Наценка | J1: Цена/кг | K1: ЧП | L1: Заработок | M1: Цена всего | N1: Прим | O1: Ссылка
A2: 45396 | B2: =VLOOKUP(Делаю[[#This Row],[Название]],Рецепты[],2,0) -> Колбаса | C2: Дрогобычская | D2: 6686 | E2: 6326 | F2: =IF(Делаю[[#This Row],[Масса готов]]>0,(Делаю[[#This Row],[Масса]]-Делаю[[#This Row],[Масса готов]])*100%/Делаю[[#This Row],[Масса]],"") -> 0.053843853 | G2: =VLOOKUP(Делаю[[#This Row],[Название]],СводЦена!A:F,4,0) -> 0.15 | H2: =VLOOKUP(Делаю[[#This Row],[Название]],СводЦена!A:F,2,0) -> 411.76519 | I2: =VLOOKUP(Делаю[[#This Row],[Название]],СводЦена!A:F,3,0) -> 0.7 | J2: =VLOOKUP(Делаю[[#This Row],[Название]],СводЦена!A:F,6,0) -> 820 | K2: =VLOOKUP(Делаю[[#This Row],[Название]],СводЦена!A:F,5,0) -> 333.81799 | L2: =Делаю[[#This Row],[ЧП]]*Делаю[[#This Row],[Масса готов]]/1000 -> 2111.7326 | M2: =Делаю[[#This Row],[Цена/кг]]*Делаю[[#This Row],[Масса готов]]/1000 -> 5187.32 | O2: =VLOOKUP(Делаю[[#This Row],[Название]],Рецепты[],16,0) -> Очень вкусная домашняя колбаса - Дрогобычская. Просто, дома, своими руками - YouTube
A3: 45396 | B3: =VLOOKUP(Делаю[[#This Row],[Название]],Рецепты[],2,0) -> Колбаса | C3: Краковская | D3: 3500 | E3: 3064 | F3: =IF(Делаю[[#This Row],[Масса готов]]>0,(Делаю[[#This Row],[Масса]]-Делаю[[#This Row],[Масса готов]])*100%/Делаю[[#This Row],[Масса]],"") -> 0.12457143 | G3: =VLOOKUP(Делаю[[#This Row],[Название]],СводЦена!A:F,4,0) -> 0.15 | H3: =VLOOKUP(Делаю[[#This Row],[Название]],СводЦена!A:F,2,0) -> 519.33865 | I3: =VLOOKUP(Делаю[[#This Row],[Название]],СводЦена!A:F,3,0) -> 0.9 | J3: =VLOOKUP(Делаю[[#This Row],[Название]],СводЦена!A:F,6,0) -> 1160 | K3: =VLOOKUP(Делаю[[#This Row],[Название]],СводЦена!A:F,5,0) -> 545.16383 | L3: =Делаю[[#This Row],[ЧП]]*Делаю[[#This Row],[Масса готов]]/1000 -> 1670.382 | M3: =Делаю[[#This Row],[Цена/кг]]*Делаю[[#This Row],[Масса готов]]/1000 -> 3554.24 | O3: =VLOOKUP(Делаю[[#This Row],[Название]],Рецепты[],16,0) -> Классическая Краковская колбаса полукопченая своими руками - YouTube
A4: 45409 | B4: =VLOOKUP(Делаю[[#This Row],[Название]],Рецепты[],2,0) -> Сосиски | C4: Сардельки Свиные | D4: 5000 | F4: =IF(Делаю[[#This Row],[Масса готов]]>0,(Делаю[[#This Row],[Масса]]-Делаю[[#This Row],[Масса готов]])*100%/Делаю[[#This Row],[Масса]],"") | G4: =VLOOKUP(Делаю[[#This Row],[Название]],СводЦена!A:F,4,0) -> 0.15 | H4: =VLOOKUP(Делаю[[#This Row],[Название]],СводЦена!A:F,2,0) -> 415.32177 | I4: =VLOOKUP(Делаю[[#This Row],[Название]],СводЦена!A:F,3,0) -> 0.7 | J4: =VLOOKUP(Делаю[[#This Row],[Название]],СводЦена!A:F,6,0) -> 820 | K4: =VLOOKUP(Делаю[[#This Row],[Название]],СводЦена!A:F,5,0) -> 336.30759 | L4: =Делаю[[#This Row],[ЧП]]*Делаю[[#This Row],[Масса готов]]/1000 -> 0 | M4: =Делаю[[#This Row],[Цена/кг]]*Делаю[[#This Row],[Масса готов]]/1000 -> 0 | O4: =VLOOKUP(Делаю[[#This Row],[Название]],Рецепты[],16,0) -> https://www.youtube.com/watch?v=Mu_glCpe-Y8
A5: 45409 | B5: =VLOOKUP(Делаю[[#This Row],[Название]],Рецепты[],2,0) -> Колбаса | C5: Дрогобычская | D5: 4769 | F5: =IF(Делаю[[#This Row],[Масса готов]]>0,(Делаю[[#This Row],[Масса]]-Делаю[[#This Row],[Масса готов]])*100%/Делаю[[#This Row],[Масса]],"") | G5: =VLOOKUP(Делаю[[#This Row],[Название]],СводЦена!A:F,4,0) -> 0.15 | H5: =VLOOKUP(Делаю[[#This Row],[Название]],СводЦена!A:F,2,0) -> 411.76519 | I5: =VLOOKUP(Делаю[[#This Row],[Название]],СводЦена!A:F,3,0) -> 0.7 | J5: =VLOOKUP(Делаю[[#This Row],[Название]],СводЦена!A:F,6,0) -> 820 | K5: =VLOOKUP(Делаю[[#This Row],[Название]],СводЦена!A:F,5,0) -> 333.81799 | L5: =Делаю[[#This Row],[ЧП]]*Делаю[[#This Row],[Масса готов]]/1000 -> 0 | M5: =Делаю[[#This Row],[Цена/кг]]*Делаю[[#This Row],[Масса готов]]/1000 -> 0 | O5: =VLOOKUP(Делаю[[#This Row],[Название]],Рецепты[],16,0) -> Очень вкусная домашняя колбаса - Дрогобычская. Просто, дома, своими руками - YouTube
A6: 45409 | B6: =VLOOKUP(Делаю[[#This Row],[Название]],Рецепты[],2,0) -> Колбаса | C6: Краковская | D6: 1500 | F6: =IF(Делаю[[#This Row],[Масса готов]]>0,(Делаю[[#This Row],[Масса]]-Делаю[[#This Row],[Масса готов]])*100%/Делаю[[#This Row],[Масса]],"") | G6: =VLOOKUP(Делаю[[#This Row],[Название]],СводЦена!A:F,4,0) -> 0.15 | H6: =VLOOKUP(Делаю[[#This Row],[Название]],СводЦена!A:F,2,0) -> 519.33865 | I6: =VLOOKUP(Делаю[[#This Row],[Название]],СводЦена!A:F,3,0) -> 0.9 | J6: =VLOOKUP(Делаю[[#This Row],[Название]],СводЦена!A:F,6,0) -> 1160 | K6: =VLOOKUP(Делаю[[#This Row],[Название]],СводЦена!A:F,5,0) -> 545.16383 | L6: =Делаю[[#This Row],[ЧП]]*Делаю[[#This Row],[Масса готов]]/1000 -> 0 | M6: =Делаю[[#This Row],[Цена/кг]]*Делаю[[#This Row],[Масса готов]]/1000 -> 0 | O6: =VLOOKUP(Делаю[[#This Row],[Название]],Рецепты[],16,0) -> Классическая Краковская колбаса полукопченая своими руками - YouTube
A7: 45409 | B7: =VLOOKUP(Делаю[[#This Row],[Название]],Рецепты[],2,0) -> Колбаса | C7: Зельц | D7: 2000 | F7: =IF(Делаю[[#This Row],[Масса готов]]>0,(Делаю[[#This Row],[Масса]]-Делаю[[#This Row],[Масса готов]])*100%/Делаю[[#This Row],[Масса]],"") | G7: =VLOOKUP(Делаю[[#This Row],[Название]],СводЦена!A:F,4,0) -> 0.15 | H7: =VLOOKUP(Делаю[[#This Row],[Название]],СводЦена!A:F,2,0) -> 126.67814 | I7: =VLOOKUP(Делаю[[#This Row],[Название]],СводЦена!A:F,3,0) -> 0.7 | J7: =VLOOKUP(Делаю[[#This Row],[Название]],СводЦена!A:F,6,0) -> 250 | K7: =VLOOKUP(Делаю[[#This Row],[Название]],СводЦена!A:F,5,0) -> 101.02764 | L7: =Делаю[[#This Row],[ЧП]]*Делаю[[#This Row],[Масса готов]]/1000 -> 0 | M7: =Делаю[[#This Row],[Цена/кг]]*Делаю[[#This Row],[Масса готов]]/1000 -> 0 | O7: =VLOOKUP(Делаю[[#This Row],[Название]],Рецепты[],16,0) -> Немецкий холодец - Зельц. Как приготовить Зельц правильно. (youtube.com)
A8: 45412 | B8: =VLOOKUP(Делаю[[#This Row],[Название]],Рецепты[],2,0) -> Цельное | C8: Курица ГК | D8: 3326 | F8: =IF(Делаю[[#This Row],[Масса готов]]>0,(Делаю[[#This Row],[Масса]]-Делаю[[#This Row],[Масса готов]])*100%/Делаю[[#This Row],[Масса]],"") | G8: =VLOOKUP(Делаю[[#This Row],[Название]],СводЦена!A:F,4,0) -> 0.15 | H8: =VLOOKUP(Делаю[[#This Row],[Название]],СводЦена!A:F,2,0) -> 201.84115 | I8: =VLOOKUP(Делаю[[#This Row],[Название]],СводЦена!A:F,3,0) -> 0.9 | J8: =VLOOKUP(Делаю[[#This Row],[Название]],СводЦена!A:F,6,0) -> 460 | K8: =VLOOKUP(Делаю[[#This Row],[Название]],СводЦена!A:F,5,0) -> 213.42174 | L8: =Делаю[[#This Row],[ЧП]]*Делаю[[#This Row],[Масса готов]]/1000 -> 0 | M8: =Делаю[[#This Row],[Цена/кг]]*Делаю[[#This Row],[Масса готов]]/1000 -> 0 | O8: =VLOOKUP(Делаю[[#This Row],[Название]],Рецепты[],16,0) -> https://www.youtube.com/watch?v=bwqN7FZs5Ds
A9: 45412 | B9: =VLOOKUP(Делаю[[#This Row],[Название]],Рецепты[],2,0) -> Цельное | C9: Корейка ГК | D9: 1904 | F9: =IF(Делаю[[#This Row],[Масса готов]]>0,(Делаю[[#This Row],[Масса]]-Делаю[[#This Row],[Масса готов]])*100%/Делаю[[#This Row],[Масса]],"") | G9: =VLOOKUP(Делаю[[#This Row],[Название]],СводЦена!A:F,4,0) -> 0.15 | H9: =VLOOKUP(Делаю[[#This Row],[Название]],СводЦена!A:F,2,0) -> 402.32591 | I9: =VLOOKUP(Делаю[[#This Row],[Название]],СводЦена!A:F,3,0) -> 0.9 | J9: =VLOOKUP(Делаю[[#This Row],[Название]],СводЦена!A:F,6,0) -> 900 | K9: =VLOOKUP(Делаю[[#This Row],[Название]],СводЦена!A:F,5,0) -> 425.62114 | L9: =Делаю[[#This Row],[ЧП]]*Делаю[[#This Row],[Масса готов]]/1000 -> 0 | M9: =Делаю[[#This Row],[Цена/кг]]*Делаю[[#This Row],[Масса готов]]/1000 -> 0 | O9: =VLOOKUP(Делаю[[#This Row],[Название]],Рецепты[],16,0) -> Сколько соли нужно для рассола, которым шприцуют мясо. Карбонад (балык) варено-копченый. - YouTube
A10: 45430 | B10: =VLOOKUP(Делаю[[#This Row],[Название]],Рецепты[],2,0) -> Колбаса | C10: Дрогобычская | D10: 3968 | E10: 3310 | F10: =IF(Делаю[[#This Row],[Масса готов]]>0,(Делаю[[#This Row],[Масса]]-Делаю[[#This Row],[Масса готов]])*100%/Делаю[[#This Row],[Масса]],"") -> 0.16582661 | G10: =VLOOKUP(Делаю[[#This Row],[Название]],СводЦена!A:F,4,0) -> 0.15 | H10: =VLOOKUP(Делаю[[#This Row],[Название]],СводЦена!A:F,2,0) -> 411.76519 | I10: =VLOOKUP(Делаю[[#This Row],[Название]],СводЦена!A:F,3,0) -> 0.7 | J10: =VLOOKUP(Делаю[[#This Row],[Название]],СводЦена!A:F,6,0) -> 820 | K10: =VLOOKUP(Делаю[[#This Row],[Название]],СводЦена!A:F,5,0) -> 333.81799 | L10: =Делаю[[#This Row],[ЧП]]*Делаю[[#This Row],[Масса готов]]/1000 -> 1104.9375 | M10: =Делаю[[#This Row],[Цена/кг]]*Делаю[[#This Row],[Масса готов]]/1000 -> 2714.2 | O10: =VLOOKUP(Делаю[[#This Row],[Название]],Рецепты[],16,0) -> Очень вкусная домашняя колбаса - Дрогобычская. Просто, дома, своими руками - YouTube
A11: 45430 | B11: =VLOOKUP(Делаю[[#This Row],[Название]],Рецепты[],2,0) -> Сосиски | C11: Сардельки Свиные | D11: 3500 | E11: 3512 | F11: =IF(Делаю[[#This Row],[Масса готов]]>0,(Делаю[[#This Row],[Масса]]-Делаю[[#This Row],[Масса готов]])*100%/Делаю[[#This Row],[Масса]],"") -> -0.0034285714 | G11: =VLOOKUP(Делаю[[#This Row],[Название]],СводЦена!A:F,4,0) -> 0.15 | H11: =VLOOKUP(Делаю[[#This Row],[Название]],СводЦена!A:F,2,0) -> 415.32177 | I11: =VLOOKUP(Делаю[[#This Row],[Название]],СводЦена!A:F,3,0) -> 0.7 | J11: =VLOOKUP(Делаю[[#This Row],[Название]],СводЦена!A:F,6,0) -> 820 | K11: =VLOOKUP(Делаю[[#This Row],[Название]],СводЦена!A:F,5,0) -> 336.30759 | L11: =Делаю[[#This Row],[ЧП]]*Делаю[[#This Row],[Масса готов]]/1000 -> 1181.1123 | M11: =Делаю[[#This Row],[Цена/кг]]*Делаю[[#This Row],[Масса готов]]/1000 -> 2879.84 | O11: =VLOOKUP(Делаю[[#This Row],[Название]],Рецепты[],16,0) -> https://www.youtube.com/watch?v=Mu_glCpe-Y8
A12: 45430 | B12: =VLOOKUP(Делаю[[#This Row],[Название]],Рецепты[],2,0) -> Сосиски | C12: Куриные сливочные | D12: 2822 | E12: 2326 | F12: =IF(Делаю[[#This Row],[Масса готов]]>0,(Делаю[[#This Row],[Масса]]-Делаю[[#This Row],[Масса готов]])*100%/Делаю[[#This Row],[Масса]],"") -> 0.17576187 | G12: =VLOOKUP(Делаю[[#This Row],[Название]],СводЦена!A:F,4,0) -> 0.15 | H12: =VLOOKUP(Делаю[[#This Row],[Название]],СводЦена!A:F,2,0) -> 384.17357 | I12: =VLOOKUP(Делаю[[#This Row],[Название]],СводЦена!A:F,3,0) -> 0.7 | J12: =VLOOKUP(Делаю[[#This Row],[Название]],СводЦена!A:F,6,0) -> 740 | K12: =VLOOKUP(Делаю[[#This Row],[Название]],СводЦена!A:F,5,0) -> 301.18448 | L12: =Делаю[[#This Row],[ЧП]]*Делаю[[#This Row],[Масса готов]]/1000 -> 700.55509 | M12: =Делаю[[#This Row],[Цена/кг]]*Делаю[[#This Row],[Масса готов]]/1000 -> 1721.24 | O12: =VLOOKUP(Делаю[[#This Row],[Название]],Рецепты[],16,0) -> 🍗 Сосиски Сливочные Куриные 🌭🔥🥣 Делаем Дома! Просто и Вкусно! 🤤✨ (youtube.com)
A13: 45430 | B13: =VLOOKUP(Делаю[[#This Row],[Название]],Рецепты[],2,0) -> Цельное | C13: Корейка ГК | D13: 2230 | E13: 1898 | F13: =IF(Делаю[[#This Row],[Масса готов]]>0,(Делаю[[#This Row],[Масса]]-Делаю[[#This Row],[Масса готов]])*100%/Делаю[[#This Row],[Масса]],"") -> 0.14887892 | G13: =VLOOKUP(Делаю[[#This Row],[Название]],СводЦена!A:F,4,0) -> 0.15 | H13: =VLOOKUP(Делаю[[#This Row],[Название]],СводЦена!A:F,2,0) -> 402.32591 | I13: =VLOOKUP(Делаю[[#This Row],[Название]],СводЦена!A:F,3,0) -> 0.9 | J13: =VLOOKUP(Делаю[[#This Row],[Название]],СводЦена!A:F,6,0) -> 900 | K13: =VLOOKUP(Делаю[[#This Row],[Название]],СводЦена!A:F,5,0) -> 425.62114 | L13: =Делаю[[#This Row],[ЧП]]*Делаю[[#This Row],[Масса готов]]/1000 -> 807.82893 | M13: =Делаю[[#This Row],[Цена/кг]]*Делаю[[#This Row],[Масса готов]]/1000 -> 1708.2 | N13: Окорок свин | O13: =VLOOKUP(Делаю[[#This Row],[Название]],Рецепты[],16,0) -> Сколько соли нужно для рассола, которым шприцуют мясо. Карбонад (балык) варено-копченый. - YouTube
A14: 45430 | B14: =VLOOKUP(Делаю[[#This Row],[Название]],Рецепты[],2,0) -> Цельное | C14: Курица ГК | D14: 900 | E14: 647 | F14: =IF(Делаю[[#This Row],[Масса готов]]>0,(Делаю[[#This Row],[Масса]]-Делаю[[#This Row],[Масса готов]])*100%/Делаю[[#This Row],[Масса]],"") -> 0.28111111 | G14: =VLOOKUP(Делаю[[#This Row],[Название]],СводЦена!A:F,4,0) -> 0.15 | H14: =VLOOKUP(Делаю[[#This Row],[Название]],СводЦена!A:F,2,0) -> 201.84115 | I14: =VLOOKUP(Делаю[[#This Row],[Название]],СводЦена!A:F,3,0) -> 0.9 | J14: =VLOOKUP(Делаю[[#This Row],[Название]],СводЦена!A:F,6,0) -> 460 | K14: =VLOOKUP(Делаю[[#This Row],[Название]],СводЦена!A:F,5,0) -> 213.42174 | L14: =Делаю[[#This Row],[ЧП]]*Делаю[[#This Row],[Масса готов]]/1000 -> 138.08386 | M14: =Делаю[[#This Row],[Цена/кг]]*Делаю[[#This Row],[Масса готов]]/1000 -> 297.62 | N14: Крылышки | O14: =VLOOKUP(Делаю[[#This Row],[Название]],Рецепты[],16,0) -> https://www.youtube.com/watch?v=bwqN7FZs5Ds
A15: 45430 | B15: =VLOOKUP(Делаю[[#This Row],[Название]],Рецепты[],2,0) -> Цельное | C15: Курица ГК | D15: 3492 | E15: 3030 | F15: =IF(Делаю[[#This Row],[Масса готов]]>0,(Делаю[[#This Row],[Масса]]-Делаю[[#This Row],[Масса готов]])*100%/Делаю[[#This Row],[Масса]],"") -> 0.13230241 | G15: =VLOOKUP(Делаю[[#This Row],[Название]],СводЦена!A:F,4,0) -> 0.15 | H15: =VLOOKUP(Делаю[[#This Row],[Название]],СводЦена!A:F,2,0) -> 201.84115 | I15: =VLOOKUP(Делаю[[#This Row],[Название]],СводЦена!A:F,3,0) -> 0.9 | J15: =VLOOKUP(Делаю[[#This Row],[Название]],СводЦена!A:F,6,0) -> 460 | K15: =VLOOKUP(Делаю[[#This Row],[Название]],СводЦена!A:F,5,0) -> 213.42174 | L15: =Делаю[[#This Row],[ЧП]]*Делаю[[#This Row],[Масса готов]]/1000 -> 646.66787 | M15: =Делаю[[#This Row],[Цена/кг]]*Делаю[[#This Row],[Масса готов]]/1000 -> 1393.8 | N15: Грудка | O15: =VLOOKUP(Делаю[[#This Row],[Название]],Рецепты[],16,0) -> https://www.youtube.com/watch?v=bwqN7FZs5Ds
A16: 45443 | B16: =VLOOKUP(Делаю[[#This Row],[Название]],Рецепты[],2,0) -> Колбаса | C16: Краковская | D16: 2000 | E16: 2088 | F16: =IF(Делаю[[#This Row],[Масса готов]]>0,(Делаю[[#This Row],[Масса]]-Делаю[[#This Row],[Масса готов]])*100%/Делаю[[#This Row],[Масса]],"") -> -0.044 | G16: =VLOOKUP(Делаю[[#This Row],[Название]],СводЦена!A:F,4,0) -> 0.15 | H16: =VLOOKUP(Делаю[[#This Row],[Название]],СводЦена!A:F,2,0) -> 519.33865 | I16: =VLOOKUP(Делаю[[#This Row],[Название]],СводЦена!A:F,3,0) -> 0.9 | J16: =VLOOKUP(Делаю[[#This Row],[Название]],СводЦена!A:F,6,0) -> 1160 | K16: =VLOOKUP(Делаю[[#This Row],[Название]],СводЦена!A:F,5,0) -> 545.16383 | L16: =Делаю[[#This Row],[ЧП]]*Делаю[[#This Row],[Масса готов]]/1000 -> 1138.3021 | M16: =Делаю[[#This Row],[Цена/кг]]*Делаю[[#This Row],[Масса готов]]/1000 -> 2422.08 | N16: Заказала Наташа кому-то на подарок 7 колбас | O16: =VLOOKUP(Делаю[[#This Row],[Название]],Рецепты[],16,0) -> Классическая Краковская колбаса полукопченая своими руками - YouTube
A17: 45447 | B17: =VLOOKUP(Делаю[[#This Row],[Название]],Рецепты[],2,0) -> Колбаса | C17: Ветчина Мраморная | D17: 3355 | E17: 3400 | F17: =IF(Делаю[[#This Row],[Масса готов]]>0,(Делаю[[#This Row],[Масса]]-Делаю[[#This Row],[Масса готов]])*100%/Делаю[[#This Row],[Масса]],"") -> -0.013412817 | G17: =VLOOKUP(Делаю[[#This Row],[Название]],СводЦена!A:F,4,0) -> 0.15 | H17: =VLOOKUP(Делаю[[#This Row],[Название]],СводЦена!A:F,2,0) -> 398.5285 | I17: =VLOOKUP(Делаю[[#This Row],[Название]],СводЦена!A:F,3,0) -> 0.7 | J17: =VLOOKUP(Делаю[[#This Row],[Название]],СводЦена!A:F,6,0) -> 800 | K17: =VLOOKUP(Делаю[[#This Row],[Название]],СводЦена!A:F,5,0) -> 325.60707 | L17: =Делаю[[#This Row],[ЧП]]*Делаю[[#This Row],[Масса готов]]/1000 -> 1107.064 | M17: =Делаю[[#This Row],[Цена/кг]]*Делаю[[#This Row],[Масса готов]]/1000 -> 2720 | O17: =VLOOKUP(Делаю[[#This Row],[Название]],Рецепты[],16,0) -> ВЕТЧИНА МРАМОРНАЯ НАСТОЯЩАЯ в домашних условиях (youtube.com)
A18: 45509 | B18: =VLOOKUP(Делаю[[#This Row],[Название]],Рецепты[],2,0) -> Рыба | C18: Белый амур вяленый | D18: 7350 | E18: 5000 | F18: =IF(Делаю[[#This Row],[Масса готов]]>0,(Делаю[[#This Row],[Масса]]-Делаю[[#This Row],[Масса готов]])*100%/Делаю[[#This Row],[Масса]],"") -> 0.31972789 | G18: =VLOOKUP(Делаю[[#This Row],[Название]],СводЦена!A:F,4,0) -> 0.35 | H18: =VLOOKUP(Делаю[[#This Row],[Название]],СводЦена!A:F,2,0) -> 675.98431 | I18: =VLOOKUP(Делаю[[#This Row],[Название]],СводЦена!A:F,3,0) -> 2 | J18: =VLOOKUP(Делаю[[#This Row],[Название]],СводЦена!A:F,6,0) -> 3110 | K18: =VLOOKUP(Делаю[[#This Row],[Название]],СводЦена!A:F,5,0) -> 2069.9173 | L18: =Делаю[[#This Row],[ЧП]]*Делаю[[#This Row],[Масса готов]]/1000 -> 10349.587 | M18: =Делаю[[#This Row],[Цена/кг]]*Делаю[[#This Row],[Масса готов]]/1000 -> 15550 | O18: =VLOOKUP(Делаю[[#This Row],[Название]],Рецепты[],16,0) -> https://www.youtube.com/watch?v=RcLAgLhXOwU
A19: 45553 | B19: =VLOOKUP(Делаю[[#This Row],[Название]],Рецепты[],2,0) -> Цельное | C19: Шашлык свиной | D19: 1602 | F19: =IF(Делаю[[#This Row],[Масса готов]]>0,(Делаю[[#This Row],[Масса]]-Делаю[[#This Row],[Масса готов]])*100%/Делаю[[#This Row],[Масса]],"") | G19: =VLOOKUP(Делаю[[#This Row],[Название]],СводЦена!A:F,4,0) -> 0.15 | H19: =VLOOKUP(Делаю[[#This Row],[Название]],СводЦена!A:F,2,0) -> 598.80281 | I19: =VLOOKUP(Делаю[[#This Row],[Название]],СводЦена!A:F,3,0) -> 0.7 | J19: =VLOOKUP(Делаю[[#This Row],[Название]],СводЦена!A:F,6,0) -> 1200 | K19: =VLOOKUP(Делаю[[#This Row],[Название]],СводЦена!A:F,5,0) -> 490.80902 | L19: =Делаю[[#This Row],[ЧП]]*Делаю[[#This Row],[Масса готов]]/1000 -> 0 | M19: =Делаю[[#This Row],[Цена/кг]]*Делаю[[#This Row],[Масса готов]]/1000 -> 0 | O19: =VLOOKUP(Делаю[[#This Row],[Название]],Рецепты[],16,0) -> как сделать ШАШЛЫК максимально СОЧНЫМ наглядный эксперимент (youtube.com)
